Workbook

Sheet Plan1
A1: Dados base | M1: Possiveis Itens | N1: Estatísticas | AI1: Ações | AO1: Perícias
A2: Nome | B2: Anotação | C2: Descricao | D2: Aparencia | E2: Habitat | F2: Curiosidades de Astrolong TerraNova | G2: Categoria | H2: Tipo | I2: Natureza | J2: Grau de Ameaça | K2: Tamanho | L2: Comportamento | M2: Itens | N2: FOR | O2: DES | P2: VIT | Q2: INT | R2: PRE | S2: Pontos de Vida | T2: Pontos de Mana | U2: Defesa | V2: Fortitude | W2: Reflexos | X2: Vontade (Resistência) | Y2: Percepção | Z2: Iniciativa | AA2: Deslocamento | AB2: Sentidos Especiais | AC2: Resistências | AD2: Vulnerabilidades | AE2: Ataque Básico | AF2: CD Conjurador | AG2: Atributo Conjurador | AH2: Tesouro | AI2: Ação Padrão 1 | AJ2: Ação Padrão 2 | AK2: Ação de Movimento | AL2: Reação | AM2: Ação Livre | AN2: Ação Completa | AO2: Atletismo | AP2: Reflexo | AQ2: Tenacidade | AR2: Vontade | AS2: Foco | AT2: Luta | AU2: Sobrevivência
A3: Dríade das Florestas Ancestrais | B3: Poucos aventureiros encontram uma Dríade. Menos ainda percebem que foram observados por uma durante toda a viagem. — Astrolong TerraNova | C3: As Dríades das Florestas Ancestrais são criaturas humanoides compostas por madeira viva, folhas, flores e mana natural. Diferente do que muitos acreditam, elas não são espíritos nem elementais. São seres vivos pertencentes à categoria das Bestas Mágicas e possuem sociedades próprias escondidas nas profundezas das florestas élficas. Suas comunidades raramente ultrapassam algumas dezenas de indivíduos e costumam existir próximas a árvores ancestrais ou fontes naturais de mana. Embora possuam aparência delicada, as Dríades vivem por séculos e acumulam conhecimento profundo sobre a floresta. | D3: Criatura humanide que se assemelha muita a humanos e elfos, com corpos cobertos de vegetação, tem rosto simpaticos e muita belas. | E3: Reino dos Elfos, Florestas Ancestrais | F3: Muitos aventureiros descrevem as Dríades como belas. Isso é verdade. Porém, a beleza não é a característica mais impressionante delas. O que realmente chama atenção é sua capacidade de permanecer completamente imóvel por horas. Mais de uma vez passei por uma árvore para descobrir, dias depois, que ela estava me observando. | G3: Besta Mágica - Tribal | H3: Planta | I3: Arcano, Água e Terra | J3: Comum | K3: Médio | L3: Tribal, Social e Pacificos | M3: Flores de Mana Sementes Feéricas Essência Natural Frutos Ancestrais
A4: Ent Jovem | B4: Quando uma floresta deseja se defender, ela cria espinhos. Quando deseja se lembrar, cria Ents. — Astrolong TerraNova | C4: Os Ents Jovens são árvores despertas pela mana das Florestas Ancestrais. Diferente das Dríades, que possuem comunidades e cultura própria, os Ents existem como guardiões vivos da natureza. Seu corpo é formado por madeira viva extremamente resistente, coberta por musgos, flores, cipós e pequenos animais que frequentemente utilizam sua estrutura como abrigo. Embora sejam chamados de jovens, muitos já possuem mais de cinquenta anos de idade. O termo é utilizado pelos Elfos para diferenciar indivíduos que ainda não atingiram o tamanho colossal dos Ents Ancestrais. São criaturas lentas e pacientes. Um Ent pode permanecer imóvel por semanas observando uma mesma região antes de agir. | D4: Um Ent Jovem possui entre 4 e 6 metros de altura. Seu tronco lembra o de uma árvore centenária, enquanto seus braços assumem a forma de galhos robustos capazes de esmagar pedras. Seu rosto surge naturalmente na madeira, formado por rachaduras e nós que lembram olhos, nariz e boca. Durante a primavera, alguns desenvolvem flores e folhas coloridas em seus ombros e braços. | E4: Reino dos Elfos, Florestas Ancestrais | F4: Muitos aventureiros acreditam que os Ents são lentos porque são árvores. Estão enganados. Eles são lentos porque já viram séculos passarem diante de seus olhos. Para uma criatura que mede o tempo em florestas e não em anos, nós somos os apressados. | G4: Besta Mágica | H4: Planta | I4: Terra | J4: Ameaça | K4: Grande | L4: Territórialista | M4: Madeira Ancestral Seiva Encantada Núcleo de Mana Natural Sementes Primordiais
A5: Ave do Paraíso Ancestral | B5: Durante décadas acreditei que os bardos exageravam ao descrever estas aves. Descobri meu erro no momento em que vi um bando cruzar o céu ao amanhecer. Nenhuma tinta é capaz de reproduzir todas as cores que brilham em suas penas. | C5: A Ave do Paraíso Ancestral é considerada uma das criaturas mais belas de todo o Continente Ancestral. Seu canto harmonioso pode ser ouvido ao amanhecer e ao entardecer, sendo frequentemente associado a presságios de boa sorte por viajantes e habitantes das florestas. Apesar de ser conhecida como uma única espécie, estudiosos catalogaram mais de duzentas variedades diferentes espalhadas pelas florestas, pradarias e bosques do continente. Cada espécie apresenta combinações únicas de cores, padrões e formatos de penas. As Dríades acreditam que essas aves surgiram quando os primeiros ventos da criação atravessaram as florestas recém-nascidas, espalhando fragmentos de mana sobre as árvores ancestrais. São criaturas extremamente importantes para o equilíbrio natural, atuando na dispersão de sementes, pólen mágico e pequenas essências naturais entre diferentes regiões da floresta. | D5: A Ave do Paraíso Ancestral possui entre 20 e 40 centímetros de comprimento, com corpo leve e elegante adaptado ao voo ágil entre galhos e copas densas. Suas penas apresentam uma impressionante variedade de cores vibrantes, incluindo tons de azul, verde-esmeralda, dourado, violeta, vermelho-rubi e branco-perolado. Algumas espécies possuem caudas longas que podem atingir três vezes o comprimento do corpo. Quando expostas à luz do sol ou à mana ambiente, certas penas produzem reflexos iridescentes que mudam constantemente de cor, criando um espetáculo visual difícil de descrever. Os machos geralmente apresentam plumagens mais extravagantes, enquanto as fêmeas possuem padrões mais discretos, porém igualmente belos. Diversas espécies desenvolvem pequenas cristas, leques de penas ou caudas ornamentais utilizadas durante elaborados rituais de acasalamento que transformam clareiras inteiras em verdadeiros espetáculos naturais. | E5: Reino dos Elfos, Terras dos Faunos e Florestas Ancestrais | F5: A maioria dos aventureiros observa apenas a plumagem dessas aves. Eu prefiro observar os outros animais ao seu redor. Em mais de uma ocasião, encontrei predadores descansando próximos a um bando de Aves do Paraíso Ancestrais sem demonstrar qualquer intenção de caça. Não compreendo completamente o motivo, mas suspeito que a mana presente em suas penas produza uma sensação de tranquilidade nas criaturas ao redor. | G5: Besta Mágica | H5: Ave | I5: Vento | J5: Inofensivo | K5: Pequeno | L5: Pacífico e Sociável | M5: Pena Arcoiris
A6: MegaMutty | B6: Quando vi um pela primeira vez à distância, pensei estar observando uma colina ambulante. Somente após me aproximar percebi que se tratava de uma criatura viva. O mais curioso foi descobrir que a enorme besta que poderia facilmente me esmagar estava mais interessada em comer frutas do que em me atacar. — Astrolong TerraNova | C6: Os MegaMuttys são grandes mamíferos mágicos conhecidos por sua natureza dócil e comportamento altamente social. Vivem em pequenos grupos familiares que podem variar entre seis e vinte indivíduos, percorrendo extensas áreas de floresta e pradarias em busca de alimento. Apesar de sua aparência intimidadora e enorme força física, raramente demonstram agressividade contra outras criaturas. A maioria dos conflitos envolvendo MegaMuttys ocorre durante a estação de acasalamento ou quando um filhote é ameaçado. São considerados uma das espécies mais importantes da região, pois ajudam a moldar o ambiente por onde passam. Ao derrubarem árvores antigas, abrirem trilhas naturais e espalharem sementes durante suas migrações, contribuem diretamente para a renovação das florestas. Muitos Faunos os consideram símbolos de prosperidade, enquanto alguns Elfos os enxergam como guardiões silenciosos das fronteiras naturais entre os bosques e as pradarias. | D6: Um MegaMutty adulto possui entre três e quatro metros de altura quando apoiado sobre as quatro patas e pode ultrapassar oito metros de comprimento. Seu corpo é robusto e extremamente musculoso, sustentado por patas grossas adaptadas para longas caminhadas e investidas devastadoras. Sua anatomia lembra a de um enorme mamífero quadrúpede coberto por uma espessa camada de pelos marrons, cinzentos e negros que o protege das mudanças climáticas. A cabeça apresenta um focinho alongado e poderoso, enquanto suas presas curvas crescem para frente, sendo utilizadas para escavar raízes, derrubar árvores e disputar parceiros durante a época reprodutiva. Os indivíduos mais velhos costumam desenvolver camadas ainda mais densas de pelos, frequentemente cobertas por musgos, flores e pequenos insetos que passam a viver em simbiose com a criatura. | E6: Fronteiras entre o Reino dos Elfos e as Terras dos Faunos | F6: A maioria dos aventureiros acredita que os MegaMuttys são perigosos por causa do tamanho. Na realidade, são perigosos por causa da velocidade. Poucos esperam que uma criatura tão grande consiga atravessar uma clareira inteira em poucos segundos. Os filhotes permanecem próximos da mãe por quase cinco anos. Durante esse período, qualquer criatura que se aproxime demais será tratada como uma ameaça, independentemente de suas intenções. Em uma ocasião observei um grupo de Dríades utilizando um MegaMutty adormecido como ponto de encontro. A criatura sequer pareceu se importar quando acordou cercada por elas. As trilhas abertas pelos rebanhos mais antigos são tão utilizadas por outras criaturas que alguns mapas élficos as registram como rotas permanentes de viagem. Jamais confunda um MegaMutty relaxado com um MegaMutty amigável. Eles são pacíficos, mas continuam sendo criaturas capazes de derrubar uma árvore centenária com uma única investida. | G6: Besta Mágica | H6: Besta | I6: Terra | J6: Comum | K6: Grande | L6: Social e Pacífico (Territorial durante o acasalamento e proteção dos filhotes) | M6: Presas de MegaMutty Couro Espesso de MegaMutty Pelagem Gigante Osso Reforçado Glândula de Resistência Natural Musgos Simbióticos Crescidos na Pelagem Fragmentos de Mana Natural
A7: Pantera Felina Negra | B7: A maioria dos viajantes acredita que a escuridão da Floresta Negra esconde monstros. Estão parcialmente corretos. O verdadeiro problema é que algumas criaturas se tornaram tão adaptadas à escuridão que a própria floresta parece conspirar para ocultá-las. Nenhuma representa melhor isso do que a Pantera Felina Negra. — Astrolong TerraNova | C7: A Pantera Felina Negra é uma das cinco espécies conhecidas de Panteras Felinas. Embora compartilhem a característica comum de possuir dois pares de pernas dianteiras e um par de pernas traseiras, esta espécie se destaca por sua extraordinária adaptação à vida noturna. Habitando as regiões mais profundas da Floresta Negra, esses predadores raramente são vistos durante o dia. Preferem caçar sob a cobertura da noite, utilizando a vegetação densa e as sombras naturais para se aproximarem de suas presas sem serem percebidos. Sua dieta é composta principalmente por cervos, javalis, pequenos monstros da floresta e, ocasionalmente, criaturas mágicas menores. Ataques contra humanoides são raros e geralmente ocorrem apenas quando o animal se sente encurralado ou quando seu território é invadido repetidamente. Apesar da reputação assustadora, a Pantera Felina Negra desempenha um papel fundamental no equilíbrio ecológico da Floresta Negra, controlando populações de criaturas menores e eliminando indivíduos doentes ou enfraquecidos. | D7: Uma Pantera Felina Negra adulta possui aproximadamente 300 quilos de massa corporal e pode atingir mais de quatro metros de comprimento da cabeça até a ponta da cauda. Seu corpo musculoso é sustentado por seis patas poderosas: quatro dianteiras e duas traseiras. Essa anatomia incomum proporciona estabilidade excepcional durante corridas, saltos e emboscadas. Toda sua pelagem é composta por pelos negros extremamente densos, capazes de absorver grande parte da luz ambiente. Sob certas condições, a criatura parece se fundir completamente às sombras da floresta. Seus olhos brilham em tons de verde-esmeralda ou dourado intenso durante a noite, sendo muitas vezes a única parte visível do animal quando está observando uma presa. A cauda longa auxilia no equilíbrio durante perseguições e saltos entre raízes, rochas e troncos caídos. | E7: Floresta Negra | F7: Em vinte e três anos explorando a Floresta Negra, encontrei rastros de Panteras Felinas Negras centenas de vezes. Vi uma delas apenas quatro. Seu corpo produz tão pouco ruído durante a movimentação que alguns caçadores acreditam que a criatura utiliza magia para silenciar seus passos. Até o momento não encontrei evidências que comprovem essa teoria. Os filhotes nascem com manchas cinzentas espalhadas pela pelagem. Essas marcas desaparecem completamente antes de atingirem a idade adulta. É comum encontrar cervos e outras presas vivendo relativamente próximos do território de uma Pantera Felina Negra. Diferente de muitos predadores, elas raramente matam mais do que o necessário para se alimentar. A primeira vez que percebi estar sendo seguido por uma dessas criaturas foi ao notar que os pássaros haviam parado de cantar. A segunda vez, percebi tarde demais. | G7: Besta Mágica | H7: Felina | I7: Terra e Vento | J7: Ameaça | K7: Grande | L7: Solitário, Territorial e Predador Noturno | M7: Presas de Pantera Negra Garras Sombrias Couro Negro Reforçado Pelagem Noturna Olhos Cristalizados de Pantera Bigodes Sensoriais Glândula de Caça Noturna Essência Predatória
A8: Pantera Felina Marrom | B8: Diferente de sua prima da Floresta Negra, a Pantera Felina Marrom não se esconde nas sombras. Ela prefere observar o mundo sob a luz do sol, descansando sobre rochedos elevados ou galhos robustos enquanto vigia seu território. Muitos viajantes sequer percebem que estão sendo observados até que a criatura decida partir. — Astrolong TerraNova | C8: A Pantera Felina Marrom é uma das espécies mais comuns entre os grandes felinos de seis patas encontrados no Continente Ancestral. Habita principalmente encostas montanhosas, florestas elevadas e regiões de transição entre os bosques élficos e as montanhas anãs. Embora seja um predador eficiente, raramente demonstra agressividade gratuita. Sua estratégia de caça baseia-se em paciência, observação e emboscadas rápidas, utilizando a vegetação e os desníveis do terreno para se aproximar das presas. Sua dieta é composta principalmente por cervos, cabras-montesas, javalis, aves de grande porte e outras criaturas de médio porte. Em regiões montanhosas, são frequentemente vistas caçando ao longo de penhascos e trilhas estreitas. Anões costumam respeitar essas criaturas, considerando-as símbolos de força e independência. Já os Elfos as enxergam como importantes guardiãs naturais das fronteiras selvagens. | D8: Uma Pantera Felina Marrom adulta pesa aproximadamente 150 quilos e mede entre três e quatro metros de comprimento. Seu corpo apresenta a característica típica das Panteras Felinas: dois pares de patas dianteiras e um par de patas traseiras. Essa anatomia proporciona equilíbrio excepcional durante escaladas, perseguições e saltos entre rochas. A pelagem varia entre diferentes tons de marrom, castanho, cobre e bege, permitindo excelente camuflagem em montanhas, bosques secos e regiões rochosas. Sua musculatura é mais compacta e ágil que a da Pantera Felina Negra, sendo adaptada para terrenos acidentados. A longa cauda auxilia no equilíbrio durante deslocamentos sobre penhascos e galhos elevados. Os olhos costumam apresentar coloração âmbar, dourada ou cobre, refletindo intensamente a luz solar. As quatro patas dianteiras terminam em garras retráteis extremamente afiadas, capazes de se fixar em superfícies rochosas quase verticais. | E8: Reino dos Anões e Reino dos Elfos | F8: Se uma Pantera Felina Negra é um fantasma da noite, a Pantera Felina Marrom é uma rainha das montanhas. Durante minhas expedições ao Reino dos Anões observei diversas vezes indivíduos descansando sobre formações rochosas tão altas que pareciam impossíveis de alcançar. Ainda hoje não compreendo completamente como conseguem subir até alguns daqueles locais. Filhotes costumam brincar simulando caçadas entre si. Curiosamente, utilizam as quatro patas dianteiras para imobilizar os irmãos enquanto praticam mordidas controladas. Muitos caçadores acreditam que a espécie possui um senso de direção sobrenatural. Diversos indivíduos marcados por estudiosos foram observados retornando exatamente ao mesmo território anos depois. Embora sejam predadores temidos, são conhecidos por evitar confrontos desnecessários. Em mais de uma ocasião observei uma Pantera Felina Marrom abandonar uma caça ao perceber a presença de filhotes de outra espécie nas proximidades. | G8: Besta Mágica | H8: Felina | I8: Terra | J8: Menor | K8: Grande | L8: Solitário, Territorial e Predador Diurno | M8: Garras de Pantera Marrom Presas Serrilhadas Couro Montanhês Pelagem Castanha Bigodes Sensoriais Olhos Âmbar Cristalizados Glândula de Equilíbrio Essência de Predador Alpino
A9: Pantera Felina Real | B9: Entre todas as Panteras Felinas que cataloguei, nenhuma demonstra tanta nobreza quanto a Pantera Felina Real. Elas caminham pelas pradarias e florestas como verdadeiros reis da natureza. Curiosamente, já encontrei indivíduos que toleraram minha presença por dias inteiros, observando-me com a mesma curiosidade que eu observava a eles. — Astrolong TerraNova | C9: A Pantera Felina Real é considerada a mais majestosa das cinco espécies conhecidas de Panteras Felinas. Diferente de suas parentes mais solitárias, vivem em grupos familiares organizados chamados de bandos reais. Esses grupos normalmente são liderados por um macho dominante, acompanhado por diversas fêmeas adultas, filhotes e jovens em treinamento. São criaturas naturalmente pacíficas e costumam ignorar viajantes, aventureiros e até outras espécies, desde que não representem ameaça ao grupo. Durante a época de reprodução, entretanto, seu comportamento muda drasticamente. Machos disputam território e direito de acasalamento através de confrontos violentos que podem durar horas. Nesse período tornam-se extremamente agressivos e perigosos. As fêmeas também demonstram feroz instinto protetor quando possuem filhotes recém-nascidos, atacando imediatamente qualquer criatura que se aproxime demais. Apesar disso, fora dessas situações, são consideradas uma das grandes maravilhas vivas do Continente Ancestral. | D9: Uma Pantera Felina Real adulta pode atingir cerca de 450 quilos e ultrapassar cinco metros de comprimento da cabeça até a ponta da cauda. Como todas as Panteras Felinas, possui dois pares de patas dianteiras e um único par de patas traseiras, característica que lhe proporciona estabilidade extraordinária durante corridas, saltos e combates. Sua pelagem varia entre tons dourados, laranja intenso e cobre brilhante. Sob a luz do sol, seus pelos parecem refletir a própria luz, produzindo um brilho majestoso visível a grandes distâncias. Os machos desenvolvem uma exuberante juba dourada que cresce ao redor do pescoço, peito e ombros. Quanto mais velho e dominante o indivíduo, maior tende a ser sua juba. Seus olhos costumam apresentar coloração âmbar, dourada ou alaranjada, transmitindo uma expressão de inteligência, confiança e serenidade. Sua musculatura é impressionante, combinando força bruta com elegância e agilidade raramente vistas em criaturas de seu porte. | E9: Terras dos Faunos e Reino dos Elfos | F9: Já observei grupos de Faunos caminhando ao lado de Panteras Felinas Reais sem qualquer demonstração de medo. Nenhuma das partes parecia considerar a outra uma ameaça. Filhotes são criados coletivamente por todas as fêmeas do grupo. Em alguns casos, uma única ninhada pode receber cuidados de cinco ou seis mães diferentes. Os rugidos dos machos podem ser ouvidos a quilômetros de distância durante a estação de reprodução. O som ecoa pelas pradarias como um trovão distante. Ao contrário do que muitos acreditam, a juba não serve apenas para impressionar parceiros. Ela também protege regiões vitais do pescoço durante disputas territoriais. Entre os Faunos existe a crença de que encontrar uma Pantera Felina Real descansando tranquilamente durante uma viagem é um presságio de boa sorte e prosperidade. | G9: Besta Mágica | H9: Felina | I9: Terra e Trovão | J9: Ameaça | K9: Grande | L9: Social, Familiar e Territorial durante reprodução ou proteção dos filhotes | M9: Juba Dourada de Pantera Real Garras Reais Presas Majestosas Couro Real Olhos Âmbar Cristalizados Bigodes Sensoriais Glândula de Vitalidade Essência do Guardião da Pradaria
A10: Pantera Felina dos Riachos Albina | B10: Poucas criaturas conseguem transmitir beleza e perigo na mesma medida. A Pantera dos Riachos Albina parece uma escultura viva de gelo e neve quando observada à distância. Muitos exploradores ficam fascinados por sua aparência majestosa. Os mais imprudentes raramente têm uma segunda oportunidade para admirar sua beleza. — Astrolong TerraNova | C10: A Pantera Felina dos Riachos Albina é uma variante rara das Panteras Felinas adaptada às regiões geladas do extremo norte. Considerada uma das mais eficientes predadoras do Continente Ancestral, desenvolveu habilidades extraordinárias para caça tanto em terra quanto na água. Embora possa perseguir presas sobre a neve, escalar encostas e atravessar terrenos congelados com facilidade, seu verdadeiro domínio encontra-se nos rios, lagos e canais subterrâneos das Terras do Norte Gelado. Essas criaturas são capazes de permanecer submersas por longos períodos, utilizando sua excepcional capacidade pulmonar e controle corporal para se aproximar silenciosamente das presas. Peixes gigantes, focas glaciais, cervos do norte e até jovens gigantes podem se tornar alvos de uma Pantera dos Riachos adulta. Apesar de serem predadoras extremamente eficientes, raramente desperdiçam energia em conflitos desnecessários. | D10: Uma Pantera Felina dos Riachos Albina adulta pode ultrapassar os 250 quilos e atingir mais de quatro metros de comprimento. Seu corpo possui a anatomia característica das Panteras Felinas, com dois pares de patas dianteiras e um único par de patas traseiras. Sua pelagem é completamente branca, variando entre tons de neve, marfim e prata clara. Em alguns indivíduos, manchas extremamente sutis podem ser observadas sob determinadas condições de iluminação. Os olhos costumam apresentar coloração azul-glacial, violeta pálido ou vermelho-rubi, características comuns do albinismo presente na espécie. Sua musculatura é compacta e poderosa, especialmente na região dos ombros e das patas dianteiras, permitindo explosões repentinas de velocidade tanto na água quanto em terra firme. As patas possuem membranas discretas entre os dedos que aumentam significativamente sua eficiência durante a natação. Observação Anatômica As patas dianteiras menores possuem articulações especiais que permitem recolher completamente as garras e dobrar parte da estrutura óssea atrás do par principal de patas dianteiras. Essa adaptação faz com que muitos observadores acreditem estar diante de uma criatura de quatro patas até o momento do ataque. Quando necessário, essas patas ocultas são utilizadas para desferir golpes inesperados, agarrar presas ou aumentar drasticamente sua capacidade de escalada e natação. | E10: Terras do Norte Gelado, rios congelados, lagos glaciais, vales nevados e encostas montanhosas | F10: Já observei uma Pantera dos Riachos permanecer imóvel sob uma camada de gelo por quase uma hora inteira aguardando o momento ideal para atacar. Os habitantes das Terras Geladas costumam chamá-las de Fantasmas Brancos dos Rios, pois muitas vezes a única coisa visível é o reflexo de seus olhos sob a água. Durante uma expedição, testemunhei uma dessas criaturas capturar um peixe quase do mesmo tamanho que seu próprio corpo. A luta durou menos de trinta segundos. Poucos aventureiros sabem da existência de suas patas ocultas. Mais de um caçador experiente foi surpreendido ao descobrir que a criatura possuía muito mais alcance e controle do que aparentava. Embora sejam predadoras formidáveis, as mães demonstram cuidado extraordinário com seus filhotes. Já vi uma delas atravessar um rio parcialmente congelado diversas vezes para transportar seus jovens em segurança. Entre os povos do norte existe uma antiga crença de que avistar uma Pantera dos Riachos Albina nadando contra a corrente significa que uma grande mudança está prestes a acontecer. | G10: Besta Mágica | H10: Felina | I10: Terra e Água | J10: Elite | K10: Grande | L10: Solitária ou Familiar, Territorial, Predadora Aquática | M10: Pelagem Glacial Albina Garras Ocultas dos Riachos Presas do Caçador Ártico Couro Impermeável Superior Bigodes Sensoriais Aquáticos Olhos Cristalinos Glaciais Membranas Natatórias Glândula de Respiração Prolongada Essência da Caçadora dos Rios Gelados
A11: Pantera Felina das Areias | B11: Se a Pantera Felina Negra é a sombra e a Pantera Felina dos Riachos é a água, então a Pantera Felina das Areias é o próprio vento. Já observei uma delas desaparecer no horizonte mais rápido do que um cavalo em disparada. Felizmente para os aventureiros, elas preferem fugir de problemas em vez de procurá-los. — Astrolong TerraNova | C11: A Pantera Felina das Areias é considerada a mais veloz entre todas as espécies conhecidas de Panteras Felinas. Adaptada aos terrenos áridos, pradarias secas e regiões de vegetação escassa das Terras Devastadas, desenvolveu um corpo extremamente leve e eficiente. Diferente de suas parentes maiores e mais agressivas, esta espécie evita conflitos sempre que possível. Seu primeiro instinto diante de qualquer ameaça é a fuga, utilizando sua velocidade extraordinária para escapar antes mesmo que um confronto aconteça. Sua dieta é composta principalmente por pequenos mamíferos, répteis, aves terrestres e criaturas de médio porte. Apesar de ser uma caçadora eficiente, raramente enfrenta presas muito maiores que ela. Durante a época de reprodução, entretanto, seu comportamento muda drasticamente. Machos tornam-se extremamente competitivos e disputam territórios através de corridas, demonstrações de velocidade e confrontos rápidos, porém violentos. Por sua natureza cautelosa, muitos estudiosos acreditam que existam mais Panteras das Areias do que os registros indicam, já que poucas pessoas conseguem observá-las por tempo suficiente para estudá-las adequadamente. | D11: Uma Pantera Felina das Areias adulta pesa cerca de 100 quilos, embora indivíduos excepcionais possam ultrapassar os 120 quilos. Seu corpo apresenta a anatomia característica das Panteras Felinas, com dois pares de patas dianteiras e um par de patas traseiras. Entre todas as espécies, possui a estrutura corporal mais esguia e aerodinâmica. A pelagem combina tons de amarelo dourado, laranja queimado, vermelho-terra e manchas escuras espalhadas pelo corpo. Sua musculatura é seca e alongada, construída para velocidade em vez de força bruta. As pernas longas permitem passadas impressionantes, enquanto a cauda comprida atua como leme durante curvas realizadas em alta velocidade. Os olhos geralmente apresentam coloração âmbar, dourada ou cobre intenso, adaptados para detectar movimentos a grandes distâncias. Em disparada máxima, uma Pantera Felina das Areias pode ultrapassar os 120 quilômetros por hora durante curtas distâncias, tornando-a uma das criaturas terrestres mais rápidas já catalogadas por Astrolong TerraNova. | E11: Terras Devastadas, fronteiras da Floresta dos Orcs, arredores da Floresta Negra e ocasionalmente as Terras dos Gigantes | F11: A maioria dos predadores foge quando está ferida. A Pantera das Areias foge quando está saudável. Já acompanhei um indivíduo por quase três dias antes que ele finalmente permitisse que eu me aproximasse o suficiente para observá-lo adequadamente. Os filhotes passam boa parte da infância disputando corridas entre si. A velocidade parece ser tão importante para sua sociedade quanto a força é para outras espécies. Durante uma tempestade de areia, observei uma dessas criaturas utilizar as próprias dunas como cobertura, movendo-se de forma tão eficiente que parecia desaparecer entre os grãos de areia. Embora possam alcançar velocidades impressionantes, raramente mantêm uma perseguição longa. Seu método de caça consiste em explosões repentinas de velocidade seguidas de ataques extremamente precisos. Entre os Orcs existe a crença de que capturar uma Pantera das Areias é impossível. Após muitos anos estudando a espécie, acredito que talvez estejam certos. | G11: Besta Mágica | H11: Felina | I11: Terra e Vento | J11: Ameaça | K11: Elite | L11: Arisco, Medroso, Territorial durante o período reprodutivo | M11: Couro das Areias Garras de Velocidade Presas Serrilhadas Bigodes Sensoriais Tendões Elásticos Olhos de Caçador do Deserto Essência da Rapidez Pelagem Escarlate
A12: Urso de Pijama Listrado | B12: A primeira vez que encontrei um Urso de Pijama Listrado, pensei estar observando uma criatura lenta e pesada descansando à margem de um lago. Instantes depois, vi a besta atravessar dezenas de metros de água em poucos segundos e arrancar um Peixe Gigante Vermelho do rio com uma única investida. Nunca mais subestimei sua velocidade. — Astrolong TerraNova | C12: O Urso de Pijama Listrado é uma das maiores bestas terrestres conhecidas do mundo. Habitando regiões frias e montanhosas próximas às Terras dos Gigantes e às Ilhas dos Dragões, tornou-se um dos predadores mais respeitados desses territórios. Apesar de seu tamanho colossal, raramente entra em conflito com outras criaturas. Prefere patrulhar sozinho vastas extensões de território, visitando regularmente rios e lagos onde caça sua presa favorita: os Peixes Gigantes Vermelhos. Sua técnica de caça é simples, mas devastadora. Permanecendo imóvel próximo à água, aguarda pacientemente o momento exato para atacar. Quando a presa se aproxima, avança com velocidade surpreendente, utilizando seus enormes membros dianteiros para capturá-la. Uma vez agarrada, escapar torna-se praticamente impossível. O abraço do Urso de Pijama Listrado é conhecido entre os caçadores como o Abraço do Penhasco, pois poucos seres possuem força suficiente para romper sua imobilização. | D12: O Urso de Pijama Listrado pode ultrapassar os 800 quilos e atingir mais de quatro metros de altura quando se ergue sobre as patas traseiras. Seu corpo é coberto por uma espessa pelagem listrada composta por faixas negras, cinzentas, castanhas e douradas. Os padrões são únicos para cada indivíduo e lembram as sombras projetadas pelas montanhas ao amanhecer. Sua anatomia é extremamente incomum. As patas dianteiras são significativamente maiores que as traseiras, formando ombros largos e musculosos capazes de mover pedras e derrubar árvores jovens. As garras dianteiras podem atingir quase meio metro de comprimento em indivíduos mais velhos, sendo utilizadas tanto para escavar quanto para capturar presas. Quando ataca, o Urso utiliza os braços para envolver completamente o alvo. Nesse momento, suas patas traseiras entram em ação, prendendo a vítima contra seu corpo enquanto as enormes garras impedem qualquer tentativa de fuga. A combinação entre força, peso e alcance faz com que poucas criaturas consigam escapar após serem capturadas. Sua cabeça apresenta focinho largo, mandíbulas poderosas e olhos pequenos, porém extremamente atentos. | E12: Terras dos Gigantes, Ilhas dos Dragões, costas geladas, grandes rios, lagos profundos e regiões montanhosas próximas ao mar | F12: Apesar de sua aparência feroz, os Urso de Pijama Listrado passam boa parte do dia descansando próximo a rios e lagos. Já encontrei indivíduos observando cardumes por horas antes de realizar um único ataque. Sua paciência rivaliza com a dos melhores caçadores. Muitos aventureiros acreditam que suas patas dianteiras servem apenas para combate. Na verdade, são ferramentas incrivelmente versáteis, utilizadas para escavar, nadar, escalar e até mover obstáculos enormes. Os Gigantes costumam respeitar essas criaturas. Em algumas regiões, matar um Urso de Pijama Listrado sem necessidade é considerado um ato de extrema desonra. Poucas criaturas conseguem enfrentar um adulto saudável. Mesmo dragões jovens evitam conflitos desnecessários com eles. Durante minhas viagens, encontrei marcas de garras gravadas em rochas sólidas por indivíduos que provavelmente viveram há séculos. | G12: Besta Mágica | H12: Besta | I12: Terra | J12: Elite | K12: Enorme | L12: Solitário, Territorial e Predador de Emboscada | M12: Tesouros Pelagem Listrada Gigante Garras do Abraço Implacável Presas Quebra-Ossos Couro Reforçado de Montanha Ossos de Predador Colossal Óleo de Glândulas Naturais Coração de Caçador Solitário Essência da Força Selvagem
A13: Urso-Baleia Branco | B13: Nenhuma criatura me ensinou mais sobre aparências enganosas do que o Urso-Baleia Branco. Seu rosto transmite uma expressão quase amigável, como se estivesse constantemente satisfeito com a vida. Infelizmente, ele também considera quase tudo que encontra uma possível refeição. — Astrolong TerraNova | C13: O Urso-Baleia Branco é o maior entre todas as espécies de ursos conhecidas do mundo. Habitando regiões geladas onde terra, gelo e oceano se encontram, tornou-se o predador dominante de inúmeras costas congeladas. Diferente de outros grandes predadores que dependem de velocidade ou emboscadas elaboradas, o Urso-Baleia Branco utiliza uma estratégia que muitos aventureiros descrevem como perturbadora. Ele simplesmente se aproxima. Sem demonstrar pressa, sem rugidos e sem qualquer sinal de agressividade aparente, a criatura avança lentamente em direção ao alvo. Muitos viajantes inexperientes interpretam esse comportamento como curiosidade ou desinteresse. Quando a distância se torna pequena o suficiente, o ataque acontece. Sua explosão repentina de velocidade é tão inesperada que poucas criaturas conseguem reagir a tempo. Embora seja perfeitamente capaz de viver em terra firme, passa grande parte da vida no oceano, onde caça peixes gigantes, focas glaciais, monstros marinhos e praticamente qualquer criatura que considere vulnerável. No mar, poucos predadores rivalizam com sua eficiência. | D13: Um Urso-Baleia Branco adulto pode ultrapassar duas toneladas de peso e atingir mais de cinco metros de comprimento. Seu corpo combina características adaptadas tanto para ambientes terrestres quanto aquáticos. A estrutura é massiva, com musculatura densa escondida sob uma camada espessa de gordura isolante. Sua pelagem é predominantemente branca, porém marcada por grandes manchas negras ou cinza-escuras distribuídas pelo dorso, laterais e cabeça. A cabeça é arredondada e larga, com olhos pequenos e expressivos que frequentemente produzem uma aparência curiosamente amigável. O formato natural de sua mandíbula cria uma impressão constante de sorriso, característica responsável por inúmeros acidentes envolvendo exploradores que subestimaram a criatura. As patas são largas e poderosas, adaptadas para caminhar sobre neve profunda, gelo instável e também para impulsionar o animal durante a natação. Debaixo d'água sua coloração branca e negra se mistura aos reflexos do gelo e às sombras profundas dos mares glaciais, tornando-o surpreendentemente difícil de detectar. Quando observado do fundo para a superfície, muitas vezes parece apenas mais uma formação de gelo flutuante. Até que se mova. | E13: Terras do Norte Gelado, Terras dos Gigantes, mares glaciais, fiordes congelados e costas árticas | F13: Se existe uma criatura capaz de parecer feliz enquanto planeja devorá-lo, é o Urso-Baleia Branco. Já testemunhei um indivíduo nadando sob uma camada de gelo tão espessa que eu sequer percebi sua presença até vê-lo emergir poucos metros adiante. A maioria dos ataques ocorre porque as vítimas acreditam que a criatura está apenas passando. Na realidade, ela já tomou sua decisão há muito tempo. Filhotes são surpreendentemente brincalhões e passam horas deslizando sobre encostas congeladas. Essa diversão frequentemente termina com alguma criatura menor sendo acidentalmente esmagada. Os Gigantes do Norte respeitam profundamente essas criaturas e costumam evitar caçá-las, exceto em situações extremas. Ao contrário da maioria dos predadores, eles não parecem sentir necessidade de demonstrar dominância. Simplesmente agem como se já fossem os donos do território. Em águas profundas, sua silhueta desaparece quase completamente. Mais de um marinheiro jurou que o mar simplesmente abriu uma boca e engoliu sua embarcação. | G13: Besta Mágica | H13: Besta | I13: Terra e Água | J13: Elite | K13: Enorme | L13: Territorial, Agressivo e Predador Semimarinho | M13: Pelagem Glacial Colossal Dentes de Quebra-Gelo Garras Oceânicas Couro Marinho Reforçado Gordura Alquímica Glacial Óleo de Respiração Profunda Ossos de Titã Polar Coração do Predador dos Mares Gelados Essência da Maré Congelante
A14: Urso Anão Marrom | B14: Entre todos os ursos que cataloguei, este é certamente o mais preguiçoso. Já encontrei um indivíduo dormindo no mesmo tronco durante três dias consecutivos. No quarto dia, ele apenas mudou de lado e continuou dormindo. — Astrolong TerraNova | C14: O Urso Anão Marrom é a menor espécie conhecida entre os ursos do mundo, embora seu conceito de pequeno ainda seja consideravelmente maior que o de muitas outras criaturas. Extremamente dóceis quando bem tratados, tornaram-se uma das poucas Bestas Mágicas que podem conviver pacificamente com povos civilizados. Em algumas regiões do Continente Ancestral, especialmente entre Faunos e comunidades élficas mais isoladas, é comum encontrar indivíduos criados desde filhotes como companheiros e animais de guarda. Apesar de sua aparência amigável, continuam sendo criaturas fortes e resistentes. Quando ameaçados, podem utilizar sua poderosa musculatura para afastar predadores ou proteger seus cuidadores. Sua rotina diária consiste principalmente em comer, descansar e procurar novos locais confortáveis para dormir. Muitos indivíduos passam mais da metade da vida descansando. | D14: Um Urso Anão Marrom adulto pesa aproximadamente 200 quilos e possui altura semelhante à de um humanoide adulto quando apoiado sobre as quatro patas. Seu corpo é compacto e robusto, coberto por uma espessa pelagem marrom que varia entre tons castanhos claros e escuros. Possui patas largas adaptadas para caminhar por florestas densas, troncos caídos e terrenos irregulares. Sua cabeça é arredondada, com orelhas pequenas, focinho curto e olhos expressivos que frequentemente transmitem uma aparência tranquila e curiosa. Diferente das demais espécies de ursos, sua constituição corporal favorece conforto e resistência ao invés de velocidade ou agressividade. É comum encontrar folhas, flores e pequenos galhos presos à sua pelagem após longos períodos de sono em clareiras ou bosques. Quando descansando, costuma enrolar-se como uma enorme bola de pelos, tornando difícil distinguir a criatura de um monte de folhas secas à distância. | E14: Pacífico, Sonolento e Sociável | F14: Se a preguiça fosse uma forma de magia, os Ursos Anões Marrons seriam arquimagos. Muitos aventureiros confundem indivíduos adormecidos com pedras cobertas por musgo. Alguns aprendem o erro da maneira mais constrangedora possível quando a 'pedra' começa a roncar. Os filhotes desenvolvem forte apego a criaturas que os alimentam regularmente. Já conheci um que seguiu um ferreiro anão por quase dois meses inteiros. Apesar de sua natureza tranquila, jamais tente acordar um Urso Anão Marrom tocando seu alimento. Alguns instintos permanecem fortes independentemente da personalidade da criatura. As Dríades gostam particularmente da companhia desses animais. Dizem que seu ronco ajuda as árvores jovens a crescerem mais saudáveis. Até hoje não encontrei evidências que comprovem essa teoria. Uma vez observei um indivíduo dormir durante uma tempestade inteira. A chuva parou antes que ele acordasse. | G14: Besta Mágica | H14: Besta | I14: Terra | J14: Comum | K14: Médio | L14: Reino dos Elfos, Terras dos Faunos e florestas temperadas do Continente Ancestral | M14: Tesouros Pelagem Marrom Macia Garras de Escavação Couro Flexível Almofadas Plantares Resistentes Presas de Urso Anão Mel Selvagem Armazenado na Pelagem Essência da Tranquilidade Coração de Guardião da Floresta
... A66: Salamandra das Chamas | B66: "Pequena, adorável e quente o suficiente para transformar uma fogueira em algo desnecessário. A Salamandra das Chamas é uma das poucas criaturas elementais que consegue conquistar o coração de aventureiros sem tentar devorá-los primeiro." — Astrolong TerraNova | C66: As Salamandras das Chamas são pequenos espíritos elementais ligados ao fogo natural do mundo. Apesar de sua origem mágica, raramente representam perigo para outras criaturas. São conhecidas por sua personalidade curiosa e comportamento amigável, aproximando-se frequentemente de acampamentos, forjas e lareiras para observar atividades mortais. Alimentam-se de calor, brasas, energia elemental e pequenas quantidades de mana de fogo presentes no ambiente. Quando felizes, produzem pequenas faíscas que dançam ao seu redor. Embora sejam dóceis, podem tornar-se defensivas caso sejam capturadas ou maltratadas. | D66: Uma Salamandra das Chamas mede entre quinze e trinta centímetros de comprimento. Seu corpo lembra um pequeno anfíbio de formas arredondadas, com grandes olhos brilhantes e expressão constantemente curiosa. Sua pele varia entre vermelho, laranja, dourado e amarelo intenso, emitindo um brilho suave semelhante ao de brasas vivas. Pequenas chamas dançam sobre sua cabeça, costas e cauda sem consumir seu corpo. Quando animadas, essas chamas aumentam de intensidade; quando assustadas, diminuem até parecer apenas carvão incandescente. | E66: Regiões vulcânicas, cavernas aquecidas por magma, fontes termais, montanhas dracônicas e florestas próximas a áreas de atividade geotérmica. | F66: Salamandras das Chamas costumam dormir dentro de fogueiras apagadas. Filhotes de dragões frequentemente tentam brincar com elas. Ferreiros consideram sua presença um sinal de boa sorte para a produção de armas e armaduras. Algumas conseguem aquecer pequenas áreas durante tempestades de neve. É comum vê-las reunidas próximas a rios de lava como se estivessem tomando banho de sol. Apesar de serem espíritos do fogo, não gostam de incêndios descontrolados. Druidas acreditam que elas ajudam a manter o equilíbrio entre destruição e renovação causados pelo elemento fogo. Existem relatos de Salamandras extremamente antigas que se transformaram em poderosos espíritos elementais maiores. | G66: Anfíbio Mágico | H66: Anfibio | I66: Fogo | J66: Comum | K66: Muito Pequeno | L66: Curioso, Brincalhão e Social | M66: Essência de Chama Menor Escama Incandescente Núcleo de Brasa Viva Cristal de Fogo Natural Lágrima Flamejante Cinzas Encantadas Fragmento de Mana Ígnea Coração de Brasa

Sheet Nivels
D3: Grau de Ameaça
C4: =COUNTIF(Plan1!J:J,D4) | D4: Inofensivo | E4: Grau 0 — Inofensivo Criaturas dóceis que raramente apresentam qualquer risco para humanoides. Normalmente fogem diante de ameaças e não possuem capacidade real de causar ferimentos graves, mesmo quando acuadas. Podem servir como alimento, montaria, companhia ou parte do ecossistema local. Exemplos: pequenos animais, aves comuns, criaturas domésticas.
C5: =COUNTIF(Plan1!J:J,D5) | D5: Comum | E5: Grau I — Comum Criaturas geralmente pacíficas que podem reagir quando ameaçadas ou protegendo filhotes. Possuem força suficiente para ferir uma pessoa despreparada, mas raramente representam perigo para aventureiros experientes. São abundantes e amplamente conhecidas. Exemplos: cervos, montarias comuns, grandes herbívoros.
C6: =COUNTIF(Plan1!J:J,D6) | D6: Menor | E6: Grau II — Menor Criaturas ariscas ou naturalmente agressivas. Possuem meios eficazes de defesa ou ataque e podem causar ferimentos sérios em indivíduos isolados. São consideradas perigosas para viajantes comuns. Exemplos: predadores pequenos e médios, criaturas venenosas, animais territoriais.
C7: =COUNTIF(Plan1!J:J,D7) | D7: Ameaça | E7: Grau III — Ameaça Criaturas capazes de matar um humanoide adulto com relativa facilidade. Possuem força, velocidade, venenos ou capacidades naturais suficientemente perigosas para exigir preparação. Embora letais, geralmente evitam confrontos desnecessários para conservar energia. Exemplos: grandes predadores, monstros de caça especializados.
C8: =COUNTIF(Plan1!J:J,D8) | D8: Elite | E8: Grau IV — Elite Predadores dominantes ou criaturas extremamente agressivas. Frequentemente atacam primeiro, defendem vastos territórios e representam ameaça significativa até para grupos organizados. Costumam ocupar o topo da cadeia alimentar regional. Exemplos: superpredadores, monstros territoriais excepcionais.
C9: =COUNTIF(Plan1!J:J,D9) | D9: Lendário | E9: Grau V — Lendário Criaturas cuja simples presença altera o equilíbrio de uma região. Possuem inteligência elevada, enorme poder físico ou capacidades sobrenaturais raras. São frequentemente tema de lendas, religiões e histórias locais. Enfrentá-las exige planejamento, recursos e experiência. Exemplos: dragões maiores, matriarcas monstruosas, guardiões ancestrais.
C10: =COUNTIF(Plan1!J:J,D10) | D10: Mítico | E10: Grau VI — Mítico Seres dotados de consciência avançada e compreensão do mundo. Frequentemente possuem cultura, linguagem, conhecimento ancestral ou poderes capazes de influenciar civilizações inteiras. Podem negociar, governar ou manipular eventos históricos. Exemplos: dragões extremamente antigos, entidades primordiais menores.
C11: =COUNTIF(Plan1!J:J,D11) | D11: Cataclísmico | E11: Grau VII — Cataclísmico Criaturas capazes de destruir cidades, reinos ou regiões inteiras. Sua existência representa uma ameaça estratégica para nações. O surgimento de uma criatura desse nível costuma mobilizar exércitos inteiros. Exemplos: Dragões Anciões, titãs primordiais, monstros do Negativo.
C12: =COUNTIF(Plan1!J:J,D12) | D12: Apocalíptico | E12: Grau VIII — Apocalíptico Entidades capazes de alterar o destino do mundo. Sua ação pode levar à extinção de espécies, destruição de continentes ou colapso de civilizações inteiras. São consideradas ameaças globais. Exemplos: entidades supremas do Negativo, Primordiais corrompidos, seres ligados ao fim dos tempos.
A15: =SUM(A16:A42) | B15: =SUM(B16:B42) | C15: =SUM(C16:C42) | D15: Categoria | E15: Descrição
A16: =B16-C16 | B16: 24 | C16: =COUNTIF(Plan1!G:G,D16) | D16: Besta Mágica | E16: São criaturas que possui ligação com um ou mais elementos (Terra, Fogo, Agua, Vento ou Trovão)
A17: =B17-C17 | B17: 6 | C17: =COUNTIF(Plan1!G:G,D17) | D17: Besta Mágica - Tribal | E17: São criaturas que tem conciencias e linguagem, possui elementos, mas algumas especies pode ter apenas famialidade com Arcano
A18: =B18-C18 | B18: 8 | C18: =COUNTIF(Plan1!G:G,D18) | D18: Besta Mágica Suprema | E18: São Criaturas que possui ligação com um ou mais elementos adicionalmente elementos de entidade Sagrado ou Caótico
A19: =B19-C19 | B19: 1 | C19: =COUNTIF(Plan1!G:G,D19) | D19: Dragão Superior | E19: Criaturas de origem comum de dragões mais de nivies mitologicos
A20: =B20-C20 | B20: 8 | C20: =COUNTIF(Plan1!G:G,D20) | D20: Aquático Mágico | E20: São criaturas de origem marinha que não consegue viver fora da agua e possui ligação com um ou mais elementos
A21: =B21-C21 | B21: 6 | C21: =COUNTIF(Plan1!G:G,D21) | D21: Aquático Mágico Supremo | E21: São criaturas de origem marinha que não consegue viver fora da agua e possui ligação com um ou mais elementos adicionalmente naturezas divinas com oSagrados ou Caótico
A22: =B22-C22 | B22: 10 | C22: =COUNTIF(Plan1!G:G,D22) | D22: Místicos Mágicos | E22: São criaturas, ligadas a magia de origem arcana pode ou não contem elementos que não existentes a esse plano
A23: =B23-C23 | B23: 8 | C23: =COUNTIF(Plan1!G:G,D23) | D23: Místicos Mágicos Supremo | E23: São criaturas, ligadas a magia geralmente arcana e sagrado ou caóticos não existentes a esse plano
A24: =B24-C24 | B24: 10 | C24: =COUNTIF(Plan1!G:G,D24) | D24: Anfíbio Mágico | E24: Criaturas que vivem nasceram na agua mas pode viver fora em terra, e possui ligação com elementos
A25: =B25-C25 | B25: 4 | C25: =COUNTIF(Plan1!G:G,D25) | D25: Anfíbio Mágico Supremo | E25: Criaturas que vivem nasceram na agua mas pode viver fora em terra, e possui ligação com elementos incluindo de entidades sagradas ou caóticas
A26: =B26-C26 | B26: 15 | C26: =COUNTIF(Plan1!G:G,D26) | D26: Criatura do Negativo | E26: Criaturas que foram corrompdas pelo Negativo e perderam totalmente suas propriedades
A27: =B27-C27 | B27: 8 | C27: =COUNTIF(Plan1!G:G,D27) | D27: Criatura do Negativo Supremo | E27: Criaturas que foram corrompdas pelo Negativo e perderam totalmente suas propriedades com ligação forte a entidade do Nada.
... A35: =B35-C35 | B35: 1 | C35: =COUNTIF(Plan1!G:G,D35) | D35: Dragão Primordial | E35: Criaturas de origem comum de dragões mais antigos

Sheet LEGADO
A1: Dados base | M1: Possiveis Itens | N1: Estatísticas | AA1: Habilidades | AF1: Perícias
A2: Nome | B2: Anotação | C2: Descricao | D2: Aparencia | E2: Habitat | F2: Curiosidades de Astrolong TerraNova | G2: Categoria | H2: Tipo | I2: Natureza | J2: Grau de Ameaça | K2: Tamanho | L2: Comportamento | M2: Itens | N2: FOR | O2: DES | P2: VIT | Q2: INT | R2: PRE | S2: Vida | T2: Defesa | U2: Mana | V2: Ataque Basico | W2: CD Conjurador | X2: Atributo Conjurador | Y2: Resistencia | Z2: Fraqueza | AA2: Habilidade 1 | AB2: Habilidade 2 | AC2: Habilidade 3 | AD2: Habilidade 4 | AE2: Habilidade 5 | AF2: Atletismo | AG2: Reflexo | AH2: Tenacidade | AI2: Vontade | AJ2: Foco | AK2: Luta | AL2: Sobrevivência
A3: Dríade das Florestas Ancestrais | B3: Poucos aventureiros encontram uma Dríade. Menos ainda percebem que foram observados por uma durante toda a viagem. — Astrolong TerraNova | C3: As Dríades das Florestas Ancestrais são criaturas humanoides compostas por madeira viva, folhas, flores e mana natural. Diferente do que muitos acreditam, elas não são espíritos nem elementais. São seres vivos pertencentes à categoria das Bestas Mágicas e possuem sociedades próprias escondidas nas profundezas das florestas élficas. Suas comunidades raramente ultrapassam algumas dezenas de indivíduos e costumam existir próximas a árvores ancestrais ou fontes naturais de mana. Embora possuam aparência delicada, as Dríades vivem por séculos e acumulam conhecimento profundo sobre a floresta. | D3: Criatura humanide que se assemelha muita a humanos e elfos, com corpos cobertos de vegetação, tem rosto simpaticos e muita belas. | E3: Reino dos Elfos, Florestas Ancestrais | F3: Muitos aventureiros descrevem as Dríades como belas. Isso é verdade. Porém, a beleza não é a característica mais impressionante delas. O que realmente chama atenção é sua capacidade de permanecer completamente imóvel por horas. Mais de uma vez passei por uma árvore para descobrir, dias depois, que ela estava me observando. | G3: Besta Mágica - Tribal | H3: Planta | I3: Arcano, Água e Terra | J3: Comum | K3: Médio | L3: Tribal, Social e Pacificos | M3: Flores de Mana Sementes Feéricas Essência Natural Frutos Ancestrais | N3: 1 | O3: 2 | P3: 2 | Q3: 2 | R3: 3 | S3: 24 | T3: 13 | U3: 6 | W3: 13 | X3: PRE | AA3: Toque Vital (custo 2 PM, 3x por cena) - cura 1d6 + Presença de Vida em uma criatura tocada, ou causa 1d6 de dano de Terra em um inimigo (CD 13, salv. Tenacidade para metade). | AB3: Emaranhar (custo 2 PM, 2x por cena) - raízes seguram um alvo a 6m (CD 13, salv. Atletismo ou fica Aprisionado por 1 rodada). | AF3: 0 | AG3: 0 | AH3: 0 | AI3: 3 | AJ3: 2 | AK3: 0 | AL3: 2
A4: Ent Jovem | B4: Quando uma floresta deseja se defender, ela cria espinhos. Quando deseja se lembrar, cria Ents. — Astrolong TerraNova | C4: Os Ents Jovens são árvores despertas pela mana das Florestas Ancestrais. Diferente das Dríades, que possuem comunidades e cultura própria, os Ents existem como guardiões vivos da natureza. Seu corpo é formado por madeira viva extremamente resistente, coberta por musgos, flores, cipós e pequenos animais que frequentemente utilizam sua estrutura como abrigo. Embora sejam chamados de jovens, muitos já possuem mais de cinquenta anos de idade. O termo é utilizado pelos Elfos para diferenciar indivíduos que ainda não atingiram o tamanho colossal dos Ents Ancestrais. São criaturas lentas e pacientes. Um Ent pode permanecer imóvel por semanas observando uma mesma região antes de agir. | D4: Um Ent Jovem possui entre 4 e 6 metros de altura. Seu tronco lembra o de uma árvore centenária, enquanto seus braços assumem a forma de galhos robustos capazes de esmagar pedras. Seu rosto surge naturalmente na madeira, formado por rachaduras e nós que lembram olhos, nariz e boca. Durante a primavera, alguns desenvolvem flores e folhas coloridas em seus ombros e braços. | E4: Reino dos Elfos, Florestas Ancestrais | F4: Muitos aventureiros acreditam que os Ents são lentos porque são árvores. Estão enganados. Eles são lentos porque já viram séculos passarem diante de seus olhos. Para uma criatura que mede o tempo em florestas e não em anos, nós somos os apressados. | G4: Besta Mágica | H4: Planta | I4: Terra | J4: Ameaça | K4: Grande | L4: Territórialista | M4: Madeira Ancestral Seiva Encantada Núcleo de Mana Natural Sementes Primordiais | N4: 4 | O4: 1 | P4: 4 | Q4: 1 | R4: 1 | S4: 57 | T4: 14 | U4: 2 | W4: 9 | X4: INT | AA4: Raízes Imobilizantes (custo 2 PM, 3x por cena) - prende um inimigo a até 9m em raízes vivas (CD 9, salv. Atletismo ou fica Aprisionado por 1 rodada). | AB4: Golpe de Tronco (custo 2 PM, 2x por cena) - golpe de galho que causa 2d6 de dano de Terra adicional (CD 9, salv. Reflexo para metade). | AF4: 6 | AG4: 0 | AH4: 6 | AI4: 0 | AJ4: 0 | AK4: 4 | AL4: 2
A5: Ave do Paraíso Ancestral | B5: Durante décadas acreditei que os bardos exageravam ao descrever estas aves. Descobri meu erro no momento em que vi um bando cruzar o céu ao amanhecer. Nenhuma tinta é capaz de reproduzir todas as cores que brilham em suas penas. | C5: A Ave do Paraíso Ancestral é considerada uma das criaturas mais belas de todo o Continente Ancestral. Seu canto harmonioso pode ser ouvido ao amanhecer e ao entardecer, sendo frequentemente associado a presságios de boa sorte por viajantes e habitantes das florestas. Apesar de ser conhecida como uma única espécie, estudiosos catalogaram mais de duzentas variedades diferentes espalhadas pelas florestas, pradarias e bosques do continente. Cada espécie apresenta combinações únicas de cores, padrões e formatos de penas. As Dríades acreditam que essas aves surgiram quando os primeiros ventos da criação atravessaram as florestas recém-nascidas, espalhando fragmentos de mana sobre as árvores ancestrais. São criaturas extremamente importantes para o equilíbrio natural, atuando na dispersão de sementes, pólen mágico e pequenas essências naturais entre diferentes regiões da floresta. | D5: A Ave do Paraíso Ancestral possui entre 20 e 40 centímetros de comprimento, com corpo leve e elegante adaptado ao voo ágil entre galhos e copas densas. Suas penas apresentam uma impressionante variedade de cores vibrantes, incluindo tons de azul, verde-esmeralda, dourado, violeta, vermelho-rubi e branco-perolado. Algumas espécies possuem caudas longas que podem atingir três vezes o comprimento do corpo. Quando expostas à luz do sol ou à mana ambiente, certas penas produzem reflexos iridescentes que mudam constantemente de cor, criando um espetáculo visual difícil de descrever. Os machos geralmente apresentam plumagens mais extravagantes, enquanto as fêmeas possuem padrões mais discretos, porém igualmente belos. Diversas espécies desenvolvem pequenas cristas, leques de penas ou caudas ornamentais utilizadas durante elaborados rituais de acasalamento que transformam clareiras inteiras em verdadeiros espetáculos naturais. | E5: Reino dos Elfos, Terras dos Faunos e Florestas Ancestrais | F5: A maioria dos aventureiros observa apenas a plumagem dessas aves. Eu prefiro observar os outros animais ao seu redor. Em mais de uma ocasião, encontrei predadores descansando próximos a um bando de Aves do Paraíso Ancestrais sem demonstrar qualquer intenção de caça. Não compreendo completamente o motivo, mas suspeito que a mana presente em suas penas produza uma sensação de tranquilidade nas criaturas ao redor. | G5: Besta Mágica | H5: Ave | I5: Vento | J5: Inofensivo | K5: Pequeno | L5: Pacífico e Sociável | M5: Pena Arcoiris | N5: 0 | O5: 2 | P5: 1 | Q5: 0 | R5: 1 | S5: 11 | T5: 12 | U5: 2 | W5: 9 | X5: PRE | AA5: Canto Encantador (custo 1 PM, 2x por cena) - canto que acalma; uma criatura a 6m faz salv. Vontade (CD 9) ou fica Fascinada (não pode atacar a ave) por 1 rodada. | AF5: 0 | AG5: 2 | AH5: 0 | AI5: 0 | AJ5: 0 | AK5: 0 | AL5: 1
A6: MegaMutty | B6: Quando vi um pela primeira vez à distância, pensei estar observando uma colina ambulante. Somente após me aproximar percebi que se tratava de uma criatura viva. O mais curioso foi descobrir que a enorme besta que poderia facilmente me esmagar estava mais interessada em comer frutas do que em me atacar. — Astrolong TerraNova | C6: Os MegaMuttys são grandes mamíferos mágicos conhecidos por sua natureza dócil e comportamento altamente social. Vivem em pequenos grupos familiares que podem variar entre seis e vinte indivíduos, percorrendo extensas áreas de floresta e pradarias em busca de alimento. Apesar de sua aparência intimidadora e enorme força física, raramente demonstram agressividade contra outras criaturas. A maioria dos conflitos envolvendo MegaMuttys ocorre durante a estação de acasalamento ou quando um filhote é ameaçado. São considerados uma das espécies mais importantes da região, pois ajudam a moldar o ambiente por onde passam. Ao derrubarem árvores antigas, abrirem trilhas naturais e espalharem sementes durante suas migrações, contribuem diretamente para a renovação das florestas. Muitos Faunos os consideram símbolos de prosperidade, enquanto alguns Elfos os enxergam como guardiões silenciosos das fronteiras naturais entre os bosques e as pradarias. | D6: Um MegaMutty adulto possui entre três e quatro metros de altura quando apoiado sobre as quatro patas e pode ultrapassar oito metros de comprimento. Seu corpo é robusto e extremamente musculoso, sustentado por patas grossas adaptadas para longas caminhadas e investidas devastadoras. Sua anatomia lembra a de um enorme mamífero quadrúpede coberto por uma espessa camada de pelos marrons, cinzentos e negros que o protege das mudanças climáticas. A cabeça apresenta um focinho alongado e poderoso, enquanto suas presas curvas crescem para frente, sendo utilizadas para escavar raízes, derrubar árvores e disputar parceiros durante a época reprodutiva. Os indivíduos mais velhos costumam desenvolver camadas ainda mais densas de pelos, frequentemente cobertas por musgos, flores e pequenos insetos que passam a viver em simbiose com a criatura. | E6: Fronteiras entre o Reino dos Elfos e as Terras dos Faunos | F6: A maioria dos aventureiros acredita que os MegaMuttys são perigosos por causa do tamanho. Na realidade, são perigosos por causa da velocidade. Poucos esperam que uma criatura tão grande consiga atravessar uma clareira inteira em poucos segundos. Os filhotes permanecem próximos da mãe por quase cinco anos. Durante esse período, qualquer criatura que se aproxime demais será tratada como uma ameaça, independentemente de suas intenções. Em uma ocasião observei um grupo de Dríades utilizando um MegaMutty adormecido como ponto de encontro. A criatura sequer pareceu se importar quando acordou cercada por elas. As trilhas abertas pelos rebanhos mais antigos são tão utilizadas por outras criaturas que alguns mapas élficos as registram como rotas permanentes de viagem. Jamais confunda um MegaMutty relaxado com um MegaMutty amigável. Eles são pacíficos, mas continuam sendo criaturas capazes de derrubar uma árvore centenária com uma única investida. | G6: Besta Mágica | H6: Besta | I6: Terra | J6: Comum | K6: Grande | L6: Social e Pacífico (Territorial durante o acasalamento e proteção dos filhotes) | M6: Presas de MegaMutty Couro Espesso de MegaMutty Pelagem Gigante Osso Reforçado Glândula de Resistência Natural Musgos Simbióticos Crescidos na Pelagem Fragmentos de Mana Natural | N6: 3 | O6: 1 | P6: 3 | Q6: 0 | R6: 0 | S6: 27 | T6: 12 | U6: 0 | AF6: 3 | AG6: 0 | AH6: 3 | AI6: 0 | AJ6: 0 | AK6: 0 | AL6: 1
A7: Pantera Felina Negra | B7: A maioria dos viajantes acredita que a escuridão da Floresta Negra esconde monstros. Estão parcialmente corretos. O verdadeiro problema é que algumas criaturas se tornaram tão adaptadas à escuridão que a própria floresta parece conspirar para ocultá-las. Nenhuma representa melhor isso do que a Pantera Felina Negra. — Astrolong TerraNova | C7: A Pantera Felina Negra é uma das cinco espécies conhecidas de Panteras Felinas. Embora compartilhem a característica comum de possuir dois pares de pernas dianteiras e um par de pernas traseiras, esta espécie se destaca por sua extraordinária adaptação à vida noturna. Habitando as regiões mais profundas da Floresta Negra, esses predadores raramente são vistos durante o dia. Preferem caçar sob a cobertura da noite, utilizando a vegetação densa e as sombras naturais para se aproximarem de suas presas sem serem percebidos. Sua dieta é composta principalmente por cervos, javalis, pequenos monstros da floresta e, ocasionalmente, criaturas mágicas menores. Ataques contra humanoides são raros e geralmente ocorrem apenas quando o animal se sente encurralado ou quando seu território é invadido repetidamente. Apesar da reputação assustadora, a Pantera Felina Negra desempenha um papel fundamental no equilíbrio ecológico da Floresta Negra, controlando populações de criaturas menores e eliminando indivíduos doentes ou enfraquecidos. | D7: Uma Pantera Felina Negra adulta possui aproximadamente 300 quilos de massa corporal e pode atingir mais de quatro metros de comprimento da cabeça até a ponta da cauda. Seu corpo musculoso é sustentado por seis patas poderosas: quatro dianteiras e duas traseiras. Essa anatomia incomum proporciona estabilidade excepcional durante corridas, saltos e emboscadas. Toda sua pelagem é composta por pelos negros extremamente densos, capazes de absorver grande parte da luz ambiente. Sob certas condições, a criatura parece se fundir completamente às sombras da floresta. Seus olhos brilham em tons de verde-esmeralda ou dourado intenso durante a noite, sendo muitas vezes a única parte visível do animal quando está observando uma presa. A cauda longa auxilia no equilíbrio durante perseguições e saltos entre raízes, rochas e troncos caídos. | E7: Floresta Negra | F7: Em vinte e três anos explorando a Floresta Negra, encontrei rastros de Panteras Felinas Negras centenas de vezes. Vi uma delas apenas quatro. Seu corpo produz tão pouco ruído durante a movimentação que alguns caçadores acreditam que a criatura utiliza magia para silenciar seus passos. Até o momento não encontrei evidências que comprovem essa teoria. Os filhotes nascem com manchas cinzentas espalhadas pela pelagem. Essas marcas desaparecem completamente antes de atingirem a idade adulta. É comum encontrar cervos e outras presas vivendo relativamente próximos do território de uma Pantera Felina Negra. Diferente de muitos predadores, elas raramente matam mais do que o necessário para se alimentar. A primeira vez que percebi estar sendo seguido por uma dessas criaturas foi ao notar que os pássaros haviam parado de cantar. A segunda vez, percebi tarde demais. | G7: Besta Mágica | H7: Felina | I7: Terra e Vento | J7: Ameaça | K7: Grande | L7: Solitário, Territorial e Predador Noturno | M7: Presas de Pantera Negra Garras Sombrias Couro Negro Reforçado Pelagem Noturna Olhos Cristalizados de Pantera Bigodes Sensoriais Glândula de Caça Noturna Essência Predatória | N7: 3 | O7: 4 | P7: 2 | Q7: 1 | R7: 1 | S7: 51 | T7: 17 | U7: 2 | W7: 9 | X7: INT | AA7: Salto Predador (sem custo, 1x por rodada) - antes de atacar, pode se mover até 6m sem provocar reações. | AB7: Garras Sombrias (custo 2 PM, 2x por cena) - ataque que causa 2d6 de dano adicional do tipo Vento (CD 9, salv. Reflexo para metade). | AF7: 4 | AG7: 6 | AH7: 0 | AI7: 0 | AJ7: 0 | AK7: 6 | AL7: 2
A8: Pantera Felina Marrom | B8: Diferente de sua prima da Floresta Negra, a Pantera Felina Marrom não se esconde nas sombras. Ela prefere observar o mundo sob a luz do sol, descansando sobre rochedos elevados ou galhos robustos enquanto vigia seu território. Muitos viajantes sequer percebem que estão sendo observados até que a criatura decida partir. — Astrolong TerraNova | C8: A Pantera Felina Marrom é uma das espécies mais comuns entre os grandes felinos de seis patas encontrados no Continente Ancestral. Habita principalmente encostas montanhosas, florestas elevadas e regiões de transição entre os bosques élficos e as montanhas anãs. Embora seja um predador eficiente, raramente demonstra agressividade gratuita. Sua estratégia de caça baseia-se em paciência, observação e emboscadas rápidas, utilizando a vegetação e os desníveis do terreno para se aproximar das presas. Sua dieta é composta principalmente por cervos, cabras-montesas, javalis, aves de grande porte e outras criaturas de médio porte. Em regiões montanhosas, são frequentemente vistas caçando ao longo de penhascos e trilhas estreitas. Anões costumam respeitar essas criaturas, considerando-as símbolos de força e independência. Já os Elfos as enxergam como importantes guardiãs naturais das fronteiras selvagens. | D8: Uma Pantera Felina Marrom adulta pesa aproximadamente 150 quilos e mede entre três e quatro metros de comprimento. Seu corpo apresenta a característica típica das Panteras Felinas: dois pares de patas dianteiras e um par de patas traseiras. Essa anatomia proporciona equilíbrio excepcional durante escaladas, perseguições e saltos entre rochas. A pelagem varia entre diferentes tons de marrom, castanho, cobre e bege, permitindo excelente camuflagem em montanhas, bosques secos e regiões rochosas. Sua musculatura é mais compacta e ágil que a da Pantera Felina Negra, sendo adaptada para terrenos acidentados. A longa cauda auxilia no equilíbrio durante deslocamentos sobre penhascos e galhos elevados. Os olhos costumam apresentar coloração âmbar, dourada ou cobre, refletindo intensamente a luz solar. As quatro patas dianteiras terminam em garras retráteis extremamente afiadas, capazes de se fixar em superfícies rochosas quase verticais. | E8: Reino dos Anões e Reino dos Elfos | F8: Se uma Pantera Felina Negra é um fantasma da noite, a Pantera Felina Marrom é uma rainha das montanhas. Durante minhas expedições ao Reino dos Anões observei diversas vezes indivíduos descansando sobre formações rochosas tão altas que pareciam impossíveis de alcançar. Ainda hoje não compreendo completamente como conseguem subir até alguns daqueles locais. Filhotes costumam brincar simulando caçadas entre si. Curiosamente, utilizam as quatro patas dianteiras para imobilizar os irmãos enquanto praticam mordidas controladas. Muitos caçadores acreditam que a espécie possui um senso de direção sobrenatural. Diversos indivíduos marcados por estudiosos foram observados retornando exatamente ao mesmo território anos depois. Embora sejam predadores temidos, são conhecidos por evitar confrontos desnecessários. Em mais de uma ocasião observei uma Pantera Felina Marrom abandonar uma caça ao perceber a presença de filhotes de outra espécie nas proximidades. | G8: Besta Mágica | H8: Felina | I8: Terra | J8: Menor | K8: Grande | L8: Solitário, Territorial e Predador Diurno | M8: Garras de Pantera Marrom Presas Serrilhadas Couro Montanhês Pelagem Castanha Bigodes Sensoriais Olhos Âmbar Cristalizados Glândula de Equilíbrio Essência de Predador Alpino | N8: 3 | O8: 3 | P8: 2 | Q8: 0 | R8: 1 | S8: 36 | T8: 15 | U8: 2 | W8: 9 | X8: PRE | AA8: Rugido Territorial (custo 1 PM, 2x por cena) - rugido que assusta; inimigos em 6m fazem salv. Vontade (CD 9) ou ficam Amedrontados por 1 rodada. | AF8: 2 | AG8: 4 | AH8: 0 | AI8: 0 | AJ8: 0 | AK8: 4 | AL8: 2
A9: Pantera Felina Real | B9: Entre todas as Panteras Felinas que cataloguei, nenhuma demonstra tanta nobreza quanto a Pantera Felina Real. Elas caminham pelas pradarias e florestas como verdadeiros reis da natureza. Curiosamente, já encontrei indivíduos que toleraram minha presença por dias inteiros, observando-me com a mesma curiosidade que eu observava a eles. — Astrolong TerraNova | C9: A Pantera Felina Real é considerada a mais majestosa das cinco espécies conhecidas de Panteras Felinas. Diferente de suas parentes mais solitárias, vivem em grupos familiares organizados chamados de bandos reais. Esses grupos normalmente são liderados por um macho dominante, acompanhado por diversas fêmeas adultas, filhotes e jovens em treinamento. São criaturas naturalmente pacíficas e costumam ignorar viajantes, aventureiros e até outras espécies, desde que não representem ameaça ao grupo. Durante a época de reprodução, entretanto, seu comportamento muda drasticamente. Machos disputam território e direito de acasalamento através de confrontos violentos que podem durar horas. Nesse período tornam-se extremamente agressivos e perigosos. As fêmeas também demonstram feroz instinto protetor quando possuem filhotes recém-nascidos, atacando imediatamente qualquer criatura que se aproxime demais. Apesar disso, fora dessas situações, são consideradas uma das grandes maravilhas vivas do Continente Ancestral. | D9: Uma Pantera Felina Real adulta pode atingir cerca de 450 quilos e ultrapassar cinco metros de comprimento da cabeça até a ponta da cauda. Como todas as Panteras Felinas, possui dois pares de patas dianteiras e um único par de patas traseiras, característica que lhe proporciona estabilidade extraordinária durante corridas, saltos e combates. Sua pelagem varia entre tons dourados, laranja intenso e cobre brilhante. Sob a luz do sol, seus pelos parecem refletir a própria luz, produzindo um brilho majestoso visível a grandes distâncias. Os machos desenvolvem uma exuberante juba dourada que cresce ao redor do pescoço, peito e ombros. Quanto mais velho e dominante o indivíduo, maior tende a ser sua juba. Seus olhos costumam apresentar coloração âmbar, dourada ou alaranjada, transmitindo uma expressão de inteligência, confiança e serenidade. Sua musculatura é impressionante, combinando força bruta com elegância e agilidade raramente vistas em criaturas de seu porte. | E9: Terras dos Faunos e Reino dos Elfos | F9: Já observei grupos de Faunos caminhando ao lado de Panteras Felinas Reais sem qualquer demonstração de medo. Nenhuma das partes parecia considerar a outra uma ameaça. Filhotes são criados coletivamente por todas as fêmeas do grupo. Em alguns casos, uma única ninhada pode receber cuidados de cinco ou seis mães diferentes. Os rugidos dos machos podem ser ouvidos a quilômetros de distância durante a estação de reprodução. O som ecoa pelas pradarias como um trovão distante. Ao contrário do que muitos acreditam, a juba não serve apenas para impressionar parceiros. Ela também protege regiões vitais do pescoço durante disputas territoriais. Entre os Faunos existe a crença de que encontrar uma Pantera Felina Real descansando tranquilamente durante uma viagem é um presságio de boa sorte e prosperidade. | G9: Besta Mágica | H9: Felina | I9: Terra e Trovão | J9: Ameaça | K9: Grande | L9: Social, Familiar e Territorial durante reprodução ou proteção dos filhotes | M9: Juba Dourada de Pantera Real Garras Reais Presas Majestosas Couro Real Olhos Âmbar Cristalizados Bigodes Sensoriais Glândula de Vitalidade Essência do Guardião da Pradaria | N9: 3 | O9: 3 | P9: 2 | Q9: 1 | R9: 2 | S9: 51 | T9: 16 | U9: 4 | W9: 10 | X9: PRE | AA9: Liderança de Bando (sem custo, passiva) - panteras aliadas a 9m recebem +2 em Reflexo. | AB9: Rugido Real (custo 2 PM, 2x por cena) - rugido em área de 6m; inimigos fazem salv. Vontade (CD 10) ou ficam Amedrontados por 1 rodada. | AF9: 3 | AG9: 5 | AH9: 0 | AI9: 2 | AJ9: 0 | AK9: 5 | AL9: 3
A10: Pantera Felina dos Riachos Albina | B10: Poucas criaturas conseguem transmitir beleza e perigo na mesma medida. A Pantera dos Riachos Albina parece uma escultura viva de gelo e neve quando observada à distância. Muitos exploradores ficam fascinados por sua aparência majestosa. Os mais imprudentes raramente têm uma segunda oportunidade para admirar sua beleza. — Astrolong TerraNova | C10: A Pantera Felina dos Riachos Albina é uma variante rara das Panteras Felinas adaptada às regiões geladas do extremo norte. Considerada uma das mais eficientes predadoras do Continente Ancestral, desenvolveu habilidades extraordinárias para caça tanto em terra quanto na água. Embora possa perseguir presas sobre a neve, escalar encostas e atravessar terrenos congelados com facilidade, seu verdadeiro domínio encontra-se nos rios, lagos e canais subterrâneos das Terras do Norte Gelado. Essas criaturas são capazes de permanecer submersas por longos períodos, utilizando sua excepcional capacidade pulmonar e controle corporal para se aproximar silenciosamente das presas. Peixes gigantes, focas glaciais, cervos do norte e até jovens gigantes podem se tornar alvos de uma Pantera dos Riachos adulta. Apesar de serem predadoras extremamente eficientes, raramente desperdiçam energia em conflitos desnecessários. | D10: Uma Pantera Felina dos Riachos Albina adulta pode ultrapassar os 250 quilos e atingir mais de quatro metros de comprimento. Seu corpo possui a anatomia característica das Panteras Felinas, com dois pares de patas dianteiras e um único par de patas traseiras. Sua pelagem é completamente branca, variando entre tons de neve, marfim e prata clara. Em alguns indivíduos, manchas extremamente sutis podem ser observadas sob determinadas condições de iluminação. Os olhos costumam apresentar coloração azul-glacial, violeta pálido ou vermelho-rubi, características comuns do albinismo presente na espécie. Sua musculatura é compacta e poderosa, especialmente na região dos ombros e das patas dianteiras, permitindo explosões repentinas de velocidade tanto na água quanto em terra firme. As patas possuem membranas discretas entre os dedos que aumentam significativamente sua eficiência durante a natação. Observação Anatômica As patas dianteiras menores possuem articulações especiais que permitem recolher completamente as garras e dobrar parte da estrutura óssea atrás do par principal de patas dianteiras. Essa adaptação faz com que muitos observadores acreditem estar diante de uma criatura de quatro patas até o momento do ataque. Quando necessário, essas patas ocultas são utilizadas para desferir golpes inesperados, agarrar presas ou aumentar drasticamente sua capacidade de escalada e natação. | E10: Terras do Norte Gelado, rios congelados, lagos glaciais, vales nevados e encostas montanhosas | F10: Já observei uma Pantera dos Riachos permanecer imóvel sob uma camada de gelo por quase uma hora inteira aguardando o momento ideal para atacar. Os habitantes das Terras Geladas costumam chamá-las de Fantasmas Brancos dos Rios, pois muitas vezes a única coisa visível é o reflexo de seus olhos sob a água. Durante uma expedição, testemunhei uma dessas criaturas capturar um peixe quase do mesmo tamanho que seu próprio corpo. A luta durou menos de trinta segundos. Poucos aventureiros sabem da existência de suas patas ocultas. Mais de um caçador experiente foi surpreendido ao descobrir que a criatura possuía muito mais alcance e controle do que aparentava. Embora sejam predadoras formidáveis, as mães demonstram cuidado extraordinário com seus filhotes. Já vi uma delas atravessar um rio parcialmente congelado diversas vezes para transportar seus jovens em segurança. Entre os povos do norte existe uma antiga crença de que avistar uma Pantera dos Riachos Albina nadando contra a corrente significa que uma grande mudança está prestes a acontecer. | G10: Besta Mágica | H10: Felina | I10: Terra e Água | J10: Elite | K10: Grande | L10: Solitária ou Familiar, Territorial, Predadora Aquática | M10: Pelagem Glacial Albina Garras Ocultas dos Riachos Presas do Caçador Ártico Couro Impermeável Superior Bigodes Sensoriais Aquáticos Olhos Cristalinos Glaciais Membranas Natatórias Glândula de Respiração Prolongada Essência da Caçadora dos Rios Gelados | N10: 4 | O10: 4 | P10: 3 | Q10: 1 | R10: 2 | S10: 74 | T10: 19 | U10: 4 | W10: 10 | X10: PRE | AA10: Emboscada Glacial (custo 3 PM, 2x por cena) - ataque surpresa que causa 2d8 de dano de Água adicional e aplica Lentidão por 2 rodadas (CD 10, salv. Atletismo para sem Lentidão). | AB10: Pelagem Branca (passiva) - vantagem em Furtividade em terrenos nevados/gelados. | AC10: Sopro Gélido (custo 2 PM, 1x por cena) - cone de 6m de ar congelante; criaturas na área fazem salv. Reflexo (CD 10) ou sofrem 2d6 de dano de Água e ficam Lentas por 1 rodada. | AF10: 6 | AG10: 7 | AH10: 2 | AI10: 0 | AJ10: 0 | AK10: 7 | AL10: 5
A11: Pantera Felina das Areias | B11: Se a Pantera Felina Negra é a sombra e a Pantera Felina dos Riachos é a água, então a Pantera Felina das Areias é o próprio vento. Já observei uma delas desaparecer no horizonte mais rápido do que um cavalo em disparada. Felizmente para os aventureiros, elas preferem fugir de problemas em vez de procurá-los. — Astrolong TerraNova | C11: A Pantera Felina das Areias é considerada a mais veloz entre todas as espécies conhecidas de Panteras Felinas. Adaptada aos terrenos áridos, pradarias secas e regiões de vegetação escassa das Terras Devastadas, desenvolveu um corpo extremamente leve e eficiente. Diferente de suas parentes maiores e mais agressivas, esta espécie evita conflitos sempre que possível. Seu primeiro instinto diante de qualquer ameaça é a fuga, utilizando sua velocidade extraordinária para escapar antes mesmo que um confronto aconteça. Sua dieta é composta principalmente por pequenos mamíferos, répteis, aves terrestres e criaturas de médio porte. Apesar de ser uma caçadora eficiente, raramente enfrenta presas muito maiores que ela. Durante a época de reprodução, entretanto, seu comportamento muda drasticamente. Machos tornam-se extremamente competitivos e disputam territórios através de corridas, demonstrações de velocidade e confrontos rápidos, porém violentos. Por sua natureza cautelosa, muitos estudiosos acreditam que existam mais Panteras das Areias do que os registros indicam, já que poucas pessoas conseguem observá-las por tempo suficiente para estudá-las adequadamente. | D11: Uma Pantera Felina das Areias adulta pesa cerca de 100 quilos, embora indivíduos excepcionais possam ultrapassar os 120 quilos. Seu corpo apresenta a anatomia característica das Panteras Felinas, com dois pares de patas dianteiras e um par de patas traseiras. Entre todas as espécies, possui a estrutura corporal mais esguia e aerodinâmica. A pelagem combina tons de amarelo dourado, laranja queimado, vermelho-terra e manchas escuras espalhadas pelo corpo. Sua musculatura é seca e alongada, construída para velocidade em vez de força bruta. As pernas longas permitem passadas impressionantes, enquanto a cauda comprida atua como leme durante curvas realizadas em alta velocidade. Os olhos geralmente apresentam coloração âmbar, dourada ou cobre intenso, adaptados para detectar movimentos a grandes distâncias. Em disparada máxima, uma Pantera Felina das Areias pode ultrapassar os 120 quilômetros por hora durante curtas distâncias, tornando-a uma das criaturas terrestres mais rápidas já catalogadas por Astrolong TerraNova. | E11: Terras Devastadas, fronteiras da Floresta dos Orcs, arredores da Floresta Negra e ocasionalmente as Terras dos Gigantes | F11: A maioria dos predadores foge quando está ferida. A Pantera das Areias foge quando está saudável. Já acompanhei um indivíduo por quase três dias antes que ele finalmente permitisse que eu me aproximasse o suficiente para observá-lo adequadamente. Os filhotes passam boa parte da infância disputando corridas entre si. A velocidade parece ser tão importante para sua sociedade quanto a força é para outras espécies. Durante uma tempestade de areia, observei uma dessas criaturas utilizar as próprias dunas como cobertura, movendo-se de forma tão eficiente que parecia desaparecer entre os grãos de areia. Embora possam alcançar velocidades impressionantes, raramente mantêm uma perseguição longa. Seu método de caça consiste em explosões repentinas de velocidade seguidas de ataques extremamente precisos. Entre os Orcs existe a crença de que capturar uma Pantera das Areias é impossível. Após muitos anos estudando a espécie, acredito que talvez estejam certos. | G11: Besta Mágica | H11: Felina | I11: Terra e Vento | J11: Ameaça | K11: Elite | L11: Arisco, Medroso, Territorial durante o período reprodutivo | M11: Couro das Areias Garras de Velocidade Presas Serrilhadas Bigodes Sensoriais Tendões Elásticos Olhos de Caçador do Deserto Essência da Rapidez Pelagem Escarlate | N11: 3 | O11: 5 | P11: 1 | Q11: 0 | R11: 2 | S11: 48 | T11: 18 | U11: 4 | W11: 10 | X11: PRE | AA11: Velocidade das Areias (passiva) - +3m de deslocamento; uma vez por combate pode repetir um teste de Reflexo. | AB11: Tempestade de Areia (custo 2 PM, 2x por cena) - levanta areia em 6m; inimigos na área fazem salv. Reflexo (CD 10) ou ficam Cegos por 1 rodada. | AF11: 4 | AG11: 7 | AH11: 0 | AI11: 0 | AJ11: 0 | AK11: 4 | AL11: 3
A12: Urso de Pijama Listrado | B12: A primeira vez que encontrei um Urso de Pijama Listrado, pensei estar observando uma criatura lenta e pesada descansando à margem de um lago. Instantes depois, vi a besta atravessar dezenas de metros de água em poucos segundos e arrancar um Peixe Gigante Vermelho do rio com uma única investida. Nunca mais subestimei sua velocidade. — Astrolong TerraNova | C12: O Urso de Pijama Listrado é uma das maiores bestas terrestres conhecidas do mundo. Habitando regiões frias e montanhosas próximas às Terras dos Gigantes e às Ilhas dos Dragões, tornou-se um dos predadores mais respeitados desses territórios. Apesar de seu tamanho colossal, raramente entra em conflito com outras criaturas. Prefere patrulhar sozinho vastas extensões de território, visitando regularmente rios e lagos onde caça sua presa favorita: os Peixes Gigantes Vermelhos. Sua técnica de caça é simples, mas devastadora. Permanecendo imóvel próximo à água, aguarda pacientemente o momento exato para atacar. Quando a presa se aproxima, avança com velocidade surpreendente, utilizando seus enormes membros dianteiros para capturá-la. Uma vez agarrada, escapar torna-se praticamente impossível. O abraço do Urso de Pijama Listrado é conhecido entre os caçadores como o Abraço do Penhasco, pois poucos seres possuem força suficiente para romper sua imobilização. | D12: O Urso de Pijama Listrado pode ultrapassar os 800 quilos e atingir mais de quatro metros de altura quando se ergue sobre as patas traseiras. Seu corpo é coberto por uma espessa pelagem listrada composta por faixas negras, cinzentas, castanhas e douradas. Os padrões são únicos para cada indivíduo e lembram as sombras projetadas pelas montanhas ao amanhecer. Sua anatomia é extremamente incomum. As patas dianteiras são significativamente maiores que as traseiras, formando ombros largos e musculosos capazes de mover pedras e derrubar árvores jovens. As garras dianteiras podem atingir quase meio metro de comprimento em indivíduos mais velhos, sendo utilizadas tanto para escavar quanto para capturar presas. Quando ataca, o Urso utiliza os braços para envolver completamente o alvo. Nesse momento, suas patas traseiras entram em ação, prendendo a vítima contra seu corpo enquanto as enormes garras impedem qualquer tentativa de fuga. A combinação entre força, peso e alcance faz com que poucas criaturas consigam escapar após serem capturadas. Sua cabeça apresenta focinho largo, mandíbulas poderosas e olhos pequenos, porém extremamente atentos. | E12: Terras dos Gigantes, Ilhas dos Dragões, costas geladas, grandes rios, lagos profundos e regiões montanhosas próximas ao mar | F12: Apesar de sua aparência feroz, os Urso de Pijama Listrado passam boa parte do dia descansando próximo a rios e lagos. Já encontrei indivíduos observando cardumes por horas antes de realizar um único ataque. Sua paciência rivaliza com a dos melhores caçadores. Muitos aventureiros acreditam que suas patas dianteiras servem apenas para combate. Na verdade, são ferramentas incrivelmente versáteis, utilizadas para escavar, nadar, escalar e até mover obstáculos enormes. Os Gigantes costumam respeitar essas criaturas. Em algumas regiões, matar um Urso de Pijama Listrado sem necessidade é considerado um ato de extrema desonra. Poucas criaturas conseguem enfrentar um adulto saudável. Mesmo dragões jovens evitam conflitos desnecessários com eles. Durante minhas viagens, encontrei marcas de garras gravadas em rochas sólidas por indivíduos que provavelmente viveram há séculos. | G12: Besta Mágica | H12: Besta | I12: Terra | J12: Elite | K12: Enorme | L12: Solitário, Territorial e Predador de Emboscada | M12: Tesouros Pelagem Listrada Gigante Garras do Abraço Implacável Presas Quebra-Ossos Couro Reforçado de Montanha Ossos de Predador Colossal Óleo de Glândulas Naturais Coração de Caçador Solitário Essência da Força Selvagem | N12: 5 | O12: 2 | P12: 5 | Q12: 1 | R12: 1 | S12: 80 | T12: 17 | U12: 2 | W12: 9 | X12: INT | AA12: Emboscada Brutal (custo 4 PM, 2x por cena) - primeiro ataque da cena causa 2d8 de dano adicional se o alvo estiver Desprevenido (CD 9, sem salvaguarda). | AB12: Couro Espesso (passivo) - resistência a dano de Frio. | AC12: Golpe Atordoante (custo 3 PM, 1x por cena) - golpe de pata que causa 2d6 de dano e o alvo faz salv. Tenacidade (CD 9) ou fica Atordoado por 1 rodada. | AF12: 6 | AG12: 0 | AH12: 8 | AI12: 0 | AJ12: 0 | AK12: 8 | AL12: 5
A13: Urso-Baleia Branco | B13: Nenhuma criatura me ensinou mais sobre aparências enganosas do que o Urso-Baleia Branco. Seu rosto transmite uma expressão quase amigável, como se estivesse constantemente satisfeito com a vida. Infelizmente, ele também considera quase tudo que encontra uma possível refeição. — Astrolong TerraNova | C13: O Urso-Baleia Branco é o maior entre todas as espécies de ursos conhecidas do mundo. Habitando regiões geladas onde terra, gelo e oceano se encontram, tornou-se o predador dominante de inúmeras costas congeladas. Diferente de outros grandes predadores que dependem de velocidade ou emboscadas elaboradas, o Urso-Baleia Branco utiliza uma estratégia que muitos aventureiros descrevem como perturbadora. Ele simplesmente se aproxima. Sem demonstrar pressa, sem rugidos e sem qualquer sinal de agressividade aparente, a criatura avança lentamente em direção ao alvo. Muitos viajantes inexperientes interpretam esse comportamento como curiosidade ou desinteresse. Quando a distância se torna pequena o suficiente, o ataque acontece. Sua explosão repentina de velocidade é tão inesperada que poucas criaturas conseguem reagir a tempo. Embora seja perfeitamente capaz de viver em terra firme, passa grande parte da vida no oceano, onde caça peixes gigantes, focas glaciais, monstros marinhos e praticamente qualquer criatura que considere vulnerável. No mar, poucos predadores rivalizam com sua eficiência. | D13: Um Urso-Baleia Branco adulto pode ultrapassar duas toneladas de peso e atingir mais de cinco metros de comprimento. Seu corpo combina características adaptadas tanto para ambientes terrestres quanto aquáticos. A estrutura é massiva, com musculatura densa escondida sob uma camada espessa de gordura isolante. Sua pelagem é predominantemente branca, porém marcada por grandes manchas negras ou cinza-escuras distribuídas pelo dorso, laterais e cabeça. A cabeça é arredondada e larga, com olhos pequenos e expressivos que frequentemente produzem uma aparência curiosamente amigável. O formato natural de sua mandíbula cria uma impressão constante de sorriso, característica responsável por inúmeros acidentes envolvendo exploradores que subestimaram a criatura. As patas são largas e poderosas, adaptadas para caminhar sobre neve profunda, gelo instável e também para impulsionar o animal durante a natação. Debaixo d'água sua coloração branca e negra se mistura aos reflexos do gelo e às sombras profundas dos mares glaciais, tornando-o surpreendentemente difícil de detectar. Quando observado do fundo para a superfície, muitas vezes parece apenas mais uma formação de gelo flutuante. Até que se mova. | E13: Terras do Norte Gelado, Terras dos Gigantes, mares glaciais, fiordes congelados e costas árticas | F13: Se existe uma criatura capaz de parecer feliz enquanto planeja devorá-lo, é o Urso-Baleia Branco. Já testemunhei um indivíduo nadando sob uma camada de gelo tão espessa que eu sequer percebi sua presença até vê-lo emergir poucos metros adiante. A maioria dos ataques ocorre porque as vítimas acreditam que a criatura está apenas passando. Na realidade, ela já tomou sua decisão há muito tempo. Filhotes são surpreendentemente brincalhões e passam horas deslizando sobre encostas congeladas. Essa diversão frequentemente termina com alguma criatura menor sendo acidentalmente esmagada. Os Gigantes do Norte respeitam profundamente essas criaturas e costumam evitar caçá-las, exceto em situações extremas. Ao contrário da maioria dos predadores, eles não parecem sentir necessidade de demonstrar dominância. Simplesmente agem como se já fossem os donos do território. Em águas profundas, sua silhueta desaparece quase completamente. Mais de um marinheiro jurou que o mar simplesmente abriu uma boca e engoliu sua embarcação. | G13: Besta Mágica | H13: Besta | I13: Terra e Água | J13: Elite | K13: Enorme | L13: Territorial, Agressivo e Predador Semimarinho | M13: Pelagem Glacial Colossal Dentes de Quebra-Gelo Garras Oceânicas Couro Marinho Reforçado Gordura Alquímica Glacial Óleo de Respiração Profunda Ossos de Titã Polar Coração do Predador dos Mares Gelados Essência da Maré Congelante | N13: 5 | O13: 1 | P13: 5 | Q13: 1 | R13: 2 | S13: 80 | T13: 16 | U13: 4 | W13: 10 | X13: PRE | AA13: Mergulho Devastador (custo 4 PM, 2x por cena) - submerge e ressurge sob um alvo, causando 2d8 de dano de Água extra e empurrando 3m (CD 10, salv. Atletismo para reduzir o empurrão a 1,5m). | AB13: Domínio Glacial (passivo) - resistência a dano de Frio e Água. | AC13: Onda de Impacto (custo 3 PM, 1x por cena) - bate na água criando ondas em 6m; criaturas na área fazem salv. Reflexo (CD 10) ou sofrem 2d6 de dano e caem. | AF13: 6 | AG13: 0 | AH13: 8 | AI13: 0 | AJ13: 0 | AK13: 8 | AL13: 5
A14: Urso Anão Marrom | B14: Entre todos os ursos que cataloguei, este é certamente o mais preguiçoso. Já encontrei um indivíduo dormindo no mesmo tronco durante três dias consecutivos. No quarto dia, ele apenas mudou de lado e continuou dormindo. — Astrolong TerraNova | C14: O Urso Anão Marrom é a menor espécie conhecida entre os ursos do mundo, embora seu conceito de pequeno ainda seja consideravelmente maior que o de muitas outras criaturas. Extremamente dóceis quando bem tratados, tornaram-se uma das poucas Bestas Mágicas que podem conviver pacificamente com povos civilizados. Em algumas regiões do Continente Ancestral, especialmente entre Faunos e comunidades élficas mais isoladas, é comum encontrar indivíduos criados desde filhotes como companheiros e animais de guarda. Apesar de sua aparência amigável, continuam sendo criaturas fortes e resistentes. Quando ameaçados, podem utilizar sua poderosa musculatura para afastar predadores ou proteger seus cuidadores. Sua rotina diária consiste principalmente em comer, descansar e procurar novos locais confortáveis para dormir. Muitos indivíduos passam mais da metade da vida descansando. | D14: Um Urso Anão Marrom adulto pesa aproximadamente 200 quilos e possui altura semelhante à de um humanoide adulto quando apoiado sobre as quatro patas. Seu corpo é compacto e robusto, coberto por uma espessa pelagem marrom que varia entre tons castanhos claros e escuros. Possui patas largas adaptadas para caminhar por florestas densas, troncos caídos e terrenos irregulares. Sua cabeça é arredondada, com orelhas pequenas, focinho curto e olhos expressivos que frequentemente transmitem uma aparência tranquila e curiosa. Diferente das demais espécies de ursos, sua constituição corporal favorece conforto e resistência ao invés de velocidade ou agressividade. É comum encontrar folhas, flores e pequenos galhos presos à sua pelagem após longos períodos de sono em clareiras ou bosques. Quando descansando, costuma enrolar-se como uma enorme bola de pelos, tornando difícil distinguir a criatura de um monte de folhas secas à distância. | E14: Pacífico, Sonolento e Sociável | F14: Se a preguiça fosse uma forma de magia, os Ursos Anões Marrons seriam arquimagos. Muitos aventureiros confundem indivíduos adormecidos com pedras cobertas por musgo. Alguns aprendem o erro da maneira mais constrangedora possível quando a 'pedra' começa a roncar. Os filhotes desenvolvem forte apego a criaturas que os alimentam regularmente. Já conheci um que seguiu um ferreiro anão por quase dois meses inteiros. Apesar de sua natureza tranquila, jamais tente acordar um Urso Anão Marrom tocando seu alimento. Alguns instintos permanecem fortes independentemente da personalidade da criatura. As Dríades gostam particularmente da companhia desses animais. Dizem que seu ronco ajuda as árvores jovens a crescerem mais saudáveis. Até hoje não encontrei evidências que comprovem essa teoria. Uma vez observei um indivíduo dormir durante uma tempestade inteira. A chuva parou antes que ele acordasse. | G14: Besta Mágica | H14: Besta | I14: Terra | J14: Comum | K14: Médio | L14: Reino dos Elfos, Terras dos Faunos e florestas temperadas do Continente Ancestral | M14: Tesouros Pelagem Marrom Macia Garras de Escavação Couro Flexível Almofadas Plantares Resistentes Presas de Urso Anão Mel Selvagem Armazenado na Pelagem Essência da Tranquilidade Coração de Guardião da Floresta | N14: 2 | O14: 2 | P14: 2 | Q14: 0 | R14: 1 | S14: 24 | T14: 13 | U14: 2 | W14: 9 | X14: PRE | AA14: Abraço de Urso (custo 1 PM, 1x por cena) - agarra um alvo, que faz salv. Atletismo (CD 9) ou fica Aprisionado por 1 rodada. | AF14: 2 | AG14: 0 | AH14: 1 | AI14: 0 | AJ14: 0 | AK14: 2 | AL14: 2
A15: Urso Negro Dracônico | B15: Poucas criaturas conseguem ser tão poderosas e tão determinadas a evitar problemas quanto o Urso Negro Dracônico. Em minhas viagens pelo Reino dos Dracônicos, vi vários deles fugirem de viajantes como se fossem culpados de algum crime. O curioso é que, quando finalmente são obrigados a lutar, lembram a todos por que até os dragões respeitam sua força. — Astrolong TerraNova | C15: O Urso Negro Dracônico é uma das criaturas mais curiosas do Reino dos Dracônicos. Apesar de possuir força suficiente para enfrentar muitos predadores da região, seu comportamento natural é extremamente reservado. Quando detecta a presença de outras criaturas, sua primeira reação quase sempre é se afastar discretamente. Muitos viajantes sequer percebem que estiveram próximos de um desses animais. Essa natureza tímida faz com que conflitos sejam raros. No entanto, quando encurralado ou obrigado a proteger seu território, o Urso Negro Dracônico revela uma força assustadora. Seu corpo combina a resistência típica dos grandes ursos com características herdadas da influência dracônica presente nas montanhas do reino. Essa combinação resulta em uma criatura incrivelmente resistente, veloz e surpreendentemente ágil para seu porte. São animais solitários, encontrando-se apenas durante a época reprodutiva ou quando uma mãe está cuidando de seus filhotes. | D15: Um Urso Negro Dracônico adulto pesa entre 300 e 400 quilos e pode atingir mais de três metros de altura quando se ergue sobre as patas traseiras. Seu corpo é coberto por uma combinação única de pelagem espessa e escamas dracônicas naturais. As escamas surgem principalmente nos ombros, costas, pescoço, patas dianteiras e ao redor da cabeça, formando uma proteção natural semelhante a uma armadura. Existem diversas colorações conhecidas: Escamas Negras, Escamas Brancas, Escamas Marrons ou Escamas Azuladas A pelagem geralmente acompanha ou complementa a cor predominante das escamas. Sua musculatura é extremamente desenvolvida, especialmente nas patas dianteiras, capazes de partir troncos ou deslocar grandes pedras com facilidade. Apesar da aparência robusta, são incrivelmente rápidos. Quando assustados, conseguem atravessar trilhas montanhosas em velocidade comparável a um cavalo em disparada, desaparecendo entre árvores e rochas em poucos instantes. Seus olhos apresentam colorações vibrantes, frequentemente douradas, azuis ou âmbar, refletindo a influência mágica de seus ancestrais dracônicos. | E15: Reino dos Dracônicos, florestas montanhosas, vales elevados, encostas rochosas e cavernas naturais | F15: Durante anos procurei um Urso Negro Dracônico de escamas azuis. Quando finalmente encontrei um, ele fugiu antes que eu pudesse terminar a primeira anotação. Muitos caçadores fracassam em localizar essa espécie não porque ela seja rara, mas porque ela evita ser encontrada. Os Dracônicos acreditam que encontrar um Urso Negro Dracônico próximo à sua moradia é sinal de que a região é segura e rica em mana natural. Filhotes costumam subir em pedras elevadas para observar o mundo ao redor. Curiosamente, mantêm esse hábito durante toda a vida. Já observei um adulto mover uma pedra maior que uma carroça para alcançar um ninho de insetos. Em seguida, passou quase uma hora alimentando-se tranquilamente. Apesar de sua força impressionante, a maioria das cicatrizes encontradas em indivíduos adultos foi causada por quedas em encostas e não por combates. Se um Urso Negro Dracônico estiver correndo na sua direção, não entre em pânico. Provavelmente ele está fugindo de alguma coisa e você apenas está no caminho. | G15: Besta Mágica | H15: Besta | I15: Terra, Vento e Fogo | J15: Menor | K15: Grande | L15: Tímido, Arisco e Territorial apenas quando encurralado | M15: Escamas Dracônicas Naturais Pelagem Dracônica Garras de Montanha Presas Reforçadas Couro Escamado Ossos de Alta Densidade Núcleo de Mana Dracônica Essência da Velocidade Selvagem Coração do Guardião das Montanhas | N15: 3 | O15: 2 | P15: 3 | Q15: 0 | R15: 1 | S15: 39 | T15: 14 | U15: 2 | W15: 9 | X15: PRE | AA15: Fôlego Quente (custo 2 PM, 2x por cena) - sopro curto que causa 1d6 de dano de Fogo em um alvo a 3m (CD 9, salv. Reflexo para metade). | AF15: 2 | AG15: 0 | AH15: 4 | AI15: 0 | AJ15: 0 | AK15: 4 | AL15: 2
A16: Preguiça de Chamas Vermelhas | B16: A primeira impressão que tive ao encontrar uma Preguiça de Chamas Vermelhas foi a de observar uma colina viva emergindo das profundezas da terra. A segunda impressão foi perceber que a colina estava mastigando um bloco de obsidiana como se fosse uma fruta madura. — Astrolong TerraNova | C16: A Preguiça de Chamas Vermelhas é uma gigantesca criatura subterrânea adaptada às regiões mais quentes do mundo. Habitando túneis profundos abaixo das Ilhas dos Dragões, raramente é vista na superfície, passando a maior parte da vida próxima a câmaras vulcânicas e rios subterrâneos de magma. Apesar do tamanho impressionante e das garras capazes de perfurar rochas, possui temperamento surpreendentemente tranquilo. Alimenta-se principalmente de minerais ricos em mana térmica, sendo particularmente conhecida por seu gosto incomum por obsidiana. Seu metabolismo é tão adaptado ao calor extremo que temperaturas capazes de matar a maioria das criaturas não lhe causam qualquer desconforto. Quando ameaçada, utiliza suas enormes patas para desferir golpes poderosos capazes de afastar predadores. Entretanto, seu comportamento natural não é lutar, mas escapar. Após alguns ataques defensivos, normalmente tenta retornar aos túneis subterrâneos onde sua enorme capacidade de escavação a torna praticamente impossível de perseguir. | D16: Uma Preguiça de Chamas Vermelhas adulta pode ultrapassar quatro metros de comprimento e atingir facilmente mais de uma tonelada de peso. Seu corpo é coberto por uma pelagem extremamente espessa de coloração vermelha, alaranjada e negra, lembrando brasas vivas sob determinadas condições de iluminação. Sob essa camada de pelos existe uma pele resistente capaz de suportar temperaturas extremas e impactos consideráveis. Sua anatomia combina características de escavadores subterrâneos com uma estrutura corporal robusta e pesada. As patas dianteiras são enormes e musculosas, terminando em garras curvas capazes de cortar rocha vulcânica relativamente macia. Essas mesmas garras são utilizadas para abrir túneis, derrubar obstáculos e defender-se quando necessário. O focinho é largo e adaptado para detectar minerais enterrados, enquanto seus olhos são pequenos e protegidos contra poeira, cinzas e fragmentos de pedra. Muitos indivíduos apresentam veios brilhantes percorrendo a pelagem, produzidos pelo acúmulo de minerais mágicos consumidos ao longo da vida. Quando descansam próximos ao magma, frequentemente parecem pequenas colinas cobertas por vegetação avermelhada e pedras vulcânicas. | E16: Ilhas dos Dragões, campos vulcânicos, túneis subterrâneos, cavernas de magma e regiões próximas a rios de lava | F16: A obsidiana parece ser sua refeição favorita. Já observei uma delas ignorar completamente uma árvore frutífera para atravessar uma encosta inteira em busca de uma única formação rochosa. Apesar da aparência intimidadora, são criaturas extraordinariamente pacientes. Uma vez acompanhei um indivíduo que levou quase duas horas para decidir atravessar um riacho. Sua pelagem é tão espessa que muitas armas comuns sequer conseguem alcançar a pele abaixo dela. Os Dragões costumam ignorá-las completamente. Alguns estudiosos acreditam que isso ocorre porque ambas as espécies compartilham habitats semelhantes há milhares de anos. Filhotes passam boa parte do tempo brincando de cavar túneis. O resultado normalmente é uma quantidade impressionante de desmoronamentos acidentais. Quando assustadas, produzem um som grave que pode ser ouvido através do solo antes mesmo da criatura surgir na superfície. Se encontrar um túnel perfeitamente circular próximo a uma região vulcânica, existe uma boa chance de uma Preguiça de Chamas Vermelhas estar dormindo em algum lugar próximo. | G16: Besta Mágica | H16: Besta | I16: Terra e Fogo | J16: Menor | K16: Grande | L16: Pacífico, Escavador e Arisco quando ameaçado | M16: Pelagem de Chamas Vermelhas Garras Escavadoras Vulcânicas Presas Minerais Couro Resistente ao Calor Cristais de Obsidiana Digestiva Núcleo Térmico Natural Ossos Reforçados por Mana Ígnea Essência da Terra Ardente Coração da Escavadora Vulcânica | N16: 3 | O16: 1 | P16: 4 | Q16: 0 | R16: 1 | S16: 42 | T16: 13 | U16: 2 | W16: 9 | X16: PRE | AA16: Calor Subterrâneo (passivo) - resistência a dano de Fogo; ataques desarmados causam +1d4 de Fogo. | AB16: Lava Cuspida (custo 2 PM, 2x por cena) - cospe lava em um alvo a 6m causando 1d8 de dano de Fogo e aplicando Em Chamas (CD 9, salv. Reflexo para metade do dano e sem Em Chamas). | AF16: 4 | AG16: 0 | AH16: 5 | AI16: 0 | AJ16: 0 | AK16: 0 | AL16: 3
A17: Imperador dos Céus | B17: Algumas criaturas dominam uma floresta. Outras dominam uma montanha. O Imperador dos Céus domina o horizonte. Quando sua sombra atravessa as nuvens, até os dragões observam com cautela. Durante minhas expedições, testemunhei um deles arrancar um jovem dragão do céu antes que a criatura percebesse o perigo. — Astrolong TerraNova | C17: O Imperador dos Céus é considerado por muitos estudiosos o maior predador voador natural do mundo. Habitando as montanhas mais altas e os penhascos mais inacessíveis das Terras dos Gigantes e das Ilhas dos Dragões, essas criaturas passam grande parte da vida sobrevoando vastas regiões em busca de presas. Sua reputação é tão impressionante que diversas espécies alteram rotas migratórias para evitar seus territórios. Diferente dos dragões, que frequentemente utilizam inteligência, magia e força bruta, o Imperador dos Céus confia em velocidade, precisão e domínio absoluto dos ventos. São capazes de realizar mergulhos tão rápidos que poucos seres conseguem reagir antes do impacto. Embora normalmente cacem grandes mamíferos, serpentes gigantes, criaturas voadoras e monstros montanheses, não é incomum atacarem jovens dragões ou indivíduos feridos. Mais impressionante ainda é sua relação com o Vale dos Abissais. Diversos exploradores relataram observar Imperadores dos Céus mergulhando nas profundezas do vale para capturar criaturas abissais que tentam emergir para a superfície. Por esse motivo, algumas culturas acreditam que essas aves gigantes foram criadas pelos próprios Primordiais para impedir que os horrores das profundezas escapem livremente. | D17: Um Imperador dos Céus adulto possui envergadura que pode ultrapassar vinte metros de uma ponta da asa à outra. Seu corpo é coberto por penas extremamente densas que combinam tons de cinza-prateado, negro, branco e dourado. A cabeça apresenta uma plumagem majestosa que lembra uma coroa natural formada pelo vento e pelo tempo. Seu bico é longo, curvado e poderoso o suficiente para perfurar escamas de dragões jovens. As garras são enormes e possuem força suficiente para capturar criaturas que pesam várias centenas de quilos durante o voo. As asas são largas e aerodinâmicas, adaptadas tanto para longos voos de patrulha quanto para mergulhos de velocidade extrema. Durante uma caçada, as penas se fecham contra o corpo, transformando a criatura em um projétil vivo capaz de atingir velocidades absurdas. Seus olhos dourados conseguem detectar movimentos a quilômetros de distância, mesmo através de tempestades, neblina ou nuvens densas. Quando planando nas correntes de ar, sua silhueta frequentemente é confundida com uma pequena nuvem escura cruzando o céu. | E17: Terras dos Gigantes, Ilhas dos Dragões, Vale dos Abissais, grandes cadeias montanhosas e ocasionalmente os limites da Floresta dos Orcs | F17: Se você consegue ver um Imperador dos Céus, saiba que ele já o viu muito antes. Os Gigantes acreditam que essas criaturas carregam mensagens dos ventos ancestrais. Após observá-las por muitos anos, não estou completamente convencido de que estejam errados. Já encontrei ninhos construídos em locais tão altos que sequer consegui enxergar o fundo dos penhascos abaixo deles. Filhotes passam anos treinando voo antes de realizarem sua primeira caçada independente. Dragões adultos raramente entram em conflito direto com um Imperador dos Céus. Nenhum dos lados parece interessado em descobrir quem venceria. A maior pena que encontrei media quase dois metros de comprimento. Durante uma expedição ao Vale dos Abissais, observei um indivíduo emergir carregando uma criatura que jamais consegui identificar. A batalha provavelmente começou muito abaixo de onde meus olhos podiam alcançar. Existe uma antiga lenda entre os povos do norte que afirma que o primeiro som ouvido pelo mundo após sua criação foi o grito de um Imperador dos Céus cruzando os ventos primordiais. | G17: Besta Mágica Suprema | H17: Ave | I17: Sagrado e Vento | J17: Lendário | K17: Enorme | L17: Territorial, Orgulhoso e Predador Aéreo Absoluto | M17: Pena Imperial dos Céus Garra de Caçador de Dragões Bico Celestial Olhos do Observador dos Ventos Asas de Corrente Ascendente Ossos Aerodinâmicos Núcleo de Voo Supremo Essência do Predador Celestial Coração do Imperador dos Céus | N17: 4 | O17: 4 | P17: 3 | Q17: 2 | R17: 4 | S17: 104 | T17: 21 | U17: 22 | W17: 12 | X17: PRE | AA17: Mergulho do Imperador (custo 4 PM, 3x por cena) - ataque em mergulho com vantagem que causa 3d8 de dano extra; se acertar, empurra o alvo 6m e o alvo faz salv. Tenacidade (CD 12) ou fica Atordoado por 1 rodada. | AB17: Garras Celestiais (custo 6 PM, 2x por cena) - ataque sagrado que causa 3d8 de dano e ignora metade da Defesa do alvo. | AC17: Vento dos Picos (passivo) - nunca sofre penalidade de deslocamento por terreno montanhoso ou ventos fortes. | AF17: 6 | AG17: 8 | AH17: 4 | AI17: 6 | AJ17: 0 | AK17: 8 | AL17: 6
A18: Dragões Menores | B18: Quando os aventureiros escutam a palavra 'dragão', imaginam imediatamente criaturas capazes de destruir reinos inteiros. Os Dragões Menores são a prova de que nem todo dragão nasce para governar o mundo. Ainda assim, recomendo o mesmo cuidado que se teria diante de qualquer outra criatura capaz de incendiar uma floresta, provocar uma tempestade ou esmagar uma carroça inteira sem esforço. — Astrolong TerraNova | C18: Os Dragões Menores representam a espécie dracônica mais comum encontrada pelos povos do mundo. Embora sejam chamados de menores, ainda figuram entre as criaturas mais poderosas que um aventureiro pode encontrar na natureza. Um adulto saudável mede entre sete e dez metros de comprimento, possuindo força, inteligência e capacidades mágicas muito superiores às da maioria das Bestas Mágicas. Diferente dos Dragões Anciões e de outras linhagens superiores, os Dragões Menores raramente estabelecem domínios permanentes. Preferem vagar pelo mundo, ocupando territórios temporários conforme a disponibilidade de alimento, mana e segurança. Todos possuem uma forte ligação elemental, característica que influencia sua aparência, comportamento e habilidades naturais. Apesar de viverem espalhados por praticamente todos os continentes, há um fenômeno observado por estudiosos há séculos: durante a época reprodutiva, todos retornam às Ilhas dos Dragões. Ninguém sabe exatamente como conseguem localizar o arquipélago mesmo após décadas longe dele. Alguns estudiosos acreditam que os dragões possuem uma conexão mágica ancestral que os guia através dos mares e céus. | D18: Todos os Dragões Menores compartilham uma estrutura corporal semelhante. Possuem corpos longos e musculosos, asas amplas adaptadas ao voo de longa distância, pescoço flexível, cauda poderosa e escamas resistentes que funcionam como armaduras naturais. A principal diferença entre eles está em sua afinidade elemental. Dragão Menor da Terra Coberto por escamas marrons, ocres e douradas. Seu corpo é mais robusto e pesado que o das demais variantes, com chifres largos e placas ósseas reforçadas. Costumam habitar montanhas, cavernas e vales rochosos. Dragão Menor dos Ventos Coberto por escamas verdes e esmeralda. Possui corpo mais esguio e asas proporcionalmente maiores. São os voadores mais habilidosos entre os Dragões Menores e frequentemente estabelecem ninhos em grandes alturas. Dragão Menor das Águas Coberto por escamas azuladas que variam entre azul-claro e azul-profundo. Possuem membranas entre as garras, maior capacidade pulmonar e facilidade para mergulhos prolongados. Habitam lagos, rios, costas marítimas e arquipélagos. Dragão Menor dos Trovões Coberto por escamas em tons de violeta claro, prata e azul elétrico. Pequenas descargas elétricas costumam percorrer seu corpo quando estão irritados ou excitados. São conhecidos por sua velocidade e temperamento imprevisível. Dragão Menor das Chamas Coberto por escamas vermelhas, alaranjadas e douradas. Possuem temperatura corporal superior à das demais variantes e são frequentemente encontrados próximos a vulcões e regiões montanhosas. São os mais agressivos entre os Dragões Menores. | E18: Todo o mundo conhecido, retornando às Ilhas dos Dragões durante a época reprodutiva | F18: A primeira mentira que ouvi sobre dragões foi que todos acumulam tesouros. A segunda foi que todos gostam de fazê-lo. Já observei um Dragão Menor dos Ventos permanecer em voo por quase dois dias inteiros sem pousar. Os Dragões Menores das Águas frequentemente acompanham embarcações por quilômetros sem qualquer intenção hostil. Acredito que façam isso apenas por curiosidade. Entre todas as variantes, os Dragões Menores dos Trovões são os mais difíceis de estudar. Eles raramente permanecem no mesmo lugar por muito tempo. A migração para as Ilhas dos Dragões continua sendo um dos maiores mistérios da zoologia moderna. Mesmo indivíduos criados longe do arquipélago acabam retornando quando atingem a maturidade. Embora sejam considerados menores, ainda são perfeitamente capazes de derrotar praticamente qualquer predador comum do mundo. O Imperador dos Céus é uma das poucas criaturas naturais que ocasionalmente caça jovens Dragões Menores. Felizmente para os dragões, essa ave colossal é muito mais rara. | G18: Dragão Comum | H18: Dragão | I18: Dependente da Cor | J18: Elite | K18: Grande | L18: Territorial, Inteligente e Solitário | M18: Tesouros Escamas Dracônicas Elementais Garras de Dragão Menor Presas Dracônicas Ossos Encantados Coração Elemental Sangue Dracônico Núcleo de Mana Dracônica Chifre de Dragão Menor Essência Elemental Dracônica | N18: 4 | O18: 3 | P18: 4 | Q18: 2 | R18: 1 | S18: 77 | T18: 18 | U18: 12 | W18: 10 | X18: INT | AA18: Sopro Elemental (custo 5 PM, 3x por cena) - cone de 9m de dano elemental conforme a cor (2d8); criaturas na área fazem salv. Reflexo (CD 10) para metade do dano. | AB18: Voo de Combate (passivo) - +2 na Defesa contra ataques corpo a corpo enquanto voando. | AC18: Garras Afiadas (custo 2 PM, 2x por cena) - ataque corpo a corpo que causa 2d8 de dano adicional. | AF18: 5 | AG18: 5 | AH18: 5 | AI18: 0 | AJ18: 0 | AK18: 8 | AL18: 4
A19: Dragões Maiores | B19: Se os Dragões Menores representam a força da natureza, os Dragões Maiores representam sua vontade. Poucas criaturas no mundo conseguem rivalizar com seu intelecto, e menos ainda sobrevivem tempo suficiente para descobrir que muitos deles são capazes de conversar. A primeira vez que um Dragão Maior respondeu a uma pergunta minha, fiquei tão surpreso que esqueci completamente de anotar a resposta. — Astrolong TerraNova | C19: Os Dragões Maiores ocupam uma posição intermediária entre os Dragões Menores e os lendários Dragões Anciões. Com corpos que podem atingir entre quinze e vinte metros de comprimento, são criaturas de imenso poder físico e mágico. Porém, o que verdadeiramente os diferencia não é seu tamanho, mas sua inteligência. Ao contrário de muitos dragões menores, os Dragões Maiores são capazes de raciocínio complexo, planejamento estratégico e comunicação verbal. Muitos aprendem a Língua Comum, enquanto praticamente todos dominam o idioma Dracônico. Alguns chegam a negociar territórios, formar alianças temporárias ou estabelecer relações relativamente pacíficas com povos civilizados. Atualmente, três grandes espécies são reconhecidas pelos estudiosos. Cada uma representa uma força distinta presente no mundo. | D19: Dragão Maior da Ilusão Conhecido popularmente como Dragão Púrpura. Habitam regiões ligadas aos Feéricos e às antigas concentrações de mana natural. Seu corpo é coberto por escamas púrpuras, lilases e prateadas que parecem mudar de tonalidade conforme a iluminação. Possuem olhos brilhantes sem pupilas visíveis e asas que frequentemente produzem reflexos ilusórios ao se moverem. São mestres da manipulação sensorial e frequentemente utilizam ilusões para evitar combates desnecessários. Muitos viajantes sequer percebem que encontraram um desses dragões. Dragão Maior da Tempestade Conhecido como Dragão Tempestade Negro. Habita principalmente as montanhas e vales elevados do Reino dos Dracônicos. Suas escamas possuem coloração negra profunda com reflexos azul-escuros e prata. Quando irritados, pequenas descargas elétricas percorrem seu corpo. As asas são largas e densas, capazes de suportar voos durante tempestades violentas. São considerados os mais orgulhosos e territorialistas entre os Dragões Maiores. Diversos clãs dracônicos os reverenciam como símbolos vivos da força dos céus. Dragão Maior de Cristal Habitante da Ilha dos Cristais. Seu corpo é coberto por formações cristalinas naturais que crescem sobre as escamas ao longo da vida. As cores variam entre azul-claro, violeta, branco, rosa e tons translúcidos semelhantes a gemas lapidadas. Quando expostos à luz, seus corpos produzem reflexos que podem ser vistos a quilômetros de distância. São considerados os mais contemplativos e sábios entre os Dragões Maiores. Muitos estudiosos acreditam que parte de sua memória fica armazenada nos próprios cristais que crescem em seus corpos. | E19: Áreas de Dominio Feéricas, Reino dos Dracônicos e Ilha dos Cristais | F19: Existe uma enorme diferença entre enfrentar um dragão e conversar com um. Em ambos os casos, é importante escolher cuidadosamente suas palavras. Os Dragões Púrpura costumam responder perguntas com outras perguntas. Ainda não descobri se isso é sabedoria ou diversão. Já observei um Dragão Tempestade permanecer imóvel durante uma tempestade inteira apenas observando os relâmpagos atingirem as montanhas. Os Dragões de Cristal possuem uma estranha fascinação por conhecimento. Um deles trocou comigo um fragmento de cristal ancestral em troca de um livro que eu havia terminado de ler. Ao contrário do que muitos acreditam, a maioria dos Dragões Maiores prefere evitar guerras. Eles geralmente consideram conflitos entre humanoides problemas temporários. Alguns indivíduos vivem por séculos e acumulam conhecimento suficiente para rivalizar com bibliotecas inteiras. A criatura mais educada que conheci em minhas viagens foi um Dragão Maior de Cristal. A segunda mais educada também. | G19: Dragão Superior | H19: Dragão | I19: Arcano | J19: Lendário | K19: Colossal | L19: Inteligente, Territorial e Racional | M19: Escamas de Dragão Maior Garras Dracônicas Superiores Presas de Dragão Maior Sangue Dracônico Superior Ossos Encantados Coração Dracônico Núcleo de Mana Superior Essência do Dragão Maior Tesouros Específicos Cristal de Ilusão - Dragão Púrpura Olho Feérico Dracônico - Dragão Púrpura Essência da Miragem - Dragão Púrpura Núcleo Tempestuoso - Dragão Tempestade Negro Escama Condutora - Dragão Tempestade Negro Essência do Relâmpago - Dragão Tempestade Negro Cristais Dracônicos Puros - Dragão de Cristal Fragmento de Memória Cristalina - Dragão de Cristal Essência da Sabedoria Mineral - Dragão de Cristal | N19: 5 | O19: 3 | P19: 4 | Q19: 3 | R19: 2 | S19: 107 | T19: 20 | U19: 18 | W19: 17 | X19: INT | AA19: Sopro Devastador (custo 6 PM, 2x por cena) - cone de 12m com 3d8 de dano elemental (CD 17, salv. Reflexo para metade). | AB19: Voo Imperial (passivo) - +2 na Defesa contra ataques corpo a corpo e ignora terrenos difíceis. | AC19: Presença Aterradora (custo 3 PM, 1x por cena) - inimigos em 9m fazem salv. Vontade (CD 17) ou ficam Amedrontados por 1 rodada. | AD19: Garras Reais (custo 3 PM, 2x por cena) - ataque corpo a corpo que causa 3d8 de dano e aplica Sangramento. | AF19: 6 | AG19: 6 | AH19: 6 | AI19: 4 | AJ19: 6 | AK19: 8 | AL19: 2
A20: Dragões Anciões | B20: Durante toda minha vida ouvi histórias sobre os Dragões Anciões. Reis afirmam ter visto suas sombras cruzando o horizonte. Navegadores juram que alguns dormem sob os oceanos. Gigantes contam lendas onde eles conversavam com os Primordiais. Quanto a mim? Nunca encontrei provas definitivas. Houve uma única ocasião, durante uma expedição às Ilhas dos Dragões, em que observei algo voando acima das nuvens. A criatura era tão grande que por alguns instantes ocultou uma montanha inteira. Talvez fosse um Dragão Ancião. Talvez não. Ainda hoje não sei responder. — Astrolong TerraNova | C20: Os Dragões Anciões são considerados as criaturas mais antigas entre todas as linhagens dracônicas conhecidas. As poucas referências existentes sobre eles remontam à Era das Sementes, período em que o mundo ainda assumia sua forma definitiva e as forças primordiais moldavam continentes, oceanos e céus. Diferentemente dos Dragões Menores e dos Dragões Maiores, não existem registros confiáveis de encontros recentes com indivíduos dessa categoria. Grande parte do conhecimento disponível provém de lendas, inscrições antigas, relatos fragmentados e tradições preservadas por povos extremamente antigos. Segundo essas histórias, os Dragões Anciões não governavam territórios. Eles governavam eras. Diversas culturas afirmam que montanhas inteiras surgiram onde um Dragão Ancião escolheu repousar. Outras alegam que tempestades capazes de durar meses eram apenas consequências involuntárias de seus voos. Embora muitas dessas histórias provavelmente sejam exageradas, existe um detalhe curioso: Todas as civilizações antigas descrevem criaturas semelhantes. Mesmo povos separados por oceanos inteiros registram dragões colossais capazes de obscurecer o sol. Tal coincidência leva muitos estudiosos a acreditar que os Dragões Anciões realmente existiram. E talvez ainda existam. | D20: Nenhum estudioso moderno conseguiu documentar um Dragão Ancião de forma conclusiva. As descrições variam entre diferentes culturas, mas apresentam características recorrentes. Um Dragão Ancião adulto seria capaz de atingir ou ultrapassar sessenta metros de comprimento. Seu corpo possuiria proporções monumentais, com asas tão vastas que poderiam projetar sombras sobre florestas inteiras. As escamas são frequentemente descritas como maiores que escudos de guerra, variando entre dourado, negro profundo, branco-prateado ou cores impossíveis de definir. Alguns relatos afirmam que suas escamas não refletem apenas luz, mas também mana. Os chifres seriam comparáveis a torres de castelos, enquanto suas garras poderiam rasgar rochas como se fossem solo macio. Diversos registros antigos mencionam olhos luminosos visíveis mesmo durante tempestades. Outros descrevem corpos cobertos por runas naturais que brilham quando a criatura utiliza seus poderes. A característica mais recorrente em todos os relatos, porém, é o tamanho. Independentemente da cultura ou época, todos concordam que um Dragão Ancião faz qualquer outro dragão parecer pequeno. | E20: Desconhecido | F20: Se os Dragões Menores são reis e os Dragões Maiores são imperadores, os Dragões Anciões pertencem a uma categoria completamente diferente. Já encontrei mais pessoas afirmando ter visto um Dragão Ancião do que pessoas capazes de descrever exatamente o que viram. Os Gigantes preservam lendas segundo as quais alguns Dragões Anciões participaram da construção do mundo ao lado dos Primordiais. Diversos dragões evitam determinadas montanhas consideradas sagradas. Talvez seja superstição. Talvez seja memória ancestral. Uma antiga inscrição encontrada nas Ilhas dos Dragões afirmava: 'Quando o último Ancião despertar, os céus recordarão seu verdadeiro dono.' Ainda não sei o que isso significa. Caso um dia você encontre um Dragão Ancião, recomendo duas coisas: observe atentamente e corra. A ordem é opcional. A única criatura que acredito ter visto sobrevoando as Ilhas dos Dragões possuía asas maiores do que qualquer coisa que já observei. Estava tão distante que não consegui distinguir detalhes. Às vezes me pergunto se realmente vi algo ou se apenas vi uma nuvem assumindo uma forma impossível. Curiosamente, os Dragões Maiores raramente falam sobre os Anciões. Considerando o orgulho natural dos dragões, isso talvez seja a evidência mais convincente de todas. | G20: Dragão Primordial | H20: Dragão | I20: Arcano | J20: Cataclísmico | K20: Titânico | L20: Desconhecido | M20: Escamas Anciãs Sangue Primordial Dracônico Garras dos Primeiros Céus Presas de Cataclismo Ossos Eternos Coração Ancestral Núcleo de Mana Infinita Chifres dos Primórdios Essência do Primeiro Dragão | N20: 5 | O20: 4 | P20: 5 | Q20: 4 | R20: 5 | S20: 215 | T20: 26 | U20: 38 | W20: 23 | X20: PRE | AA20: Sopro Primordial (custo 10 PM, 1x por cena) - cone de 18m com 4d10 de dano elemental (CD 23, salv. Reflexo para metade, mas sempre sofre Lentidão por 2 rodadas). | AB20: Ira Ancestral (custo 6 PM, 2x por cena) - realiza dois ataques corpo a corpo adicionais, cada um causando 4d10 de dano. | AC20: Couraça Dracônica (passivo) - resistência a todos os danos elementais e redução de 5 pontos em qualquer dano recebido. | AD20: Voo Tempestuoso (custo 4 PM, 1x por cena) - voa até 18m criando onda de choque; criaturas no caminho fazem salv. Atletismo (CD 23) ou ficam Atordoadas por 1 rodada e sofrem 3d10 de dano de Trovão. | AE20: Grito Dracônico (custo 8 PM, 1x por cena) - todas as criaturas em 18m fazem salv. Vontade (CD 23) ou ficam Amedrontadas e Silenciadas por 2 rodadas. | AF20: 8 | AG20: 8 | AH20: 10 | AI20: 10 | AJ20: 10 | AK20: 12 | AL20: 8
A21: Araknis Tricolor | B21: Se existe uma criatura que pode ser encontrada em praticamente qualquer floresta do mundo, é o Araknis Tricolor. Pequeno, discreto e frequentemente ignorado pelos viajantes, ele é responsável por ensinar uma importante lição aos aventureiros: tamanho e perigo raramente caminham juntos. — Astrolong TerraNova | C21: Os Araknis Tricolores são a espécie mais comum entre todos os Araknis catalogados até o momento. Habitam praticamente todas as florestas do mundo, desde os bosques élficos mais antigos até as matas úmidas das Terras Devastadas. Sua incrível capacidade de adaptação permitiu que ocupassem quase todos os ecossistemas arborizados conhecidos. Apesar de pequenos, desempenham papel importante no equilíbrio natural das florestas, controlando populações de insetos, pequenos roedores e outras criaturas diminutas. Normalmente evitam criaturas maiores, preferindo permanecer ocultos em folhas, galhos, troncos ocos ou entre raízes. Quando ameaçados, porém, tornam-se surpreendentemente perigosos. Seu veneno raramente é letal para criaturas de grande porte, mas provoca dor intensa, febre, tontura e inchaço localizado. Para pequenos animais, entretanto, a toxina pode ser fatal. Por serem extremamente numerosos, muitos estudiosos acreditam que os Araknis Tricolores representem a base evolutiva das demais espécies de Araknis espalhadas pelo mundo. | D21: Um Araknis Tricolor adulto mede entre quinze e trinta centímetros de comprimento. Seu corpo possui oito patas finas cobertas por pequenos pelos sensoriais que detectam vibrações no ambiente. O nome da espécie vem da combinação de três cores vibrantes presentes em seu exoesqueleto e abdômen. As combinações variam conforme a região onde vivem, mas geralmente incluem: - Vermelho, Amarelo e Preto. -Azul, Branco e Preto. - Verde, Amarelo e Marrom. - Laranja, Preto e Cinza. As cores funcionam como um aviso natural para possíveis predadores. Suas presas inoculadoras de veneno são pequenas, porém extremamente eficientes. Os olhos múltiplos oferecem excelente percepção de movimento, tornando difícil surpreender um indivíduo atento. Muitos exemplares produzem teias resistentes utilizadas tanto para caça quanto para construção de pequenos abrigos. | E21: Florestas de todo o mundo conhecido | F21: Quanto mais colorido o Araknis Tricolor, maior a chance de ele estar avisando para você ficar longe. Já encontrei mais Araknis Tricolores em uma única árvore do que aventureiros sensatos em uma taverna. Apesar da fama venenosa, a maioria dos acidentes ocorre porque alguém tentou capturá-los ou esmagá-los. Diversas espécies de aves aprenderam a evitar suas cores características após experiências desagradáveis. Os filhotes nascem sem a coloração vibrante dos adultos e a desenvolvem ao longo do crescimento. Dríades costumam permitir a presença desses pequenos caçadores próximos de suas aldeias, pois ajudam a controlar pragas naturais. Durante minhas viagens encontrei mais de quarenta padrões de coloração diferentes. Provavelmente existem centenas ainda não catalogados. | G21: Besta Mágica | H21: Araknis | I21: Terra e Água | J21: Menor | K21: Minúsculo | L21: Territorial, Cauteloso e Defensivo | M21: Glândula de Veneno Tricolor Seda de Araknis Olhos Compostos Presas Venenosas Casca Quitinosa Colorida Ovos de Araknis Essência do Caçador Silencioso | N21: 1 | O21: 4 | P21: 2 | Q21: 0 | R21: 2 | S21: 36 | T21: 16 | U21: 4 | W21: 10 | X21: PRE | AA21: Teia Pegajosa (custo 1 PM, 2x por cena) - dispara teia em um alvo a 6m, que faz salv. Atletismo (CD 10) ou fica Aprisionado por 1 rodada. | AF21: 2 | AG21: 5 | AH21: 2 | AI21: 1 | AJ21: 0 | AK21: 0 | AL21: 2
A22: Araknis da Floresta Negra | B22: As teias do Araknis da Floresta Negra são famosas por dois motivos: primeiro, por serem quase invisíveis durante a noite; segundo, porque quase ninguém consegue se libertar delas sozinho. Felizmente para suas vítimas, essa criatura não tem pressa para se alimentar. Infelizmente, isso raramente melhora a situação. — Astrolong TerraNova | C22: O Araknis da Floresta Negra é uma das espécies mais conhecidas e temidas entre os habitantes das regiões sombrias do Continente das Terras Devastadas. Maior e mais robusto que os Araknis Tricolores, especializou-se na captura de presas através de enormes armadilhas de seda espalhadas pelas copas das árvores e entradas de cavernas. Diferente de muitas criaturas venenosas, seu objetivo não é matar rapidamente. Seu veneno foi desenvolvido para paralisar. Após capturar uma presa em suas teias extremamente pegajosas, o Araknis injeta uma toxina que reduz gradualmente os movimentos da vítima até que ela se torne incapaz de escapar. Somente então a criatura inicia sua alimentação. Por esse motivo, viajantes experientes consideram as teias um perigo maior que o próprio Araknis. Uma vez preso, o tempo passa a favorecer o predador. | D22: Um Araknis da Floresta Negra adulto pode atingir até um metro de comprimento, tornando-se várias vezes maior que os Araknis Tricolores. Seu corpo apresenta coloração predominantemente negra, cinza-escura ou violeta profundo, permitindo que se misture facilmente às sombras das florestas e cavernas onde habita. As patas são longas e articuladas, cobertas por pequenos pelos sensoriais capazes de detectar vibrações mínimas em suas teias. Seu abdômen é volumoso e produz grandes quantidades de seda altamente adesiva. Os olhos refletem a luz em tons esverdeados ou azulados, frequentemente sendo a única parte visível da criatura na escuridão. As presas são relativamente curtas para seu tamanho, mas especializadas na aplicação de seu veneno paralisante. Muitos indivíduos apresentam padrões semelhantes a raízes, galhos ou musgos sobre o exoesqueleto, tornando-os extremamente difíceis de identificar quando permanecem imóveis. | E22: Floresta Negra, cavernas profundas, árvores ancestrais e copas gigantescas | F22: A maior teia que encontrei media quase quinze metros entre duas árvores ancestrais. Ao contrário do que muitos acreditam, o veneno dessa espécie raramente mata. O problema é tudo o que acontece depois da paralisia. Já observei um indivíduo permanecer completamente imóvel por mais de um dia aguardando uma presa. As teias mantêm sua aderência mesmo durante chuvas intensas, característica que poucos outros Araknis possuem. Diversos predadores evitam áreas onde existem muitas teias. Nem todos desejam descobrir quem as construiu. Filhotes costumam habitar as partes mais altas das árvores gigantes antes de descerem para estabelecer seus próprios territórios. Em algumas cavernas da Floresta Negra, exploradores utilizam a quantidade de teias para estimar há quanto tempo ninguém atravessa determinada passagem. | G22: Besta Mágica | H22: Araknis | I22: Terra e Vento | J22: Menor | K22: Médio | L22: Territorial, Paciente e Predador de Emboscada | M22: Seda Negra Adesiva Glândula de Veneno Paralisante Presas de Araknis Sombrio Olhos de Caçador Noturno Quitina da Floresta Negra Casulo de Captura Essência da Emboscada Fios de Seda Reforçada | N22: 2 | O22: 3 | P22: 3 | Q22: 0 | R22: 1 | S22: 39 | T22: 15 | U22: 2 | W22: 9 | X22: PRE | AA22: Veneno Paralisante (sem custo, 1x por rodada) - mordida bem-sucedida aplica 1d6 de dano de Veneno e Lentidão por 1 rodada (CD 9, salv. Tenacidade para metade do dano e sem Lentidão). | AB22: Emboscada Silenciosa (custo 1 PM, 1x por cena) - primeiro ataque da cena causa 1d8 de dano adicional. | AF22: 2 | AG22: 4 | AH22: 0 | AI22: 0 | AJ22: 0 | AK22: 3 | AL22: 3
A23: Araknis Real | B23: Existem criaturas que os povos temem. Existem criaturas que os povos veneram. E existem criaturas que conseguem ser ambas as coisas ao mesmo tempo. O Araknis Real pertence a essa última categoria. Durante minhas viagens, ouvi histórias sobre reis, dragões e monstros. Poucas causavam tanto silêncio quanto a simples menção de Arakenis. — Astrolong TerraNova | C23: Os Araknis Reais são os maiores e mais raros representantes de toda a linhagem Araknis. Diferentemente de seus parentes menores, que ocupam árvores, cavernas e florestas comuns, os Araknis Reais escolhem apenas os locais mais isolados e sombrios do mundo. São criaturas que vivem praticamente toda a vida dentro de enormes sistemas de cavernas ou florestas tão densas que a luz do sol mal alcança o chão. Seu comportamento é peculiar. Embora sejam predadores capazes de derrotar criaturas muito maiores que eles, raramente abandonam seus territórios. Em vez disso, transformam vastas áreas em verdadeiros reinos de teias, armadilhas e túneis naturais. Tudo o que entra nesses domínios passa a ser observado. E, eventualmente, caçado. A mais famosa entre todas as espécies conhecidas é Arakenis, uma gigantesca Araknis Real venerada por diversos clãs orcs como uma entidade sagrada. Segundo as lendas, Arakenis habita as profundezas da Floresta dos Orcs há séculos, talvez milênios. Muitos acreditam que inúmeros Araknis encontrados na região descendem diretamente dela. Embora estudiosos debatam a veracidade dessas histórias, o simples fato de que tantas culturas diferentes contem versões semelhantes faz com que poucos estejam dispostos a ignorá-las. | D23: Um Araknis Real adulto pode atingir entre seis e dez metros de comprimento. Seu corpo é protegido por um exoesqueleto negro extremamente resistente, frequentemente descrito como semelhante à obsidiana polida. A coloração escura absorve quase toda a luz que atinge sua superfície, tornando difícil distinguir seus contornos mesmo quando observados diretamente. As patas são longas e poderosas, permitindo que a criatura atravesse paredes, tetos e superfícies irregulares com facilidade assustadora. Seus olhos múltiplos brilham em tons vermelhos, violetas ou azul-esverdeados quando expostos à escuridão. As presas são enormes e capazes de perfurar armaduras comuns. O abdômen produz quantidades colossais de seda negra, utilizada para construir verdadeiras fortalezas subterrâneas compostas por túneis, câmaras e armadilhas. Uma característica marcante da espécie é sua extrema aversão à luz. Araknis Reais evitam qualquer ambiente iluminado, preferindo sempre as profundezas das cavernas ou regiões onde as copas das árvores bloqueiam completamente o sol. Alguns estudiosos acreditam que sua visão seja tão adaptada à escuridão que a luz intensa lhes causa dor física. | E23: Floresta Negra, Floresta dos Orcs, cavernas profundas próximas ao Vale dos Abissais e regiões subterrâneas inexploradas | F23: Já encontrei cavernas abandonadas por aventureiros. Também encontrei cavernas abandonadas por dragões jovens. Ambas continham sinais de Araknis Reais. A quantidade de seda produzida por um único indivíduo é suficiente para cobrir uma pequena aldeia. Os Orcs contam histórias em que Arakenis observa silenciosamente gerações inteiras passarem diante de sua caverna. Nenhuma criatura que conheço aprecia menos a luz do que um Araknis Real. Uma vez encontrei uma teia tão grande que inicialmente a confundi com uma formação rochosa. Os filhotes permanecem próximos da mãe por vários anos, muito mais tempo que qualquer outra espécie de Araknis conhecida. Diversos exploradores afirmam ouvir passos gigantescos nas profundezas da Floresta Negra. Poucos permanecem tempo suficiente para confirmar a origem do som. Caso encontre uma teia tão grossa quanto o braço de um humano, considere voltar pelo mesmo caminho. O proprietário provavelmente não está longe. | G23: Besta Mágica Suprema | H23: Araknis | I23: Caóticos e Terra | J23: Lendário | K23: Enorme | L23: Territorial, Solitário e Extremamente Hostil quando perturbado | M23: Seda Real Negra Presas do Araknis Real Glândula de Veneno Superior Olhos da Escuridão Profunda Quitina Obsidiana Casulo Gigante Núcleo de Mana Sombria Essência da Rainha das Teias Coração do Araknis Real Fragmento da Seda de Arakenis Ovo da Matriarca das Teias Núcleo Ancestral de Arakenis Essência da Mãe dos Araknis | N23: 4 | O23: 4 | P23: 4 | Q23: 1 | R23: 4 | S23: 107 | T23: 21 | U23: 22 | W23: 14 | X23: PRE | AA23: Teia em Massa (custo 4 PM, 2x por cena) - teia de 9m que tenta Aprisionar até 3 criaturas na área (CD 14, salv. Atletismo). | AB23: Veneno Caótico (sem custo, 1x por rodada) - mordida bem-sucedida causa 2d8 de dano de Veneno e aplica Enfraquecido (CD 14, salv. Tenacidade para metade do dano e sem Enfraquecido). | AC23: Visão Múltipla (passivo) - não pode ser surpreendida e tem vantagem contra Furtividade. | AD23: Disparo de Cerdas (custo 3 PM, 2x por cena) - dispara cerdas venenosas em cone de 6m; criaturas na área fazem salv. Reflexo (CD 14) ou sofrem 2d8 de dano de Veneno. | AF23: 6 | AG23: 8 | AH23: 6 | AI23: 5 | AJ23: 2 | AK23: 7 | AL23: 4
A24: Cervo Élfico | B24: Se existe uma criatura capaz de representar a elegância dos reinos élficos, certamente é o Cervo Élfico. Vi guerreiros montados neles cruzarem florestas inteiras sem produzir mais ruído do que uma folha tocando o solo. São tão graciosos que até mesmo os ventos parecem respeitar sua passagem. — Astrolong TerraNova | C24: Os Cervos Élficos são uma das criaturas mais abundantes e admiradas dos Reinos Élficos. Ao longo de incontáveis gerações, desenvolveram uma relação profunda com os elfos, tornando-se não apenas companheiros de viagem, mas também símbolos vivos da harmonia entre os povos da floresta e a natureza. São utilizados como montarias, mensageiros, exploradores e, em algumas ocasiões, até mesmo como guardiões naturais de áreas sagradas. Possuem inteligência superior à maioria dos animais comuns, compreendendo comandos complexos e demonstrando grande capacidade de reconhecer indivíduos conhecidos. Apesar de sua natureza dócil, protegem ferozmente os filhotes e membros mais jovens do rebanho. Quando ameaçados, preferem fugir. Entretanto, um Cervo Alfa pode transformar-se em um adversário surpreendentemente perigoso. | D24: Os Cervos Élficos possuem corpos esguios e elegantes, adaptados para longas corridas através das florestas. Sua pelagem varia entre tons de branco-prateado, dourado-claro, castanho suave e verde-musgo, dependendo da região onde vivem. Os olhos apresentam colorações vibrantes, frequentemente azul-celeste, verde-esmeralda ou âmbar dourado. A característica mais marcante da espécie é sua galhada. Nos machos adultos, especialmente nos indivíduos Alfa, a galhada cresce em formas majestosas que lembram galhos de árvores ancestrais. Alguns exemplares desenvolvem pequenas flores, musgos ou cristais naturais entre os chifres devido à forte ligação mágica com as florestas élficas. Os Cervos Alfa possuem galhadas tão impressionantes que podem ultrapassar a largura do próprio corpo. Durante certas noites, principalmente próximas a locais feéricos, suas galhadas parecem emitir um brilho suave semelhante ao luar. | E24: Reino dos Elfos, florestas ancestrais, bosques feéricos e pradarias protegidas | F24: Nunca vi um elfo maltratar um Cervo Élfico. Considerando a reação dos demais elfos, acredito que seja uma decisão extremamente sábia. Filhotes costumam seguir aventureiros por pura curiosidade. Isso normalmente diverte os elfos e desespera os aventureiros. Os Cervos Alfa parecem escolher seus próprios sucessores. Nenhum estudioso conseguiu explicar exatamente como. Existem histórias afirmando que alguns Cervos Élficos viveram por mais de duzentos anos. Durante minhas viagens, observei um rebanho inteiro mudar de direção para permitir que uma Dríade atravessasse seu caminho. Nenhum dos lados pareceu considerar isso incomum. Quando uma floresta está em perigo, os Cervos Élficos frequentemente abandonam regiões seguras para conduzir animais menores para longe do perigo. Os elfos afirmam que é impossível montar um Cervo Élfico sem sua permissão. Após inúmeras tentativas frustradas de terceiros, estou inclinado a concordar. | G24: Besta Mágica | H24: Besta | I24: Terra e Vento | J24: Comum | K24: Médio | L24: Pacífico, Sociável e Protetor do Rebanho | M24: Galhada Élfica Pelagem Lunar Cascos da Floresta Couro Élfico Cristais de Galhada Essência da Harmonia Natural Lágrima do Guardião da Floresta Coração do Cervo Alfa | N24: 2 | O24: 3 | P24: 2 | Q24: 0 | R24: 0 | S24: 24 | T24: 14 | U24: 0 | AF24: 3 | AG24: 3 | AH24: 0 | AI24: 0 | AJ24: 0 | AK24: 0 | AL24: 1
A25: Cervo das Montanhas | B25: Enquanto os Cervos Élficos parecem ter sido moldados pela graça das florestas, os Cervos das Montanhas foram claramente esculpidos pela própria pedra. São criaturas tão majestosas quanto seus parentes dos bosques, mas carregam em seus corpos a força necessária para desafiar precipícios, nevascas e encostas onde poucas criaturas conseguem sobreviver. — Astrolong TerraNova | C25: Os Cervos das Montanhas são gigantes herbívoros que habitam as regiões elevadas do Continente Ancestral. Adaptados a terrenos íngremes, clima severo e escassez de vegetação, tornaram-se uma das criaturas mais resistentes encontradas nas grandes cadeias montanhosas do mundo. Apesar de seu tamanho impressionante, possuem temperamento tranquilo e raramente demonstram agressividade. Vivem em pequenos rebanhos liderados pelos machos mais experientes, que conduzem o grupo através de trilhas ancestrais conhecidas apenas por sua espécie. Anões e Draconianos frequentemente observam essas criaturas para prever mudanças climáticas, pois os Cervos das Montanhas possuem uma capacidade quase sobrenatural de detectar tempestades, avalanches e tremores muito antes que aconteçam. Antigamente, enormes populações habitavam as montanhas de Ignareth. Contudo, após a queda do reino e a propagação da influência do Negativo sobre aquelas terras, os rebanhos desapareceram. Oficialmente, os Cervos das Montanhas de Ignareth são considerados extintos. Ainda assim, exploradores, caçadores e até alguns Gigantes relatam avistamentos ocasionais de criaturas semelhantes vagando pelas regiões corrompidas. Se essas histórias forem verdadeiras, talvez uma nova espécie tenha surgido nas ruínas da antiga terra. Uma possibilidade que poucos estudiosos desejam investigar pessoalmente. | D25: Os Cervos das Montanhas estão entre os maiores cervídeos conhecidos do mundo. Um adulto pode atingir até cinco metros de altura dos cascos ao topo da cabeça, enquanto os indivíduos Alfa frequentemente ultrapassam esse tamanho. Seu corpo é robusto e musculoso, coberto por uma espessa pelagem cinza, marrom-escura ou branca, dependendo da região onde vive. As pernas são longas e incrivelmente fortes, permitindo que atravessem encostas quase verticais com uma facilidade impressionante. Os cascos possuem estrutura reforçada, adaptada para se fixar em pedras escorregadias e superfícies instáveis. Sua característica mais impressionante é a galhada. Muito maior e mais pesada que a dos Cervos Élficos, ela se assemelha a formações rochosas ou galhos petrificados. Em indivíduos mais velhos, líquens, musgos e até pequenos cristais podem crescer naturalmente sobre ela. Os olhos apresentam coloração dourada, âmbar ou azul-claro, refletindo os céus das montanhas onde vivem. Quando observados à distância, muitos viajantes confundem um Cervo das Montanhas imóvel com uma formação rochosa. | E25: Reino dos Anões, Reino dos Draconianos, Terras dos Gigantes e antigas montanhas de Ignareth | F25: Já vi um Cervo das Montanhas atravessar uma encosta que eu sequer conseguia olhar sem sentir vertigem. Os Anões acreditam que encontrar um desses animais durante uma viagem é sinal de proteção das montanhas. Nenhuma criatura conhece melhor os caminhos ocultos das cadeias montanhosas. Os filhotes conseguem caminhar por terrenos perigosos poucas horas após o nascimento. Caso contrário, dificilmente sobreviveriam. Existe uma antiga tradição entre os Gigantes que proíbe a caça de Cervos Alfa. Alguns Draconianos afirmam que os dragões observam essas criaturas para localizar fontes ocultas de mana nas montanhas. As histórias vindas de Ignareth me preocupam. Se realmente existem Cervos vivendo lá, suspeito que já não sejam os mesmos animais descritos nos registros antigos. Uma vez encontrei uma galhada abandonada tão grande que um grupo de anões a transformou em portal de entrada para uma fortaleza. | G25: Besta Mágica | H25: Besta | I25: Terra | J25: Menor | K25: Grande | L25: Pacífico, Vigilante e Territorial durante o período reprodutivo | M25: Galhada das Montanhas Cascos Rochosos Pelagem Alpina Couro Resistente Cristais de Galhada Ossos das Alturas Essência da Resistência Coração do Guardião dos Picos | N25: 3 | O25: 2 | P25: 3 | Q25: 0 | R25: 1 | S25: 39 | T25: 14 | U25: 2 | W25: 9 | X25: PRE | AA25: Chifrada (custo 1 PM, 1x por cena) - golpe de chifre que causa 1d8 de dano adicional e empurra o alvo 1,5m. | AF25: 5 | AG25: 0 | AH25: 4 | AI25: 0 | AJ25: 0 | AK25: 0 | AL25: 3
A26: Javali Gigante | B26: Poucas criaturas conseguem demonstrar tanta agressividade simplesmente por existirem. O Javali Gigante não procura problemas, mas parece profundamente ofendido pela presença de qualquer coisa dentro de seu território. Árvores, predadores, aventureiros e até outros javalis costumam descobrir isso da pior maneira possível. — Astrolong TerraNova | C26: Os Javalis Gigantes são uma das criaturas mais comuns das planícies e florestas dos territórios faunos. Apesar de sua abundância, poucos aventureiros os consideram presas fáceis. Sua combinação de força, resistência e temperamento explosivo transforma até mesmo um encontro casual em uma situação perigosa. Vivem em pequenos grupos familiares liderados pelas fêmeas mais velhas, enquanto machos adultos frequentemente vivem sozinhos ou vagam entre territórios durante a época reprodutiva. Quando sentem qualquer ameaça próxima, raramente hesitam. Sua reação mais comum é avançar diretamente contra o problema. Esse comportamento faz com que muitos predadores prefiram caçar outras espécies, mesmo quando os Javalis Gigantes seriam presas mais nutritivas. Entre os povos das planícies, entretanto, são extremamente valorizados por sua carne abundante e saborosa. Caçar um grande macho é considerado um rito de passagem em diversas comunidades faunas. | D26: O peso dos Javalis Gigantes varia consideravelmente. Indivíduos jovens costumam possuir cerca de 80 quilos, enquanto grandes machos podem ultrapassar facilmente os 300 quilos. Seu corpo é compacto e extremamente musculoso, sustentado por patas grossas adaptadas para corridas curtas e investidas violentas. A cabeça é grande e pesada. O focinho achatado possui musculatura poderosa capaz de escavar raízes profundas, remover pedras e até derrubar árvores jovens. As presas curvas crescem continuamente ao longo da vida e são utilizadas tanto para defesa quanto para disputas territoriais. A pelagem varia entre tons castanhos, cinzentos e negros, frequentemente coberta por lama, folhas e fragmentos de vegetação. Os ombros apresentam uma corcova muscular que concentra boa parte da força da criatura. Quando um Javali Gigante entra em disparada, poucos obstáculos naturais conseguem interromper seu avanço. | E26: Terras dos Faunos, pradarias férteis, bosques abertos, florestas temperadas e ocasionalmente o Reino dos Elfos | F26: Já observei um Javali Gigante derrubar uma árvore que três lenhadores não conseguiram cortar durante toda uma manhã. Muitos aventureiros acreditam que a parte mais perigosa da criatura são suas presas. Estão errados. A parte mais perigosa é tudo o resto. Filhotes costumam brincar de empurrar troncos caídos. Alguns desses troncos pesam mais que um humano adulto. Faunos frequentemente conseguem identificar a idade de um Javali Gigante apenas observando suas presas. Embora pareçam constantemente irritados, alguns indivíduos demonstram forte proteção pelos membros de seu grupo. Já encontrei marcas de investidas tão profundas em árvores que inicialmente pensei terem sido causadas por monstros muito maiores. Se um Javali Gigante estiver olhando para você, provavelmente está avaliando se você representa uma ameaça. Se estiver correndo em sua direção, provavelmente já decidiu que sim. | G26: Besta Mágica | H26: Besta | I26: Terra | J26: Menor | K26: Médio a Grande | L26: Territorial, Agressivo e Gregário | M26: Presas de Javali Gigante Couro Reforçado Cerdas Resistentes Cascos de Investida Ossos de Guerra Gordura de Montaria Coração do Dominador das Planícies Essência da Fúria Territorial | N26: 4 | O26: 2 | P26: 3 | Q26: 0 | R26: 0 | S26: 39 | T26: 14 | U26: 0 | AF26: 4 | AG26: 0 | AH26: 3 | AI26: 0 | AJ26: 0 | AK26: 5 | AL26: 0
A27: Javali Negro | B27: Se os Javalis Gigantes dominam as planícies, os Javalis Negros governam as florestas sombrias. Já observei um deles atravessar uma barricada de madeira construída por orcs como se fosse feita de galhos secos. Felizmente para mim, ele estava mais interessado em enfrentar uma Pantera Felina próxima do que em perseguir um explorador curioso. — Astrolong TerraNova | C27: O Javali Negro é considerado por muitos caçadores uma das criaturas mais perigosas das florestas escuras. Diferente de seus parentes das planícies, que normalmente atacam apenas para defender território, os Javalis Negros parecem possuir uma tendência natural para confrontos. São conhecidos por desafiar praticamente qualquer criatura que encontre seu caminho. Panteras Felinas, Ursos, Lobos Gigantes, Araknis e até criaturas muito maiores frequentemente entram em conflito com eles. Essa agressividade constante transformou a espécie em uma verdadeira fortaleza viva. Ao longo de gerações, apenas os indivíduos mais resistentes sobreviveram aos inúmeros combates que definem sua existência. Os Orcs respeitam profundamente esses animais. Caçar um Javali Negro adulto é considerado um feito digno de reconhecimento entre diversos clãs guerreiros. Entretanto, poucos tentam enfrentá-los diretamente. A estratégia mais comum consiste na utilização de lanças especialmente reforçadas, venenos potentes e armadilhas capazes de atingir pontos vulneráveis específicos. Mesmo assim, as caçadas frequentemente terminam com mais feridos que vencedores. | D27: Um Javali Negro adulto pode ultrapassar facilmente os 500 quilos. Seu corpo é massivo, baixo e extremamente musculoso, sustentado por patas grossas capazes de impulsionar a criatura em investidas devastadoras. Sua característica mais impressionante é a pelagem. Os pelos são grossos, rígidos e densamente compactados, formando uma camada protetora que lembra escamas metálicas. Quando observados de perto, apresentam brilho escuro semelhante ao ferro polido ou ao aço enegrecido. Muitos aventureiros inexperientes descobrem tarde demais que golpes mal direcionados podem deslizar sobre essa proteção ou até danificar armas de baixa qualidade. A pele sob os pelos é igualmente resistente, funcionando como uma segunda camada defensiva. As presas são enormes, grossas e constantemente afiadas pelo atrito durante escavações e combates. Seu focinho é mais largo que o dos Javalis Gigantes comuns, permitindo arrancar raízes, pedras e até pequenos troncos durante suas investidas. Os olhos apresentam coloração vermelha, âmbar ou dourada, transmitindo uma expressão constantemente agressiva. Diversos indivíduos carregam cicatrizes antigas provenientes de batalhas contra predadores e rivais. Entre os exemplares mais velhos, algumas cicatrizes chegam a atravessar completamente a camada de pelos reforçados. | E27: Floresta dos Orcs, Floresta Negra, bosques sombrios e regiões de vegetação densa | F27: Nunca encontrei um Javali Negro que parecesse satisfeito em evitar uma luta. Os Orcs costumam dizer que um Javali Negro não procura inimigos. Ele simplesmente considera todos candidatos. Já encontrei marcas de presas gravadas em rochas que pareciam ter sido feitas por ferramentas de mineração. Alguns indivíduos acumulam tantas cicatrizes que é possível reconstruir parte de suas vidas observando apenas seus corpos. As Panteras Felinas costumam evitar confrontos diretos com adultos saudáveis. Isso diz muito sobre ambas as espécies. Filhotes passam boa parte do crescimento lutando entre si. Estranhamente, essa parece ser uma forma de socialização. Uma vez observei um Javali Negro perseguir um Urso de Pijama Listrado. Não descobri quem venceu porque considerei prudente me afastar. Se você ouvir árvores quebrando em sequência dentro da Floresta Negra, existe uma boa chance de um Javali Negro estar atravessando a região sem se preocupar com o caminho. | G27: Besta Mágica Suprema | H27: Besta | I27: Caótico e Terra | J27: Elite | K27: Médio a Grande | L27: Extremamente Territorial, Agressivo e Belicoso | M27: Presas do Javali Negro Couraça de Pelos Metálicos Couro de Guerra Sombrio Cerdas de Aço Negro Ossos de Batalha Cascos de Investida Brutal Sangue do Sobrevivente das Florestas Essência da Fúria Indomável Coração do Senhor dos Bosques Sombrios | N27: 5 | O27: 2 | P27: 5 | Q27: 0 | R27: 2 | S27: 80 | T27: 17 | U27: 4 | W27: 10 | X27: PRE | AA27: Carga Devastadora (custo 3 PM, 2x por cena) - movimento + ataque que causa 2d8 de dano extra, empurra o alvo 3m e aplica Sangramento (CD 10, salv. Atletismo para reduzir o empurrão a 1,5m). | AB27: Pele Caótica (passivo) - resistência a dano Caótico. | AC27: Presas Caóticas (custo 2 PM, 1x por cena) - mordida que causa 2d6 de dano Caótico adicional. | AF27: 7 | AG27: 0 | AH27: 7 | AI27: 0 | AJ27: 0 | AK27: 8 | AL27: 5
A28: Orc | B28: Poucos povos são tão mal compreendidos quanto os Orcs. Muitos viajantes os enxergam apenas como guerreiros brutais, mas essa visão ignora séculos de cultura, tradições e espiritualidade. Já compartilhei refeições com tribos que me receberam como convidado de honra e também encontrei clãs que tentaram me transformar no prato principal. Como acontece com quase todos os povos inteligentes, a diferença está nos indivíduos e em suas histórias. — Astrolong TerraNova | C28: Os Orcs são uma das principais espécies humanoides do mundo. Organizam-se em tribos, clãs e confederações, cada qual com costumes próprios, territórios definidos e tradições ancestrais. Embora sejam conhecidos por sua força física, os Orcs valorizam igualmente a sabedoria dos anciãos, a liderança dos chefes e a orientação dos espíritos. A espiritualidade ocupa papel central em praticamente todas as sociedades orcs. Xamãs, guardiões espirituais e contadores de histórias são tão respeitados quanto guerreiros experientes. Muitas tribos acreditam que os espíritos dos ancestrais observam constantemente os vivos, guiando suas decisões e protegendo seus territórios. Sua relação com estrangeiros varia enormemente. Alguns clãs mantêm rotas comerciais estáveis com anões, faunos e elfos, enquanto outros enxergam qualquer intruso como uma ameaça. Por esse motivo, não existe uma única definição para o comportamento dos Orcs. Cada tribo deve ser compreendida individualmente. Apesar da fama de guerreiros, grande parte das comunidades orcs dedica-se à caça, criação de animais, coleta de recursos e preservação de conhecimentos transmitidos por gerações. | D28: Os Orcs possuem corpos robustos e musculosos, adaptados à vida em ambientes selvagens. Sua altura geralmente varia entre 1,70 e 2,10 metros, embora indivíduos excepcionais possam ultrapassar essas medidas. A pele apresenta diversas tonalidades, incluindo verde-escuro, verde-acinzentado, marrom-terroso e cinza profundo. Os dentes caninos são naturalmente maiores que os de outras espécies humanoides, projetando-se levemente para fora da boca mesmo quando fechada. Os rostos apresentam traços fortes, mandíbulas largas e sobrancelhas pronunciadas. Os cabelos costumam ser negros, castanhos escuros ou grisalhos. Muitos guerreiros utilizam pinturas corporais, cicatrizes cerimoniais, adornos feitos de ossos, presas e penas para representar conquistas, linhagem ou afiliações tribais. A maioria dos Orcs veste roupas confeccionadas com couro, peles e tecidos produzidos localmente. | E28: Floresta dos Orcs, Terras Devastadas, regiões selvagens próximas à Floresta Negra e fronteiras pouco exploradas | F28: Os Orcs possuem mais histórias sobre espíritos do que qualquer outro povo que já estudei. Muitos estrangeiros confundem a forma direta de falar dos Orcs com agressividade. Normalmente descobrem o erro depois de algumas conversas. Já vi um chefe orc interromper uma reunião importante apenas para ouvir o conselho de uma anciã da tribo. Ninguém pareceu considerar isso estranho. Diversos clãs possuem canções de guerra que também funcionam como registros históricos. Os Orcs demonstram enorme respeito por criaturas fortes da natureza. Algumas tribos veneram Arakenis, enquanto outras reverenciam grandes predadores das florestas. Poucos povos conseguem sobreviver nas Terras Devastadas tão bem quanto eles. Existe um equívoco comum de que os Orcs vivem apenas para lutar. Na verdade, a maioria prefere celebrar uma vitória do que precisar conquistá-la. A melhor refeição que provei na Floresta dos Orcs veio de uma tribo que, poucas horas antes, estava considerando me expulsar de seu território. | G28: Besta Mágica - Tribal | H28: Humanoide | I28: Arcano, Terra e Fogo. | J28: Menor | K28: Médio | L28: Tribal, Social e Variável | M28: Equipamentos Tribais Orcs Máscaras Espirituais Totens Ancestrais Amuletos Xamânicos Armas Cerimoniais Ossos Gravados dos Ancestrais Pinturas Rituais Relíquias de Clã Essência da Determinação Tribal | N28: 3 | O28: 2 | P28: 3 | Q28: 1 | R28: 0 | S28: 39 | T28: 14 | U28: 0 | AA28: Grito de Guerra (sem custo, 1x por cena) - aliados Orcs a 9m recebem vantagem no próximo ataque. | AF28: 3 | AG28: 0 | AH28: 2 | AI28: 0 | AJ28: 0 | AK28: 5 | AL28: 2
A29: Nagas | B29: Entre todos os povos que conheci, poucos guardam tantos segredos quanto os Nagas. Eles observam o mundo com a paciência de quem já viu impérios nascerem e desaparecerem. São comerciantes quando desejam, guerreiros quando necessário e guardiões de conhecimentos que raramente compartilham com estrangeiros. Muitos acreditam que os Nagas escondem tesouros antigos. Eu suspeito que os verdadeiros tesouros sejam as histórias que eles se recusam a contar. — Astrolong TerraNova | C29: Os Nagas formam um dos povos mais antigos e misteriosos conhecidos no mundo. Habitando principalmente a Ilha das Nagas e regiões estratégicas próximas às grandes rotas naturais, tornaram-se importantes intermediários entre o Continente Ancestral e o Continente das Terras Devastadas. Apesar de sua reputação reservada, os Nagas não são inerentemente hostis. Na verdade, costumam adotar uma postura neutra diante dos conflitos externos, preferindo proteger seus territórios e interesses em vez de participar de disputas entre outros povos. Essa neutralidade, porém, não deve ser confundida com passividade. Os Nagas defendem suas fronteiras com extrema eficiência e raramente toleram invasões. Sua sociedade é organizada em grandes famílias e linhagens ancestrais. A lealdade familiar é considerada uma das virtudes mais importantes de sua cultura. Trair um membro da própria família é visto como uma das maiores desonras possíveis. Além de guerreiros e caçadores habilidosos, os Nagas são conhecidos por preservarem conhecimentos antigos que remontam a períodos anteriores ao surgimento de diversos reinos modernos. Muitos estudiosos acreditam que mapas perdidos, segredos arcanos e relatos das primeiras eras estejam escondidos em seus santuários. Infelizmente, convencer um Naga a compartilhar tais informações costuma ser uma tarefa extremamente difícil. | D29: Os Nagas possuem tronco, braços e cabeça humanoides combinados com um longo corpo serpentino no lugar das pernas. Seu comprimento total geralmente varia entre três e seis metros, embora indivíduos excepcionais possam ser ainda maiores. As escamas apresentam enorme diversidade de cores, incluindo verde-esmeralda, azul-profundo, dourado, vermelho-escuro, branco-perolado e negro brilhante. Os olhos possuem pupilas verticais semelhantes às de répteis e costumam apresentar colorações intensas. Alguns indivíduos desenvolvem pequenos chifres, cristas ósseas ou adornos naturais ao redor da cabeça e do pescoço. As vestimentas variam conforme a função social, mas frequentemente incluem tecidos leves, joias metálicas, pedras preciosas e símbolos familiares. Guerreiros Nagas costumam decorar suas escamas com pigmentos minerais e marcas cerimoniais representando feitos importantes de sua linhagem. Sua movimentação é silenciosa e elegante, permitindo atravessar terrenos difíceis com surpreendente rapidez. | E29: Ilha das Nagas, regiões costeiras e rotas naturais entre o Continente Ancestral e as Terras Devastadas | F29: Os Nagas conseguem permanecer imóveis por períodos impressionantes. Em certa ocasião, confundi um ancião por uma estátua durante quase uma hora. A maioria dos mapas antigos que encontrei mencionando rotas entre continentes possuía algum símbolo associado aos Nagas. Eles raramente esquecem favores. Também raramente esquecem ofensas. Diversas famílias mantêm genealogias que remontam a dezenas de gerações. Existe um provérbio Naga que diz: 'Uma palavra dita corre mais rápido que uma serpente'. Ainda não descobri se era um conselho ou um aviso. Os jovens aprendem a nadar antes mesmo de dominarem completamente sua língua nativa. Embora pareçam reservados, as celebrações familiares Nagas podem durar vários dias. Já ouvi mais de uma vez que certos segredos sobre as Eras das Sementes permanecem guardados em bibliotecas ocultas sob a Ilha das Nagas. Curiosamente, todos os Nagas com quem conversei sobre isso sorriram e mudaram de assunto. | G29: Besta Mágica - Tribal | H29: Anfibio | I29: Arcano, Água e Vento | J29: Ameaça | K29: Médio a Grande | L29: Territorial, Familiar e Cautelosamente Neutro | M29: Escamas de Naga Presas Cerimoniais Joias Familiares Máscaras Ancestrais Relíquias de Linhagem Pergaminhos Antigos Mapas das Rotas Ocultas Totens Tribais Essência da Sabedoria Ancestral | N29: 2 | O29: 3 | P29: 2 | Q29: 2 | R29: 2 | S29: 51 | T29: 16 | U29: 10 | W29: 14 | X29: INT | AA29: Encantamento Hipnótico (custo 3 PM, 2x por cena) - o alvo a 9m faz salv. Vontade (CD 14) ou fica Desorientado por 1 rodada. | AB29: Jato de Água Pressurizada (custo 2 PM, 2x por cena) - ataque à distância que causa 2d6 de dano de Água. | AF29: 2 | AG29: 5 | AH29: 0 | AI29: 2 | AJ29: 4 | AK29: 3 | AL29: 2
A30: Gigantes | B30: Durante muitos anos acreditei que os Gigantes fossem apenas uma coleção de lendas exageradas por viajantes perdidos nas montanhas. Então encontrei uma pegada maior que uma carroça. Dias depois, descobri que a pegada pertencia a um jovem. Desde então aprendi uma lição importante: quando os Gigantes dizem que desejam ficar sozinhos, normalmente possuem tamanho suficiente para garantir isso. — Astrolong TerraNova | C30: Os Gigantes são um dos povos mais antigos ainda existentes no mundo. Habitam as vastas cadeias montanhosas ao norte do Continente das Terras Devastadas, vivendo em regiões que poucos exploradores conseguem alcançar. Ao longo de incontáveis gerações, desenvolveram uma cultura profundamente isolacionista. Diferentemente de elfos, anões ou nagas, os Gigantes não demonstram interesse por alianças, comércio ou expansão territorial. Seu objetivo é simples: Ser deixados em paz. Pouco se sabe sobre sua sociedade, pois os próprios Gigantes fazem questão de manter suas comunidades afastadas dos demais povos. Suas vilas, fortalezas e povoados permanecem escondidos em vales secretos, cavernas colossais e montanhas praticamente inacessíveis. Apesar do tamanho gigantesco, possuem extraordinário conhecimento sobre camuflagem, arquitetura natural e ocultação territorial. Muitos viajantes atravessam territórios gigantes sem sequer perceber que estão sendo observados. Embora raramente iniciem conflitos, os Gigantes não toleram invasões. Aqueles que desrespeitam seus domínios frequentemente desaparecem sem deixar vestígios. Ainda assim, relatos de confrontos diretos são raros. Os Gigantes preferem afastar intrusos antes que a violência se torne necessária. | D30: Os Gigantes possuem entre doze e dezoito metros de altura. Seu corpo é extremamente robusto, com musculatura comparável às formações rochosas das montanhas onde vivem. A pele apresenta tonalidades que variam entre cinza, marrom, azul-ardósia e tons semelhantes à pedra. Essa característica contribui para sua impressionante capacidade de se misturar ao ambiente. Seus cabelos são longos e espessos, frequentemente confundidos com musgos, raízes ou vegetação montanhosa quando observados à distância. Os olhos apresentam cores claras, normalmente azul-gelo, cinza-prateado ou âmbar profundo. As roupas são confeccionadas a partir de peles de grandes criaturas, fibras vegetais resistentes e tecidos produzidos por suas próprias comunidades. Muitos utilizam adornos feitos de cristais, pedras raras e esculturas ancestrais que representam sua linhagem familiar. Sua movimentação é surpreendentemente silenciosa para criaturas de tal tamanho. Diversos exploradores relatam que um Gigante pode permanecer praticamente invisível entre montanhas até decidir revelar sua presença. | E30: Terras dos Gigantes, montanhas do extremo norte das Terras Devastadas, vales ocultos e planaltos inacessíveis | F30: Nenhum povo conhece melhor as montanhas do que os Gigantes. Nem mesmo os Anões costumam discordar disso. A primeira vez que vi um Gigante, pensei estar observando uma formação rochosa. A formação rochosa então se levantou e começou a caminhar. Embora sejam frequentemente considerados lentos, conseguem percorrer enormes distâncias em poucas horas. Os Gigantes raramente falam com estrangeiros, mas quando falam, costumam escolher suas palavras com extremo cuidado. Existe uma crença popular de que eles não utilizam magia. Isso é falso. Apenas a utilizam de formas diferentes das demais civilizações. Muitos mapas simplesmente ignoram suas aldeias porque ninguém sabe exatamente onde elas estão. Já ouvi histórias sobre fortalezas gigantes inteiras esculpidas dentro de montanhas vivas. Infelizmente, todas as tentativas de confirmação terminaram com os Gigantes me convidando educadamente a ir embora. A maior demonstração de confiança que um Gigante pode oferecer é permitir que alguém conheça sua vila. Curiosamente, apesar de seu isolamento, os Gigantes parecem saber muito mais sobre os acontecimentos do mundo do que deveriam. | G30: Besta Mágica - Tribal | H30: Titãs | I30: Arcano, Terra e Trovão. | J30: Lendário | K30: Enorme | L30: Isolacionista, Desconfiado e Territorial | M30: Cristais das Montanhas Antigas Ferramentas Gigantes Runas dos Picos Esculturas Ancestrais Pedra Rúnica Gigante Relíquias dos Primeiros Clãs Totens das Montanhas Fragmentos de Fortaleza Gigante Essência da Montanha Eterna | N30: 5 | O30: 2 | P30: 5 | Q30: 2 | R30: 3 | S30: 110 | T30: 19 | U30: 20 | W30: 13 | X30: PRE | AA30: Golpe Sísmico (custo 4 PM, 2x por cena) - bate o solo; criaturas em 6m fazem salv. Atletismo (CD 13) ou caem e sofrem 2d8 de dano e Lentidão por 1 rodada. | AB30: Lança Titânica (passivo) - ataques com lança têm alcance +1,5m e causam +1d6 de dano contra alvos Grandes ou maiores. | AC30: Arremesso de Pedra (custo 2 PM, 2x por cena) - arremessa uma pedra a até 18m causando 2d8 de dano (CD 13, salv. Reflexo para metade). | AF30: 8 | AG30: 2 | AH30: 8 | AI30: 6 | AJ30: 2 | AK30: 8 | AL30: 4
A31: Besta Comum | B31: A maioria dos aventureiros sonha em enfrentar dragões, explorar ruínas ancestrais ou descobrir criaturas lendárias. Poucos percebem que a verdadeira base do mundo é formada pelas Bestas Comuns. Sem elas não haveria alimento, transporte, agricultura ou mesmo civilizações. São tão presentes em nosso cotidiano que muitos esquecem sua importância. — Astrolong TerraNova | C31: As Bestas Comuns representam a maior parte da fauna e da flora conhecida. Diferentemente das Bestas Mágicas e demais criaturas sobrenaturais, não possuem ligação direta com elementos, entidades ou manifestações mágicas especiais. Embora toda forma de vida contenha pequenas quantidades de mana arcana natural, as Bestas Comuns não conseguem utilizá-la de forma consciente ou sobrenatural. São responsáveis por sustentar praticamente todas as civilizações do mundo. Muitas espécies são criadas para alimentação, produção de materiais, transporte, companhia ou trabalho. Outras vivem livremente em florestas, campos, desertos, montanhas e regiões costeiras, desempenhando papéis fundamentais nos ecossistemas. Apesar de geralmente inofensivas, algumas espécies podem reagir quando acuadas ou protegendo seus filhotes. Entretanto, raramente representam perigo real para aventureiros ou caçadores experientes. Entre as espécies mais conhecidas encontram-se: Mumesas, principal fonte de leite, couro e carne para diversos povos. Hoorks, animais de montaria amplamente utilizados para transporte e viagens. Canídios, companheiros leais utilizados na guarda, caça e pastoreio. Diversas espécies de aves, roedores, répteis, insetos e pequenos herbívoros. Embora raramente recebam atenção dos estudiosos, sua importância para a sobrevivência das civilizações é incalculável. | D31: As Bestas Comuns não possuem uma aparência única. Essa categoria engloba milhares de espécies diferentes espalhadas por todos os continentes. Suas características variam conforme o ambiente onde vivem, incluindo: Pequenos roedores das florestas. - Insetos polinizadores. - Aves migratórias. - Grandes herbívoros domesticados. - Animais de carga. - Predadores de pequeno porte. - Espécies agrícolas criadas por povos civilizados. - A principal característica compartilhada por todas elas é a ausência de traços mágicos evidentes. - Não apresentam afinidades elementais, mutações sobrenaturais ou capacidades extraordinárias. São simplesmente criaturas naturais do mundo. | E31: Todo o mundo conhecido | F31: Uma cidade consegue sobreviver semanas sem aventureiros. Tente deixá-la sem Mumesas e veja o que acontece. Os Hoorks foram responsáveis por mais expedições bem-sucedidas do que qualquer herói famoso que conheço. Existe uma tendência curiosa entre estudiosos: quanto mais rara uma criatura, mais atenção ela recebe. As Bestas Comuns sustentam o mundo inteiro e quase ninguém escreve livros sobre elas. A maioria dos povos possui ao menos uma espécie de Canídio adaptada às suas necessidades. Algumas aves comuns realizam migrações entre continentes inteiros todos os anos. Nem toda criatura precisa cuspir fogo ou lançar relâmpagos para ser importante. Durante minhas viagens, percebi que a saúde de uma região costuma ser medida pela abundância de suas Bestas Comuns. Se um ecossistema perde suas criaturas mais simples, as mais extraordinárias costumam desaparecer logo depois. | G31: Besta Comum | H31: Besta | I31: Arcano | J31: Inofensivo | K31: Variável | L31: Dócil, Domesticável ou Selvagem | M31: Carne Fresca Couro Comum Ossos Chifres Lã Leite Ovos Penas Peles Gordura Animal Fibras Naturais | N31: 1 | O31: 1 | P31: 1 | Q31: 0 | R31: 1 | S31: 11 | T31: 11 | U31: 2 | W31: 9 | X31: PRE | AA31: Instinto de Fuga (sem custo, passivo) - sempre tem vantagem em testes de Reflexo para escapar de combate. | AF31: 0 | AG31: 1 | AH31: 0 | AI31: 0 | AJ31: 0 | AK31: 0 | AL31: 2
A32: Grande Serpente do Mar | B32: Durante décadas ouvi histórias sobre enormes sombras movendo-se sob navios, ondas que surgiam sem tempestades e ilhas que pareciam mudar de posição durante a noite. Eu acreditava que fossem exageros de marinheiros. Então, próximo à Ilha das Nagas, vi uma coluna de escamas emergir do oceano. Durante alguns segundos pensei estar observando uma muralha viva. Descobri depois que aquilo era apenas parte do corpo da criatura. — Astrolong TerraNova | C32: As Grandes Serpentes do Mar estão entre as maiores criaturas naturais conhecidas dos oceanos. Consideradas por muitos marinheiros como os verdadeiros reis dos mares, essas criaturas raramente são vistas e ainda mais raramente estudadas. Passam praticamente toda a vida nas profundezas oceânicas, emergindo apenas em ocasiões específicas, como migrações, reprodução ou para caçar grandes presas. Sua raridade é tamanha que muitos povos costeiros acreditam que existam apenas algumas dezenas delas em todo o mundo. Diferentemente do que dizem muitas lendas, as Grandes Serpentes do Mar não costumam atacar embarcações sem motivo. Na maioria dos casos, ignoram completamente navios e criaturas menores. Entretanto, quando provocadas ou ameaçadas, tornam-se adversários capazes de destruir embarcações inteiras com facilidade. Os Nagas possuem inúmeros mitos envolvendo essas criaturas e frequentemente as tratam com profundo respeito. Alguns estudiosos acreditam que as Grandes Serpentes do Mar habitavam os oceanos muito antes da fundação das primeiras civilizações. Sua presença costuma indicar regiões oceânicas extremamente antigas e ricas em mana elemental. | D32: Uma Grande Serpente do Mar adulta possui entre dezoito e trinta metros de comprimento. Seu corpo é longo, musculoso e hidrodinâmico, perfeitamente adaptado à vida nas profundezas. As escamas são grandes, espessas e resistentes, apresentando colorações que variam entre azul-escuro, verde-abissal, negro oceânico e tons acinzentados. Sob a luz da lua ou durante tempestades, algumas escamas refletem brilhos azulados semelhantes à superfície do mar. A cabeça é alongada, com mandíbulas poderosas capazes de engolir grandes presas inteiras. Os olhos são relativamente pequenos para o tamanho do corpo, mas extremamente adaptados à escuridão das profundezas. Ao longo do pescoço e das laterais do corpo, algumas espécies apresentam estruturas semelhantes a barbatanas ou cristas ósseas que auxiliam na navegação submarina. Quando emergem, suas dimensões são tão impressionantes que muitas vezes são confundidas com formações rochosas, recifes ou pequenas ilhas. | E32: Oceanos profundos próximos à Ilha das Nagas, mares do norte gelado, fossas oceânicas e regiões marítimas pouco exploradas | F32: A maioria das pessoas passa a vida inteira sem ver uma Grande Serpente do Mar. Muitos marinheiros experientes também. Já ouvi capitães jurarem que navegaram ao lado de uma durante horas sem perceber. Os Nagas raramente falam sobre elas. Quando falam, demonstram um respeito que se aproxima da reverência. Uma única escama encontrada em uma praia pode valer mais do que um navio inteiro. Algumas lendas afirmam que as Serpentes do Mar conhecem rotas oceânicas esquecidas até mesmo pelos Nagas. Relatos antigos descrevem indivíduos tão grandes que pareciam dividir o horizonte ao emergirem. Os pescadores das Terras Congeladas acreditam que avistar uma Grande Serpente antes de uma tempestade é um sinal de boa sorte. Nunca compreendi completamente a lógica. Certa vez observei uma sombra colossal atravessar sob minha embarcação. O mar permaneceu silencioso. Eu não. | G32: Aquático Mágico | H32: Serpente | I32: Água | J32: Lendário | K32: Enorme | L32: Solitário, Territorial e Reservado | M32: Escama da Grande Serpente Dente Abissal Olho Oceânico Presa Marinha Gigante Sangue das Profundezas Cristais de Mana Oceânica Essência do Rei dos Mares Coração da Serpente Ancestral Fragmento de Crista Abissal | N32: 4 | O32: 3 | P32: 5 | Q32: 2 | R32: 3 | S32: 110 | T32: 20 | U32: 20 | W32: 13 | X32: PRE | AA32: Constrição Oceânica (custo 4 PM, 2x por cena) - agarra um alvo, que fica Aprisionado (CD 13, salv. Atletismo) e sofre 2d8 de dano a cada rodada enquanto preso. | AB32: Maré Reversa (custo 3 PM, 1x por cena) - cria correntes que empurram criaturas em 9m (CD 13, salv. Atletismo) e causam 2d6 de dano de Água. | AC32: Jato Salgado (custo 2 PM, 2x por cena) - jato de água em linha de 12m; criaturas na linha fazem salv. Reflexo (CD 13) ou sofrem 3d8 de dano e ficam Cegas por 1 rodada. | AF32: 8 | AG32: 6 | AH32: 7 | AI32: 2 | AJ32: 2 | AK32: 7 | AL32: 6
A33: Leviatã | B33: Entre todas as criaturas que cataloguei, poucas despertam tanto temor quanto os Leviatãs. Não por serem vistos frequentemente, mas justamente pelo contrário. Um dragão pode ser encontrado. Um Gigante pode ser rastreado. Um Leviatã apenas aparece. E quando aparece, geralmente significa que algo muito maior está acontecendo. — Astrolong TerraNova | C33: Os Leviatãs são criaturas dracônicas marinhas que habitam as regiões mais profundas dos oceanos. Diferentemente das Grandes Serpentes do Mar, os Leviatãs não são considerados apenas animais extraordinários. Muitas culturas os enxergam como extensões da própria vontade dos mares. Relatos confiáveis são extremamente raros. A maioria dos registros sobre Leviatãs surge durante grandes tempestades, colapsos elementais ou manifestações associadas à Entidade da Água conhecida como O Afogado. Marinheiros, xamãs e sacerdotes afirmam que a simples aparição de um Leviatã é um presságio de mudanças profundas. Tempestades impossíveis, tsunamis, desaparecimento de ilhas, surgimento de correntes desconhecidas e distorções elementais frequentemente acompanham sua presença. Existe uma crença antiga compartilhada por Nagas, Draconianos e povos costeiros: Quando o Senhor do Silêncio surge nos mares, um Leviatã jamais está distante. Alguns acreditam que sejam guardiões. Outros acreditam que sejam servos. Há ainda aqueles que defendem uma hipótese mais preocupante: Talvez os Leviatãs sejam os próprios olhos através dos quais as Entidades observam o mundo mortal. Felizmente, avistamentos são extremamente raros. Infelizmente, raramente terminam bem. | D33: Um Leviatã adulto pode ultrapassar facilmente cinquenta metros de comprimento. Seu corpo combina características dracônicas e oceânicas em uma forma que desafia descrições precisas.A estrutura principal lembra a de um dragão ancestral alongado, coberta por escamas gigantescas que refletem tons azul-escuro, negro-abissal, verde-oceânico e prata profunda. Grandes barbatanas percorrem seu pescoço, dorso e cauda, permitindo deslocamentos impossivelmente rápidos mesmo nas profundezas mais extremas. A cabeça apresenta longos chifres curvos semelhantes a corais ancestrais. Os olhos brilham em tonalidades azuladas ou esverdeadas que parecem emitir luz própria nas regiões mais escuras dos oceanos. Alguns relatos descrevem runas luminosas surgindo entre suas escamas durante tempestades. Outros afirmam que a água ao redor do Leviatã parece obedecer à sua presença, formando correntes, redemoinhos e ondas sem qualquer explicação natural. Sua simples movimentação é capaz de alterar o comportamento do mar por quilômetros. | E33: Fossas oceânicas profundas, mares próximos às Ilhas dos Dragões, regiões abissais inexploradas e locais tocados pela influência do Afogado | F33: Nunca vi um Leviatã diretamente. E sinceramente, não tenho certeza se isso é uma decepção ou um privilégio. Os Nagas raramente mencionam essas criaturas. Quando mencionam, costumam encerrar a conversa logo depois. Existem mapas antigos marcando regiões oceânicas inteiras apenas com uma palavra: Leviatã. Diversas lendas afirmam que alguns Leviatãs são mais antigos que certos reinos. Os Draconianos acreditam que os Leviatãs compartilham uma origem distante com os Dragões Anciões. Marinheiros supersticiosos evitam pronunciar o nome da criatura durante tempestades. O Afogado é frequentemente associado ao aparecimento dos Leviatãs. Curiosamente, nenhum sacerdote da água parece disposto a explicar exatamente por quê. Se o Senhor do Silêncio e um Leviatã forem vistos na mesma região, os povos costeiros costumam abandonar suas embarcações e buscar abrigo imediatamente. A maior parte dos relatos termina com a frase: 'Então o mar começou a mudar.' | G33: Aquático Mágico Supremo | H33: Dragão | I33: Água e Sagrado | J33: Cataclísmico | K33: Colossal | L33: Desconhecido, Territorial e Vinculado a Forças Superiores | M33: Escama de Leviatã Chifre Abissal Olho das Profundezas Eternas Dente do Rei Oceânico Sangue Primordial dos Mares Cristal da Tempestade Profunda Essência do Afogado Coração de Leviatã Fragmento de Runas Oceânicas Pérola do Abismo | N33: 5 | O33: 3 | P33: 5 | Q33: 4 | R33: 5 | S33: 215 | T33: 25 | U33: 38 | W33: 21 | X33: PRE | AA33: Maremoto (custo 8 PM, 1x por cena) - onda gigante em 18m; criaturas fazem salv. Atletismo (CD 21) ou ficam Aprisionadas e sofrem 4d10 de dano de Água. | AB33: Sopro Abissal (custo 6 PM, 2x por cena) - cone de água pressurizada com 3d10 de dano (CD 21, salv. Reflexo para metade do dano e sem Lentidão). | AC33: Presença Sagrada (passivo) - aliados a 9m recebem +2 em salvaguardas contra medo e efeitos do Negativo. | AD33: Tsunami Sagrado (custo 10 PM, 1x por cena) - onda sagrada em 18m; criaturas hostis fazem salv. Vontade (CD 21) ou ficam Cegas e Amedrontadas por 2 rodadas, sofrendo 4d10 de dano Sagrado. | AF33: 10 | AG33: 10 | AH33: 10 | AI33: 10 | AJ33: 8 | AK33: 10 | AL33: 8
A34: Aquatico Comum | B34: Quando os aventureiros falam sobre os mares, costumam lembrar dos Leviatãs, Serpentes Marinhas e monstros lendários. Poucos percebem que a verdadeira riqueza dos oceanos está nas incontáveis criaturas comuns que habitam rios, lagos e mares. São elas que alimentam reinos inteiros, sustentam ecossistemas e tornam possível a vida próxima às águas. — Astrolong TerraNova | C34: A categoria Aquático Comum engloba milhares de espécies encontradas nos ambientes aquáticos do mundo. Diferentemente das criaturas aquáticas mágicas, esses seres não possuem afinidade elemental nem ligação com entidades superiores. São organismos naturais adaptados à vida na água e responsáveis por sustentar a maior parte das cadeias alimentares aquáticas. Nesta categoria encontram-se peixes de pequeno porte, cardumes migratórios, crustáceos, moluscos e espécies gigantes utilizadas como fonte de alimento por diversas civilizações. Entre as criaturas mais conhecidas está o Peixe Gigante Vermelho, uma espécie abundante nas águas frias próximas às Terras dos Gigantes e Ilhas dos Dragões. Sua carne é extremamente nutritiva e constitui a principal fonte alimentar de várias criaturas de grande porte, incluindo os famosos Ursos de Pijama Listrado. A maioria dos Aquáticos Comuns evita confrontos e dedica sua vida à alimentação, reprodução e sobrevivência. Algumas espécies podem atingir tamanhos impressionantes, mas mesmo essas raramente representam ameaça deliberada aos navegadores. | D34: Como esta categoria reúne inúmeras espécies diferentes, não existe uma aparência padrão. Os Aquáticos Comuns podem apresentar: Escamas coloridas ou discretas. Corpos alongados ou arredondados. Barbatanas adaptadas a correntes rápidas. Couraças naturais. Bigodes sensoriais. Mandíbulas especializadas. Colorações de camuflagem. Os menores indivíduos possuem apenas alguns centímetros de comprimento. Já algumas espécies gigantes podem ultrapassar cinco metros, embora continuem sendo consideradas fauna comum devido à ausência de capacidades mágicas. Muitas espécies desenvolveram adaptações específicas para seus habitats, incluindo águas congeladas, rios velozes, lagos profundos ou mares abertos. | E34: Rios, lagos, pântanos, mares costeiros, oceanos e águas subterrâneas | F34: Um pescador experiente conhece mais sobre os mares do que muitos estudiosos de biblioteca. Já encontrei peixes que brilham no escuro, mas continuam sendo classificados como Aquáticos Comuns. Nem tudo que parece mágico realmente é. O Peixe Gigante Vermelho é tão importante para algumas regiões que sua migração anual altera toda a economia local. Existem espécies que passam a vida inteira sem jamais ver a luz do sol. Os Nagas conhecem centenas de espécies que ainda não foram catalogadas por estudiosos do Continente Ancestral. Boa parte dos monstros marinhos só consegue existir porque milhares de criaturas comuns servem de alimento para eles. Alguns peixes das águas profundas possuem olhos maiores que a própria cabeça. Se os oceanos fossem privados de seus habitantes mais simples, até mesmo os Leviatãs acabariam desaparecendo. | G34: Aquático Comum | H34: Peixe | I34: Arcano | J34: Inofensivo | K34: Variável | L34: Variável | M34: Carne de Peixe Escamas Comuns Barbatanas Ovas Óleo Marinho Dentes de Predadores Aquáticos Couro de Peixes Gigantes Pérolas Naturais Conchas Raras Corais | N34: 0 | O34: 2 | P34: 1 | Q34: 0 | R34: 1 | S34: 11 | T34: 12 | U34: 2 | W34: 9 | X34: PRE | AF34: 0 | AG34: 2 | AH34: 0 | AI34: 0 | AJ34: 0 | AK34: 0 | AL34: 1
A35: Megadom | B35: Durante minha primeira viagem às águas do norte, ouvi marinheiros discutirem sobre uma sombra que acompanhava embarcações durante dias inteiros. Achei que fosse mais uma lenda criada para assustar novatos. Então encontrei um casco de navio partido ao meio. Os cortes não pareciam obra de tempestades nem de monstros comuns. Desde então, passei a levar as histórias sobre os Megadons muito mais a sério. — Astrolong TerraNova | C35: Os Megadons são considerados os maiores predadores naturais encontrados próximos à superfície dos oceanos. Embora normalmente atinjam entre oito e dez metros de comprimento, pescadores, exploradores e navegadores juram ter avistado indivíduos muito maiores vagando pelas profundezas. A veracidade desses relatos permanece incerta. Os Megadons ocupam o topo da cadeia alimentar em muitas regiões oceânicas. Alimentam-se de grandes peixes, serpentes marinhas jovens, criaturas aquáticas de médio porte e qualquer presa que demonstre sinais de fraqueza. Diferentemente das Grandes Serpentes do Mar ou dos Leviatãs, os Megadons não possuem qualquer ligação com entidades ou presságios sobrenaturais. São simplesmente predadores perfeitos. Seu nome tornou-se sinônimo de perigo entre pescadores, especialmente aqueles que trabalham longe da costa. Embarcações pequenas costumam evitar regiões conhecidas pela presença desses caçadores. Apesar da fama, ataques contra navios são relativamente raros. Os Megadons preferem presas naturais e normalmente ignoram embarcações grandes. Entretanto, um indivíduo faminto ou ferido pode se tornar extremamente imprevisível. | D35: O corpo do Megadom foi moldado para a caça. Possui forma hidrodinâmica, musculatura poderosa e uma cauda gigantesca capaz de impulsioná-lo através da água em velocidades surpreendentes. Sua pele apresenta tons de azul-escuro, cinza profundo ou negro oceânico, ajudando-o a desaparecer nas profundezas. A cabeça é larga e robusta, dominada por uma mandíbula colossal repleta de fileiras de dentes serrilhados. Cada dente possui tamanho semelhante ao de uma espada curta. Os olhos são pequenos em comparação ao restante do corpo, mas extremamente eficientes para detectar movimento. Alguns exemplares apresentam cicatrizes enormes adquiridas em confrontos contra serpentes marinhas, dragões aquáticos jovens ou outros Megadons. Quando emerge próximo à superfície, sua barbatana dorsal pode ultrapassar facilmente a altura de um humano adulto. | E35: Oceanos abertos, mares profundos, águas próximas às Ilhas dos Dragões, Terras Congeladas e regiões costeiras afastadas da civilização | F35: Existe uma diferença importante entre ouvir falar de um Megadom e ver um. A segunda experiência costuma ser muito mais curta. Pescadores afirmam que o mar fica estranhamente silencioso quando um Megadom está caçando. Já encontrei dentes fossilizados maiores do que minha mão inteira. Muitos marinheiros acreditam que os indivíduos mais antigos vivem permanentemente nas profundezas e raramente sobem à superfície. Algumas histórias falam sobre Megadons grandes o suficiente para rivalizar com pequenas serpentes marinhas. Espero sinceramente que sejam apenas histórias. Ao contrário dos Leviatãs, os Megadons não trazem presságios. Eles trazem apenas dentes. Diversas criaturas marinhas mudam suas rotas migratórias quando detectam a presença de um Megadom. O maior erro de um pescador é acreditar que está sozinho no oceano. | G35: Aquático Mágico | H35: Peixe | I35: Água | J35: Elite | K35: Grande | L35: Predador, Territorial e Solitário | M35: Dente de Megadom Mandíbula de Megadom Couro Oceânico Reforçado Barbatana Gigante Olho do Predador das Profundezas Sangue Marinho Concentrado Essência do Caçador dos Mares Vértebras Colossais Cristais Digestivos Oceânicos | N35: 4 | O35: 3 | P35: 5 | Q35: 0 | R35: 2 | S35: 80 | T35: 18 | U35: 4 | W35: 10 | X35: PRE | AA35: Mordida Trituradora (custo 3 PM, 2x por cena) - ataque que causa 2d8 de dano e aplica Sangramento, ignorando 5 pontos de Defesa (CD 10, salv. Tenacidade para sem Sangramento). | AB35: Sentido de Predador (passivo) - vantagem em Percepção para detectar presas feridas. | AC35: Arremetida Aquática (custo 2 PM, 1x por cena) - movimento rápido na água seguido de ataque que causa 2d6 de dano extra. | AF35: 7 | AG35: 5 | AH35: 5 | AI35: 0 | AJ35: 0 | AK35: 8 | AL35: 2
A36: Rei do Lago Gigante | B36: Os Orcs contam histórias para assustar filhotes sobre uma criatura que vive sob as águas do Lago do Gigante. Os Gigantes, por outro lado, falam sobre ela como um caçador fala de uma presa perigosa. Quando dois povos tão diferentes concordam que algo deve ser respeitado, considero prudente prestar atenção. — Astrolong TerraNova | C36: O Rei do Lago Gigante é uma das criaturas mais temidas do norte das Terras Devastadas. Habitando as profundezas do gigantesco Lago do Gigante, raramente é visto por completo. A maioria dos relatos descreve apenas tentáculos emergindo da água, sombras enormes movendo-se sob a superfície ou embarcações desaparecendo sem deixar vestígios. Diferentemente dos Leviatãs, que pertencem aos oceanos profundos, o Rei do Lago Gigante é uma criatura exclusivamente lacustre. Durante séculos, tornou-se parte fundamental das lendas dos Orcs e dos Gigantes. Os Orcs o enxergam como um espírito monstruoso das águas profundas, evitando navegar longe das margens. Já os Gigantes possuem uma relação diferente. Embora respeitem a criatura, ocasionalmente realizam caçadas cerimoniais contra indivíduos mais jovens, consideradas demonstrações de coragem e passagem para a vida adulta. Poucos caçadores retornam dessas expedições sem cicatrizes. A criatura permanece escondida na maior parte do tempo, emergindo principalmente durante tempestades, períodos de reprodução ou quando grandes presas atravessam seu território. Alguns estudiosos acreditam que apenas um único Rei do Lago exista por vez. Outros defendem que se trata de uma espécie inteira que simplesmente vive em regiões profundas demais para ser observada. | D36: O Rei do Lago Gigante possui um corpo massivo escondido sob a água, dificultando estimativas precisas de tamanho. Os maiores relatos sugerem indivíduos entre vinte e quarenta metros de comprimento total. Sua anatomia lembra parcialmente um gigantesco predador aquático de múltiplos tentáculos. O corpo principal é robusto, coberto por uma pele espessa azul-escura ou negra, marcada por padrões luminosos que brilham fracamente sob a água. Ao redor da boca desenvolvem-se longos tentáculos musculosos capazes de agarrar embarcações, criaturas aquáticas e até mesmo grandes animais que se aproximem da margem. Seu bico ósseo é poderoso o suficiente para partir troncos inteiros e esmagar armaduras metálicas. Os olhos são grandes, adaptados à escuridão das profundezas do lago. Durante a noite, refletem a luz como duas luas azuladas emergindo da água. Quando irritado, os padrões luminosos espalhados por seu corpo tornam-se intensamente brilhantes, iluminando parte do lago ao seu redor. | E36: Lago do Gigante, no extremo norte das Terras Devastadas, entre a Floresta dos Orcs e as Terras dos Gigantes | F36: Nunca encontrei um Orc disposto a nadar no centro do Lago do Gigante. Depois de estudar a criatura, compreendi perfeitamente o motivo. Os Gigantes afirmam que os maiores indivíduos conseguem permanecer décadas sem emergir completamente. Diversas embarcações desaparecidas foram atribuídas ao Rei do Lago, embora seja impossível confirmar todos os casos. Algumas tempestades parecem seguir os períodos de atividade da criatura. Não sei se é coincidência. As águas próximas ao centro do lago possuem profundidades ainda não mapeadas. Já ouvi histórias de tentáculos grossos como árvores ancestrais. Infelizmente, as testemunhas pareciam sinceras. Os xamãs orcs acreditam que o lago possui vontade própria e que o Rei do Lago é seu guardião. Um gigante me disse certa vez que a criatura era apenas um filhote comparada aos monstros que habitavam o mundo antigo. Preferi não perguntar mais detalhes. | G36: Aquático Mágico Supremo | H36: Peixe | I36: Água e Caótico | J36: Lendário | K36: Colossal | L36: Territorial, Predador e Solitário | M36: Tentáculo do Rei do Lago Bico Abissal Olho das Profundezas Lacustres Pele do Monarca Aquático Cristais do Fundo do Lago Essência do Guardião das Águas Sangue Arcano das Profundezas Pérola do Lago Gigante Núcleo Místico Lacustre Coração do Rei do Lago | N36: 5 | O36: 2 | P36: 5 | Q36: 2 | R36: 3 | S36: 110 | T36: 19 | U36: 20 | W36: 13 | X36: PRE | AA36: Engolir (custo 5 PM, 1x por cena) - engole um alvo de tamanho Médio ou menor (CD 13, salv. Atletismo ou fica Aprisionado e Vulnerável, sofrendo 2d8 de dano por rodada). | AB36: Onda Caótica (custo 4 PM, 2x por cena) - cria onda que empurra criaturas em 9m e causa 2d8 de dano, aplicando Enfraquecido (CD 13, salv. Atletismo para metade do dano e sem Enfraquecido). | AC36: Couro Couraçado (passivo) - redução de 3 pontos em qualquer dano recebido. | AD36: Fúria das Profundezas (custo 3 PM, 2x por cena) - ataque de cauda que causa 3d8 de dano e empurra o alvo 3m. | AF36: 8 | AG36: 4 | AH36: 8 | AI36: 2 | AJ36: 2 | AK36: 8 | AL36: 6
A37: Bogle Abissal | B37: Entre todas as criaturas inteligentes que encontrei no Vale dos Abissais, os Bogles Abissais foram os únicos que tentaram conversar antes de decidir se eu serviria como refeição. Considerando a reputação da região, considero isso um sinal de grande civilidade. — Astrolong TerraNova | C37: Os Bogles Abissais são uma das poucas sociedades organizadas ainda existentes dentro do Vale dos Abissais. Antes do Cataclisma, a região era conhecida por suas florestas exuberantes, rios cristalinos e abundante energia natural. Entretanto, as transformações que atingiram o vale alteraram profundamente sua fauna, flora e habitantes. Os Bogles sobreviveram a essas mudanças. Embora sua aparência e cultura tenham sido moldadas pelo ambiente hostil, mantiveram algo raro naquele lugar: a capacidade de dialogar. A maioria das criaturas do Vale dos Abissais ataca qualquer intruso imediatamente, tratando toda forma de vida externa como presa. Os Bogles, por outro lado, observam primeiro. Isso não significa que sejam amigáveis. Estrangeiros ainda são recebidos com extrema cautela, e qualquer demonstração de hostilidade costuma ser respondida rapidamente. Sua sociedade é organizada em tribos espalhadas pelos pântanos e cavernas do vale. Cada tribo é liderada por anciãos, caçadores experientes ou xamãs que interpretam os sinais deixados pelo próprio vale. Vivem principalmente da caça, pesca e coleta de recursos locais. Ao longo das gerações, desenvolveram uma cultura própria e uma língua única. O idioma conhecido como Abissal não possui origem conhecida entre as línguas dos povos civilizados. Muitos estudiosos acreditam que tenha surgido após o Cataclisma, evoluindo de forma isolada entre os sobreviventes da região. | D37: Os Bogles Abissais possuem aparência humanoide, mas claramente inspirada em anfíbios. Sua altura varia entre 1,50 e 2 metros. O corpo é robusto e musculoso, adaptado aos terrenos pantanosos e às encostas instáveis do vale. A pele apresenta tons de verde-escuro, azul profundo, cinza úmido ou marrom lodoso. Muitos indivíduos desenvolvem padrões naturais luminosos espalhados pelo corpo, especialmente ao redor dos olhos, pescoço e braços. Seus olhos são grandes, adaptados à baixa luminosidade das cavernas e da névoa constante do vale. As mãos e pés possuem membranas que auxiliam na locomoção em ambientes alagados. A boca larga abriga dentes pequenos, porém afiados. Vestem-se com couro de criaturas locais, fibras vegetais resistentes e ossos ornamentais obtidos durante caçadas. Os líderes tribais frequentemente utilizam máscaras feitas de crânios, madeira petrificada e cristais encontrados nas profundezas do vale. | E37: Vale dos Abissais, pântanos sombrios, cavernas úmidas e ruínas do antigo vale | F37: Os Bogles afirmam que o Vale dos Abissais está vivo. Depois de algumas semanas explorando a região, comecei a considerar essa possibilidade. A língua Abissal possui sons que lembram coaxos, estalos e vibrações difíceis de reproduzir por outras espécies. Apesar da aparência intimidadora, são excelentes pescadores. Muitas tribos mantêm mapas extremamente detalhados do vale, desenhados em couro ou pedra. Já presenciei disputas territoriais resolvidas através de desafios de caça em vez de combate direto. Os Bogles conhecem caminhos seguros pelo vale que não aparecem em nenhum mapa conhecido. Alguns anciãos alegam lembrar histórias transmitidas desde os dias anteriores ao Cataclisma. É curioso perceber que, entre tantas criaturas perigosas do vale, os Bogles são considerados os mais razoáveis. Um caçador Bogle me disse certa vez: 'Aqui tudo quer te comer. Nós apenas perguntamos seu nome primeiro.' Não consegui determinar se era uma piada. | G37: Besta Mágica - Tribal | H37: Anfibio | I37: Água e Caótico | J37: Ameaça | K37: Médio | L37: Territorial, Desconfiado e Tribal | M37: Cristais do Vale Abissal Máscaras Tribais Bogles Totens Ancestrais Ossos de Predadores do Vale Couro de Criaturas Abissais Cogumelos Raros das Profundezas Relíquias Pré-Cataclisma Mapas Secretos do Vale Essência da Névoa Abissal | N37: 2 | O37: 3 | P37: 2 | Q37: 1 | R37: 3 | S37: 51 | T37: 16 | U37: 12 | W37: 14 | X37: PRE | AA37: Maré Caótica (custo 3 PM, 2x por cena) - onda de energia caótica em alvo único, causando 2d6 de dano e Enfraquecido (CD 14, salv. Vontade para metade do dano e sem Enfraquecido). | AB37: Borrifo Ácido (custo 2 PM, 2x por cena) - cone de 6m de ácido caótico; criaturas na área fazem salv. Reflexo (CD 14) ou sofrem 1d8 de dano Caótico. | AF37: 2 | AG37: 5 | AH37: 0 | AI37: 3 | AJ37: 3 | AK37: 3 | AL37: 2
